[{"Timestamp":7.86461449,"Name":"RoundStart","Data":{"gameCount":1}},{"Timestamp":8.71836948,"Name":"TowerBuilding","Data":{"tower":"Plasma Lance","X":0,"Y":0}},{"Timestamp":8.719517,"Name":"UnitBuying","Data":{"unitBought":"Hoverbuggy","currentIncome":1}},{"Timestamp":10.1682043,"Name":"TowerBuilding","Data":{"tower":"Plasma Lance","X":4,"Y":0}},{"Timestamp":10.168231,"Name":"UnitBuying","Data":{"unitBought":"Hoverbuggy","currentIncome":2}},{"Timestamp":10.3289318,"Name":"TowerBuilding","Data":{"tower":"Plasma Lance","X":1,"Y":1}},{"Timestamp":10.328949,"Name":"UnitBuying","Data":{"unitBought":"Hoverbuggy","currentIncome":3}},{"Timestamp":10.4950275,"Name":"UnitBuying","Data":{"unitBought":"Hoverbuggy","currentIncome":4}},{"Timestamp":10.6584759,"Name":"UnitBuying","Data":{"unitBought":"Hovercopter","currentIncome":6}},{"Timestamp":10.8223076,"Name":"UnitBuying","Data":{"unitBought":"Hoverbuggy","currentIncome":7}},{"Timestamp":10.9883184,"Name":"UnitBuying","Data":{"unitBought":"Hoverbuggy","currentIncome":8}},{"Timestamp":11.1557932,"Name":"UnitBuying","Data":{"unitBought":"Hoverbuggy","currentIncome":9}},{"Timestamp":11.3161745,"Name":"UnitBuying","Data":{"unitBought":"Hoverbuggy","currentIncome":10}},{"Timestamp":11.4823341,"Name":"UnitBuying","Data":{"unitBought":"Hoverbuggy","currentIncome":11}},{"Timestamp":11.6478891,"Name":"UnitBuying","Data":{"unitBought":"Hoverbuggy","currentIncome":12}},{"Timestamp":11.8093672,"Name":"UnitBuying","Data":{"unitBought":"Hovercopter","currentIncome":14}},{"Timestamp":11.9788046,"Name":"UnitBuying","Data":{"unitBought":"Hoverbuggy","currentIncome":15}},{"Timestamp":12.1423445,"Name":"UnitBuying","Data":{"unitBought":"Hovercopter","currentIncome":17}},{"Timestamp":12.3048086,"Name":"UnitBuying","Data":{"unitBought":"Hovercopter","currentIncome":19}},{"Timestamp":12.4734192,"Name":"UnitBuying","Data":{"unitBought":"Hoverbuggy","currentIncome":20}},{"Timestamp":14.300333,"Name":"UnitSpawn","Data":{"unitSpawned":"Hoverbuggy","unitCount":1}},{"Timestamp":14.5872374,"Name":"UnitDamage","Data":{"unit":"Hoverbuggy(Clone)","damage":12.0,"hp":6.0,"attacker":"Plasma Lance"}},{"Timestamp":14.5879612,"Name":"UnitDeath","Data":{"unit":"Hoverbuggy(Clone)","overkillDamage":6.0,"killTower":"Plasma Lance"}},{"Timestamp":14.9673281,"Name":"Economy","Data":{"team":"Defender","currency":1.0,"income":0.0}},{"Timestamp":14.96759,"Name":"Economy","Data":{"team":"Attacker","currency":20.0,"income":20.0}},{"Timestamp":15.1113272,"Name":"UnitBuying","Data":{"unitBought":"Hovercopter","currentIncome":22}},{"Timestamp":15.4391012,"Name":"UnitBuying","Data":{"unitBought":"Hovercopter","currentIncome":24}},{"Timestamp":16.30267,"Name":"UnitSpawn","Data":{"unitSpawned":"Hoverbuggy","unitCount":2}},{"Timestamp":16.8818722,"Name":"UnitDamage","Data":{"unit":"Hoverbuggy(Clone)","damage":12.0,"hp":6.0,"attacker":"Plasma Lance"}},{"Timestamp":16.8818913,"Name":"UnitDeath","Data":{"unit":"Hoverbuggy(Clone)","overkillDamage":6.0,"killTower":"Plasma Lance"}},{"Timestamp":18.305563,"Name":"UnitSpawn","Data":{"unitSpawned":"Hoverbuggy","unitCount":3}},{"Timestamp":18.5927639,"Name":"UnitDamage","Data":{"unit":"Hoverbuggy(Clone)","damage":12.0,"hp":6.0,"attacker":"Plasma Lance"}},{"Timestamp":18.5927811,"Name":"UnitDeath","Data":{"unit":"Hoverbuggy(Clone)","overkillDamage":6.0,"killTower":"Plasma Lance"}},{"Timestamp":19.9716587,"Name":"Economy","Data":{"team":"Defender","currency":3.0,"income":0.0}},{"Timestamp":19.9716663,"Name":"Economy","Data":{"team":"Attacker","currency":24.0,"income":24.0}},{"Timestamp":20.0609837,"Name":"UnitBuying","Data":{"unitBought":"Hoverbuggy","currentIncome":25}},{"Timestamp":20.2237015,"Name":"UnitBuying","Data":{"unitBought":"Hovercopter","currentIncome":27}},{"Timestamp":20.3066311,"Name":"UnitSpawn","Data":{"unitSpawned":"Hoverbuggy","unitCount":4}},{"Timestamp":20.8445358,"Name":"UnitDamage","Data":{"unit":"Hoverbuggy(Clone)","damage":12.0,"hp":6.0,"attacker":"Plasma Lance"}},{"Timestamp":20.84455,"Name":"UnitDeath","Data":{"unit":"Hoverbuggy(Clone)","overkillDamage":6.0,"killTower":"Plasma Lance"}},{"Timestamp":22.3101768,"Name":"UnitSpawn","Data":{"unitSpawned":"Hovercopter","unitCount":5}},{"Timestamp":22.58432,"Name":"UnitDamage","Data":{"unit":"Hovercopter(Clone)","damage":12.0,"hp":16.0,"attacker":"Plasma Lance"}},{"Timestamp":23.6936855,"Name":"UnitDamage","Data":{"unit":"Hovercopter(Clone)","damage":12.0,"hp":4.0,"attacker":"Plasma Lance"}},{"Timestamp":23.6937,"Name":"UnitDeath","Data":{"unit":"Hovercopter(Clone)","overkillDamage":8.0,"killTower":"Plasma Lance"}},{"Timestamp":24.315773,"Name":"UnitSpawn","Data":{"unitSpawned":"Hoverbuggy","unitCount":6}},{"Timestamp":24.6176376,"Name":"UnitDamage","Data":{"unit":"Hoverbuggy(Clone)","damage":12.0,"hp":6.0,"attacker":"Plasma Lance"}},{"Timestamp":24.6176567,"Name":"UnitDeath","Data":{"unit":"Hoverbuggy(Clone)","overkillDamage":6.0,"killTower":"Plasma Lance"}},{"Timestamp":24.9769058,"Name":"Economy","Data":{"team":"Defender","currency":7.0,"income":0.0}},{"Timestamp":24.9769154,"Name":"Economy","Data":{"team":"Attacker","currency":36.0,"income":27.0}},{"Timestamp":25.01324,"Name":"TowerBuilding","Data":{"tower":"Assault Cannon","X":2,"Y":0}},{"Timestamp":25.0132542,"Name":"UnitBuying","Data":{"unitBought":"Hovercopter","currentIncome":29}},{"Timestamp":25.175106,"Name":"UnitBuying","Data":{"unitBought":"Hovercopter","currentIncome":31}},{"Timestamp":25.3428421,"Name":"UnitBuying","Data":{"unitBought":"Hovercopter","currentIncome":33}},{"Timestamp":26.332037,"Name":"UnitSpawn","Data":{"unitSpawned":"Hoverbuggy","unitCount":7}},{"Timestamp":26.6114979,"Name":"UnitDamage","Data":{"unit":"Hoverbuggy(Clone)","damage":12.0,"hp":6.0,"attacker":"Plasma Lance"}},{"Timestamp":26.61153,"Name":"UnitDeath","Data":{"unit":"Hoverbuggy(Clone)","overkillDamage":6.0,"killTower":"Plasma Lance"}},{"Timestamp":28.3216381,"Name":"UnitSpawn","Data":{"unitSpawned":"Hoverbuggy","unitCount":8}},{"Timestamp":28.9911556,"Name":"UnitDamage","Data":{"unit":"Hoverbuggy(Clone)","damage":12.0,"hp":6.0,"attacker":"Plasma Lance"}},{"Timestamp":28.991169,"Name":"UnitDeath","Data":{"unit":"Hoverbuggy(Clone)","overkillDamage":6.0,"killTower":"Plasma Lance"}},{"Timestamp":29.98092,"Name":"Economy","Data":{"team":"Defender","currency":2.0,"income":0.0}},{"Timestamp":29.9809341,"Name":"Economy","Data":{"team":"Attacker","currency":39.0,"income":33.0}},{"Timestamp":30.1240826,"Name":"UnitBuying","Data":{"unitBought":"Hovercopter","currentIncome":35}},{"Timestamp":30.2898026,"Name":"UnitBuying","Data":{"unitBought":"Hovertank","currentIncome":39}},{"Timestamp":30.32465,"Name":"UnitSpawn","Data":{"unitSpawned":"Hoverbuggy","unitCount":9}},{"Timestamp":30.6063786,"Name":"UnitDamage","Data":{"unit":"Hoverbuggy(Clone)","damage":12.0,"hp":6.0,"attacker":"Plasma Lance"}},{"Timestamp":30.6064034,"Name":"UnitDeath","Data":{"unit":"Hoverbuggy(Clone)","overkillDamage":6.0,"killTower":"Plasma Lance"}},{"Timestamp":32.33169,"Name":"UnitSpawn","Data":{"unitSpawned":"Hoverbuggy","unitCount":10}},{"Timestamp":32.6236572,"Name":"UnitDamage","Data":{"unit":"Hoverbuggy(Clone)","damage":12.0,"hp":6.0,"attacker":"Plasma Lance"}},{"Timestamp":32.6236725,"Name":"UnitDeath","Data":{"unit":"Hoverbuggy(Clone)","overkillDamage":6.0,"killTower":"Plasma Lance"}},{"Timestamp":34.3333321,"Name":"UnitSpawn","Data":{"unitSpawned":"Hoverbuggy","unitCount":11}},{"Timestamp":34.60359,"Name":"UnitDamage","Data":{"unit":"Hoverbuggy(Clone)","damage":12.0,"hp":6.0,"attacker":"Plasma Lance"}},{"Timestamp":34.6036034,"Name":"UnitDeath","Data":{"unit":"Hoverbuggy(Clone)","overkillDamage":6.0,"killTower":"Plasma Lance"}},{"Timestamp":34.986454,"Name":"Economy","Data":{"team":"Defender","currency":5.0,"income":0.0}},{"Timestamp":34.98647,"Name":"Economy","Data":{"team":"Attacker","currency":41.0,"income":39.0}},{"Timestamp":35.0789452,"Name":"UnitBuying","Data":{"unitBought":"Hovercopter","currentIncome":41}},{"Timestamp":35.2416878,"Name":"UnitBuying","Data":{"unitBought":"Hovertank","currentIncome":45}},{"Timestamp":36.3357773,"Name":"UnitSpawn","Data":{"unitSpawned":"Hovercopter","unitCount":12}},{"Timestamp":37.0559769,"Name":"UnitDamage","Data":{"unit":"Hovercopter(Clone)","damage":12.0,"hp":16.0,"attacker":"Plasma Lance"}},{"Timestamp":37.9160423,"Name":"UnitDamage","Data":{"unit":"Hovercopter(Clone)","damage":0.25,"hp":4.0,"attacker":"Assault Cannon"}},{"Timestamp":37.9423981,"Name":"UnitDamage","Data":{"unit":"Hovercopter(Clone)","damage":12.0,"hp":3.75,"attacker":"Plasma Lance"}},{"Timestamp":37.9424171,"Name":"UnitDeath","Data":{"unit":"Hovercopter(Clone)","overkillDamage":8.25,"killTower":"Plasma Lance"}},{"Timestamp":38.0694656,"Name":"UnitDamage","Data":{"unit":"Hovercopter(Clone)","damage":12.0,"hp":0.0,"attacker":"Plasma Lance"}},{"Timestamp":38.3418541,"Name":"UnitSpawn","Data":{"unitSpawned":"Hoverbuggy","unitCount":13}},{"Timestamp":38.71154,"Name":"TowerBuilding","Data":{"tower":"Assault Cannon","X":5,"Y":0}},{"Timestamp":39.39062,"Name":"UnitDamage","Data":{"unit":"Hoverbuggy(Clone)","damage":0.25,"hp":6.0,"attacker":"Assault Cannon"}},{"Timestamp":39.64406,"Name":"UnitDamage","Data":{"unit":"Hoverbuggy(Clone)","damage":0.25,"hp":5.75,"attacker":"Assault Cannon"}},{"Timestamp":39.896347,"Name":"UnitDamage","Data":{"unit":"Hoverbuggy(Clone)","damage":0.25,"hp":5.5,"attacker":"Assault Cannon"}},{"Timestamp":39.9942551,"Name":"Economy","Data":{"team":"Defender","currency":0.0,"income":0.0}},{"Timestamp":39.99427,"Name":"Economy","Data":{"team":"Attacker","currency":49.0,"income":45.0}},{"Timestamp":40.00094,"Name":"UnitDamage","Data":{"unit":"Hoverbuggy(Clone)","damage":0.25,"hp":5.25,"attacker":"Assault Cannon"}},{"Timestamp":40.0276146,"Name":"UnitBuying","Data":{"unitBought":"Hovertank","currentIncome":49}},{"Timestamp":40.1507568,"Name":"UnitDamage","Data":{"unit":"Hoverbuggy(Clone)","damage":0.25,"hp":5.0,"attacker":"Assault Cannon"}},{"Timestamp":40.19162,"Name":"UnitBuying","Data":{"unitBought":"Hovercopter","currentIncome":51}},{"Timestamp":40.25302,"Name":"UnitDamage","Data":{"unit":"Hoverbuggy(Clone)","damage":0.25,"hp":4.75,"attacker":"Assault Cannon"}},{"Timestamp":40.3432541,"Name":"UnitSpawn","Data":{"unitSpawned":"Hovercopter","unitCount":14}},{"Timestamp":40.3878822,"Name":"UnitDamage","Data":{"unit":"Hoverbuggy(Clone)","damage":12.0,"hp":4.5,"attacker":"Plasma Lance"}},{"Timestamp":40.3879051,"Name":"UnitDeath","Data":{"unit":"Hoverbuggy(Clone)","overkillDamage":7.5,"killTower":"Plasma Lance"}},{"Timestamp":40.41302,"Name":"UnitDamage","Data":{"unit":"Hoverbuggy(Clone)","damage":0.25,"hp":0.0,"attacker":"Assault Cannon"}},{"Timestamp":40.5272675,"Name":"UnitBuying","Data":{"unitBought":"Hovercopter","currentIncome":53}},{"Timestamp":41.27962,"Name":"UnitDamage","Data":{"unit":"Hovercopter(Clone)","damage":12.0,"hp":16.0,"attacker":"Plasma Lance"}},{"Timestamp":41.8764534,"Name":"UnitDamage","Data":{"unit":"Hovercopter(Clone)","damage":0.25,"hp":4.0,"attacker":"Assault Cannon"}},{"Timestamp":42.0156174,"Name":"UnitDamage","Data":{"unit":"Hovercopter(Clone)","damage":12.0,"hp":3.75,"attacker":"Plasma Lance"}},{"Timestamp":42.0156326,"Name":"UnitDeath","Data":{"unit":"Hovercopter(Clone)","overkillDamage":8.25,"killTower":"Plasma Lance"}},{"Timestamp":42.3480721,"Name":"UnitSpawn","Data":{"unitSpawned":"Hovercopter","unitCount":15}},{"Timestamp":43.7135124,"Name":"UnitDamage","Data":{"unit":"Hovercopter(Clone)","damage":12.0,"hp":16.0,"attacker":"Plasma Lance"}},{"Timestamp":44.1033478,"Name":"UnitDamage","Data":{"unit":"Hovercopter(Clone)","damage":0.25,"hp":4.0,"attacker":"Assault Cannon"}},{"Timestamp":44.3521156,"Name":"UnitDamage","Data":{"unit":"Hovercopter(Clone)","damage":0.25,"hp":3.75,"attacker":"Assault Cannon"}},{"Timestamp":44.3682632,"Name":"UnitSpawn","Data":{"unitSpawned":"Hoverbuggy","unitCount":16}},{"Timestamp":44.60597,"Name":"UnitDamage","Data":{"unit":"Hovercopter(Clone)","damage":0.25,"hp":3.5,"attacker":"Assault Cannon"}},{"Timestamp":44.61449,"Name":"UnitDamage","Data":{"unit":"Hovercopter(Clone)","damage":12.0,"hp":3.25,"attacker":"Plasma Lance"}},{"Timestamp":44.6145058,"Name":"UnitDeath","Data":{"unit":"Hovercopter(Clone)","overkillDamage":8.75,"killTower":"Plasma Lance"}},{"Timestamp":44.9979858,"Name":"Economy","Data":{"team":"Defender","currency":5.0,"income":0.0}},{"Timestamp":44.9980049,"Name":"Economy","Data":{"team":"Attacker","currency":55.0,"income":53.0}},{"Timestamp":45.1400452,"Name":"UnitBuying","Data":{"unitBought":"Hovercopter","currentIncome":55}},{"Timestamp":45.2504044,"Name":"UnitDamage","Data":{"unit":"Hoverbuggy(Clone)","damage":0.25,"hp":6.0,"attacker":"Assault Cannon"}},{"Timestamp":45.30467,"Name":"UnitBuying","Data":{"unitBought":"Hoverbuggy","currentIncome":56}},{"Timestamp":45.4008522,"Name":"UnitDamage","Data":{"unit":"Hoverbuggy(Clone)","damage":12.0,"hp":5.75,"attacker":"Plasma Lance"}},{"Timestamp":45.40087,"Name":"UnitDeath","Data":{"unit":"Hoverbuggy(Clone)","overkillDamage":6.25,"killTower":"Plasma Lance"}},{"Timestamp":45.4729919,"Name":"UnitBuying","Data":{"unitBought":"Hovercopter","currentIncome":58}},{"Timestamp":45.5036354,"Name":"UnitDamage","Data":{"unit":"Hoverbuggy(Clone)","damage":0.25,"hp":0.0,"attacker":"Assault Cannon"}},{"Timestamp":45.63589,"Name":"UnitBuying","Data":{"unitBought":"Hovercopter","currentIncome":60}},{"Timestamp":45.8058128,"Name":"UnitBuying","Data":{"unitBought":"Hovercopter","currentIncome":62}},{"Timestamp":45.9743538,"Name":"UnitBuying","Data":{"unitBought":"Hovercopter","currentIncome":64}},{"Timestamp":46.3718948,"Name":"UnitSpawn","Data":{"unitSpawned":"Hovercopter","unitCount":17}},{"Timestamp":47.0767365,"Name":"UnitDamage","Data":{"unit":"Hovercopter(Clone)","damage":12.0,"hp":16.0,"attacker":"Plasma Lance"}},{"Timestamp":47.96022,"Name":"UnitDamage","Data":{"unit":"Hovercopter(Clone)","damage":12.0,"hp":4.0,"attacker":"Plasma Lance"}},{"Timestamp":47.96024,"Name":"UnitDeath","Data":{"unit":"Hovercopter(Clone)","overkillDamage":8.0,"killTower":"Plasma Lance"}},{"Timestamp":47.9831657,"Name":"UnitDamage","Data":{"unit":"Hovercopter(Clone)","damage":0.25,"hp":0.0,"attacker":"Assault Cannon"}},{"Timestamp":48.3780441,"Name":"UnitSpawn","Data":{"unitSpawned":"Hovercopter","unitCount":18}},{"Timestamp":48.7708473,"Name":"TowerBuilding","Data":{"tower":"Assault Cannon","X":3,"Y":0}},{"Timestamp":49.9602,"Name":"UnitDamage","Data":{"unit":"Hovercopter(Clone)","damage":0.25,"hp":16.0,"attacker":"Assault Cannon"}},{"Timestamp":50.002037,"Name":"Economy","Data":{"team":"Defender","currency":1.0,"income":0.0}},{"Timestamp":50.00205,"Name":"Economy","Data":{"team":"Attacker","currency":64.0,"income":64.0}},{"Timestamp":50.09033,"Name":"UnitBuying","Data":{"unitBought":"Hovertank","currentIncome":68}},{"Timestamp":50.0908623,"Name":"UnitDamage","Data":{"unit":"Hovercopter(Clone)","damage":12.0,"hp":15.75,"attacker":"Plasma Lance"}},{"Timestamp":50.2154846,"Name":"UnitDamage","Data":{"unit":"Hovercopter(Clone)","damage":0.25,"hp":3.75,"attacker":"Assault Cannon"}},{"Timestamp":50.25694,"Name":"UnitBuying","Data":{"unitBought":"Hovercopter","currentIncome":70}},{"Timestamp":50.29326,"Name":"UnitDamage","Data":{"unit":"Hovercopter(Clone)","damage":0.25,"hp":3.5,"attacker":"Assault Cannon"}},{"Timestamp":50.37862,"Name":"UnitSpawn","Data":{"unitSpawned":"Hoverbuggy","unitCount":19}},{"Timestamp":50.4254837,"Name":"UnitBuying","Data":{"unitBought":"Hovercopter","currentIncome":72}},{"Timestamp":50.4262924,"Name":"UnitDamage","Data":{"unit":"Hovercopter(Clone)","damage":12.0,"hp":3.25,"attacker":"Plasma Lance"}},{"Timestamp":50.4263039,"Name":"UnitDeath","Data":{"unit":"Hovercopter(Clone)","overkillDamage":8.75,"killTower":"Plasma Lance"}},{"Timestamp":50.4639435,"Name":"UnitDamage","Data":{"unit":"Hovercopter(Clone)","damage":0.25,"hp":0.0,"attacker":"Assault Cannon"}},{"Timestamp":50.5877724,"Name":"UnitBuying","Data":{"unitBought":"Hovercopter","currentIncome":74}},{"Timestamp":51.32903,"Name":"UnitDamage","Data":{"unit":"Hoverbuggy(Clone)","damage":12.0,"hp":6.0,"attacker":"Plasma Lance"}},{"Timestamp":51.3290443,"Name":"UnitDeath","Data":{"unit":"Hoverbuggy(Clone)","overkillDamage":6.0,"killTower":"Plasma Lance"}},{"Timestamp":52.38247,"Name":"UnitSpawn","Data":{"unitSpawned":"Hovercopter","unitCount":20}},{"Timestamp":53.59421,"Name":"UnitDamage","Data":{"unit":"Hovercopter(Clone)","damage":0.25,"hp":16.0,"attacker":"Assault Cannon"}},{"Timestamp":53.7404175,"Name":"UnitDamage","Data":{"unit":"Hovercopter(Clone)","damage":12.0,"hp":15.75,"attacker":"Plasma Lance"}},{"Timestamp":53.7502022,"Name":"UnitDamage","Data":{"unit":"Hovercopter(Clone)","damage":12.0,"hp":3.75,"attacker":"Plasma Lance"}},{"Timestamp":53.7502174,"Name":"UnitDeath","Data":{"unit":"Hovercopter(Clone)","overkillDamage":8.25,"killTower":"Plasma Lance"}},{"Timestamp":53.8435555,"Name":"UnitDamage","Data":{"unit":"Hovercopter(Clone)","damage":0.25,"hp":0.0,"attacker":"Assault Cannon"}},{"Timestamp":54.38936,"Name":"UnitSpawn","Data":{"unitSpawned":"Hovercopter","unitCount":21}},{"Timestamp":54.6670723,"Name":"UnitDamage","Data":{"unit":"Hovercopter(Clone)","damage":12.0,"hp":16.0,"attacker":"Plasma Lance"}},{"Timestamp":55.00389,"Name":"Economy","Data":{"team":"Defender","currency":6.0,"income":0.0}},{"Timestamp":55.0039024,"Name":"Economy","Data":{"team":"Attacker","currency":81.0,"income":74.0}},{"Timestamp":55.04019,"Name":"UnitBuying","Data":{"unitBought":"Hoverbuggy","currentIncome":75}},{"Timestamp":55.20636,"Name":"UnitBuying","Data":{"unitBought":"Hovercopter","currentIncome":77}},{"Timestamp":55.37481,"Name":"UnitBuying","Data":{"unitBought":"Hovercopter","currentIncome":79}},{"Timestamp":55.54218,"Name":"UnitBuying","Data":{"unitBought":"Hovertank","currentIncome":83}},{"Timestamp":55.70095,"Name":"UnitBuying","Data":{"unitBought":"Hovercopter","currentIncome":85}},{"Timestamp":55.93691,"Name":"UnitDamage","Data":{"unit":"Hovercopter(Clone)","damage":0.25,"hp":4.0,"attacker":"Assault Cannon"}},{"Timestamp":56.20117,"Name":"UnitDamage","Data":{"unit":"Hovercopter(Clone)","damage":0.25,"hp":3.75,"attacker":"Assault Cannon"}},{"Timestamp":56.26015,"Name":"UnitDamage","Data":{"unit":"Hovercopter(Clone)","damage":0.25,"hp":3.5,"attacker":"Assault Cannon"}},{"Timestamp":56.39158,"Name":"UnitSpawn","Data":{"unitSpawned":"Hovercopter","unitCount":22}},{"Timestamp":56.4430847,"Name":"UnitDamage","Data":{"unit":"Hovercopter(Clone)","damage":0.25,"hp":3.25,"attacker":"Assault Cannon"}},{"Timestamp":56.5262,"Name":"UnitDamage","Data":{"unit":"Hovercopter(Clone)","damage":0.25,"hp":3.0,"attacker":"Assault Cannon"}},{"Timestamp":56.6987038,"Name":"UnitDamage","Data":{"unit":"Hovercopter(Clone)","damage":0.25,"hp":2.75,"attacker":"Assault Cannon"}},{"Timestamp":56.76489,"Name":"UnitDamage","Data":{"unit":"Hovercopter(Clone)","damage":0.25,"hp":2.5,"attacker":"Assault Cannon"}},{"Timestamp":56.9464455,"Name":"UnitDamage","Data":{"unit":"Hovercopter(Clone)","damage":0.25,"hp":2.25,"attacker":"Assault Cannon"}},{"Timestamp":56.9691658,"Name":"UnitDamage","Data":{"unit":"Hovercopter(Clone)","damage":0.25,"hp":2.0,"attacker":"Assault Cannon"}},{"Timestamp":57.0341949,"Name":"UnitDamage","Data":{"unit":"Hovercopter(Clone)","damage":0.25,"hp":1.75,"attacker":"Assault Cannon"}},{"Timestamp":57.0726776,"Name":"UnitDamage","Data":{"unit":"Hovercopter(Clone)","damage":12.0,"hp":1.5,"attacker":"Plasma Lance"}},{"Timestamp":57.07269,"Name":"UnitDeath","Data":{"unit":"Hovercopter(Clone)","overkillDamage":10.5,"killTower":"Plasma Lance"}},{"Timestamp":57.0811844,"Name":"UnitDamage","Data":{"unit":"Hovercopter(Clone)","damage":12.0,"hp":0.0,"attacker":"Plasma Lance"}},{"Timestamp":57.9550438,"Name":"UnitDamage","Data":{"unit":"Hovercopter(Clone)","damage":0.25,"hp":16.0,"attacker":"Assault Cannon"}},{"Timestamp":58.0115356,"Name":"UnitDamage","Data":{"unit":"Hovercopter(Clone)","damage":12.0,"hp":15.75,"attacker":"Plasma Lance"}},{"Timestamp":58.21361,"Name":"UnitDamage","Data":{"unit":"Hovercopter(Clone)","damage":0.25,"hp":3.75,"attacker":"Assault Cannon"}},{"Timestamp":58.3090744,"Name":"UnitDamage","Data":{"unit":"Hovercopter(Clone)","damage":0.25,"hp":3.5,"attacker":"Assault Cannon"}},{"Timestamp":58.3933067,"Name":"UnitSpawn","Data":{"unitSpawned":"Hovercopter","unitCount":23}},{"Timestamp":58.46492,"Name":"UnitDamage","Data":{"unit":"Hovercopter(Clone)","damage":0.25,"hp":3.25,"attacker":"Assault Cannon"}},{"Timestamp":58.56308,"Name":"UnitDamage","Data":{"unit":"Hovercopter(Clone)","damage":0.25,"hp":3.0,"attacker":"Assault Cannon"}},{"Timestamp":58.72023,"Name":"UnitDamage","Data":{"unit":"Hovercopter(Clone)","damage":0.25,"hp":2.75,"attacker":"Assault Cannon"}},{"Timestamp":58.81496,"Name":"UnitDamage","Data":{"unit":"Hovercopter(Clone)","damage":0.25,"hp":2.5,"attacker":"Assault Cannon"}},{"Timestamp":58.97481,"Name":"UnitDamage","Data":{"unit":"Hovercopter(Clone)","damage":0.25,"hp":2.25,"attacker":"Assault Cannon"}},{"Timestamp":59.00424,"Name":"TowerBuilding","Data":{"tower":"Assault Cannon","X":3,"Y":1}},{"Timestamp":59.03646,"Name":"UnitDamage","Data":{"unit":"Hovercopter(Clone)","damage":0.25,"hp":2.0,"attacker":"Assault Cannon"}},{"Timestamp":59.0739,"Name":"UnitDamage","Data":{"unit":"Hovercopter(Clone)","damage":0.25,"hp":1.75,"attacker":"Assault Cannon"}},{"Timestamp":59.225544,"Name":"UnitDamage","Data":{"unit":"Hovercopter(Clone)","damage":0.25,"hp":1.5,"attacker":"Assault Cannon"}},{"Timestamp":59.28858,"Name":"UnitDamage","Data":{"unit":"Hovercopter(Clone)","damage":0.25,"hp":1.25,"attacker":"Assault Cannon"}},{"Timestamp":59.3179436,"Name":"UnitDamage","Data":{"unit":"Hovercopter(Clone)","damage":0.25,"hp":1.0,"attacker":"Assault Cannon"}},{"Timestamp":59.34885,"Name":"UnitDamage","Data":{"unit":"Hovercopter(Clone)","damage":0.25,"hp":0.75,"attacker":"Assault Cannon"}},{"Timestamp":59.47869,"Name":"UnitDamage","Data":{"unit":"Hovercopter(Clone)","damage":0.25,"hp":0.5,"attacker":"Assault Cannon"}},{"Timestamp":59.5437737,"Name":"UnitDamage","Data":{"unit":"Hovercopter(Clone)","damage":0.25,"hp":0.25,"attacker":"Assault Cannon"}},{"Timestamp":59.5437927,"Name":"UnitDeath","Data":{"unit":"Hovercopter(Clone)","overkillDamage":0.0,"killTower":"Assault Cannon"}},{"Timestamp":59.5771751,"Name":"UnitDamage","Data":{"unit":"Hovercopter(Clone)","damage":0.25,"hp":0.0,"attacker":"Assault Cannon"}},{"Timestamp":59.6172752,"Name":"UnitDamage","Data":{"unit":"Hovercopter(Clone)","damage":0.25,"hp":0.0,"attacker":"Assault Cannon"}},{"Timestamp":59.9684753,"Name":"UnitDamage","Data":{"unit":"Hovercopter(Clone)","damage":0.25,"hp":16.0,"attacker":"Assault Cannon"}},{"Timestamp":60.0052643,"Name":"Economy","Data":{"team":"Defender","currency":3.0,"income":0.0}},{"Timestamp":60.0052757,"Name":"Economy","Data":{"team":"Attacker","currency":94.0,"income":85.0}},{"Timestamp":60.2211952,"Name":"UnitDamage","Data":{"unit":"Hovercopter(Clone)","damage":0.25,"hp":15.75,"attacker":"Assault Cannon"}},{"Timestamp":60.2296677,"Name":"UnitDamage","Data":{"unit":"Hovercopter(Clone)","damage":0.25,"hp":15.5,"attacker":"Assault Cannon"}},{"Timestamp":60.3285751,"Name":"UnitDamage","Data":{"unit":"Hovercopter(Clone)","damage":0.25,"hp":15.25,"attacker":"Assault Cannon"}},{"Timestamp":60.40056,"Name":"UnitSpawn","Data":{"unitSpawned":"Hovercopter","unitCount":24}},{"Timestamp":60.41976,"Name":"UnitDamage","Data":{"unit":"Hovercopter(Clone)","damage":12.0,"hp":15.0,"attacker":"Plasma Lance"}},{"Timestamp":60.4199448,"Name":"UnitDamage","Data":{"unit":"Hovercopter(Clone)","damage":12.0,"hp":3.0,"attacker":"Plasma Lance"}},{"Timestamp":60.4199524,"Name":"UnitDeath","Data":{"unit":"Hovercopter(Clone)","overkillDamage":9.0,"killTower":"Plasma Lance"}},{"Timestamp":60.4845924,"Name":"UnitDamage","Data":{"unit":"Hovercopter(Clone)","damage":0.25,"hp":0.0,"attacker":"Assault Cannon"}},{"Timestamp":60.49301,"Name":"UnitDamage","Data":{"unit":"Hovercopter(Clone)","damage":0.25,"hp":0.0,"attacker":"Assault Cannon"}},{"Timestamp":61.33531,"Name":"UnitDamage","Data":{"unit":"Hovercopter(Clone)","damage":12.0,"hp":16.0,"attacker":"Plasma Lance"}},{"Timestamp":62.01646,"Name":"UnitDamage","Data":{"unit":"Hovercopter(Clone)","damage":0.25,"hp":4.0,"attacker":"Assault Cannon"}},{"Timestamp":62.32999,"Name":"UnitDamage","Data":{"unit":"Hovercopter(Clone)","damage":0.25,"hp":3.75,"attacker":"Assault Cannon"}},{"Timestamp":62.3300323,"Name":"UnitDamage","Data":{"unit":"Hovercopter(Clone)","damage":0.25,"hp":3.5,"attacker":"Assault Cannon"}},{"Timestamp":62.4839058,"Name":"UnitSpawn","Data":{"unitSpawned":"Hovertank","unitCount":25}},{"Timestamp":62.53736,"Name":"UnitDamage","Data":{"unit":"Hovercopter(Clone)","damage":0.25,"hp":3.25,"attacker":"Assault Cannon"}},{"Timestamp":62.5768356,"Name":"UnitDamage","Data":{"unit":"Hovercopter(Clone)","damage":0.25,"hp":3.0,"attacker":"Assault Cannon"}},{"Timestamp":62.5768623,"Name":"UnitDamage","Data":{"unit":"Hovercopter(Clone)","damage":0.25,"hp":2.75,"attacker":"Assault Cannon"}},{"Timestamp":62.7613029,"Name":"UnitDamage","Data":{"unit":"Hovercopter(Clone)","damage":0.25,"hp":2.5,"attacker":"Assault Cannon"}},{"Timestamp":62.8640022,"Name":"UnitDamage","Data":{"unit":"Hovercopter(Clone)","damage":0.25,"hp":2.25,"attacker":"Assault Cannon"}},{"Timestamp":62.86405,"Name":"UnitDamage","Data":{"unit":"Hovercopter(Clone)","damage":0.25,"hp":2.0,"attacker":"Assault Cannon"}},{"Timestamp":63.0175552,"Name":"UnitDamage","Data":{"unit":"Hovercopter(Clone)","damage":0.25,"hp":1.75,"attacker":"Assault Cannon"}},{"Timestamp":63.0727272,"Name":"UnitDamage","Data":{"unit":"Hovercopter(Clone)","damage":0.25,"hp":1.5,"attacker":"Assault Cannon"}},{"Timestamp":63.1286964,"Name":"UnitDamage","Data":{"unit":"Hovercopter(Clone)","damage":0.25,"hp":1.25,"attacker":"Assault Cannon"}},{"Timestamp":63.1287346,"Name":"UnitDamage","Data":{"unit":"Hovercopter(Clone)","damage":0.25,"hp":1.0,"attacker":"Assault Cannon"}},{"Timestamp":63.2695541,"Name":"UnitDamage","Data":{"unit":"Hovercopter(Clone)","damage":0.25,"hp":0.75,"attacker":"Assault Cannon"}},{"Timestamp":63.32572,"Name":"UnitDamage","Data":{"unit":"Hovercopter(Clone)","damage":0.25,"hp":0.5,"attacker":"Assault Cannon"}},{"Timestamp":63.3770142,"Name":"UnitDamage","Data":{"unit":"Hovercopter(Clone)","damage":0.25,"hp":0.25,"attacker":"Assault Cannon"}},{"Timestamp":63.3770447,"Name":"UnitDeath","Data":{"unit":"Hovercopter(Clone)","overkillDamage":0.0,"killTower":"Assault Cannon"}},{"Timestamp":63.3770828,"Name":"UnitDamage","Data":{"unit":"Hovercopter(Clone)","damage":0.25,"hp":0.0,"attacker":"Assault Cannon"}},{"Timestamp":63.75427,"Name":"UnitDamage","Data":{"unit":"Hovertank(Clone)","damage":12.0,"hp":35.0,"attacker":"Plasma Lance"}},{"Timestamp":64.4784851,"Name":"UnitSpawn","Data":{"unitSpawned":"Hovercopter","unitCount":26}},{"Timestamp":64.67338,"Name":"UnitDamage","Data":{"unit":"Hovertank(Clone)","damage":12.0,"hp":23.0,"attacker":"Plasma Lance"}},{"Timestamp":65.01197,"Name":"Economy","Data":{"team":"Defender","currency":7.0,"income":0.0}},{"Timestamp":65.01198,"Name":"Economy","Data":{"team":"Attacker","currency":87.0,"income":85.0}},{"Timestamp":65.05608,"Name":"UnitDamage","Data":{"unit":"Hovertank(Clone)","damage":0.25,"hp":11.0,"attacker":"Assault Cannon"}},{"Timestamp":65.1601257,"Name":"UnitDamage","Data":{"unit":"Hovertank(Clone)","damage":12.0,"hp":10.75,"attacker":"Plasma Lance"}},{"Timestamp":65.16014,"Name":"UnitDeath","Data":{"unit":"Hovertank(Clone)","overkillDamage":1.25,"killTower":"Plasma Lance"}},{"Timestamp":65.2756348,"Name":"TowerBuilding","Data":{"tower":"Assault Cannon","X":4,"Y":1}},{"Timestamp":66.235054,"Name":"UnitDamage","Data":{"unit":"Hovercopter(Clone)","damage":0.25,"hp":16.0,"attacker":"Assault Cannon"}},{"Timestamp":66.48113,"Name":"UnitSpawn","Data":{"unitSpawned":"Hovertank","unitCount":27}},{"Timestamp":66.48929,"Name":"UnitDamage","Data":{"unit":"Hovercopter(Clone)","damage":0.25,"hp":15.75,"attacker":"Assault Cannon"}},{"Timestamp":66.49785,"Name":"UnitDamage","Data":{"unit":"Hovercopter(Clone)","damage":0.25,"hp":15.5,"attacker":"Assault Cannon"}},{"Timestamp":66.6009445,"Name":"UnitDamage","Data":{"unit":"Hovercopter(Clone)","damage":0.25,"hp":15.25,"attacker":"Assault Cannon"}},{"Timestamp":66.7401657,"Name":"UnitDamage","Data":{"unit":"Hovercopter(Clone)","damage":0.25,"hp":15.0,"attacker":"Assault Cannon"}},{"Timestamp":66.7593155,"Name":"UnitDamage","Data":{"unit":"Hovercopter(Clone)","damage":0.25,"hp":14.75,"attacker":"Assault Cannon"}},{"Timestamp":66.84091,"Name":"UnitDamage","Data":{"unit":"Hovercopter(Clone)","damage":0.25,"hp":14.5,"attacker":"Assault Cannon"}},{"Timestamp":66.87486,"Name":"UnitDamage","Data":{"unit":"Hovercopter(Clone)","damage":0.25,"hp":14.25,"attacker":"Assault Cannon"}},{"Timestamp":66.99201,"Name":"UnitDamage","Data":{"unit":"Hovercopter(Clone)","damage":0.25,"hp":14.0,"attacker":"Assault Cannon"}},{"Timestamp":67.00008,"Name":"UnitDamage","Data":{"unit":"Hovercopter(Clone)","damage":0.25,"hp":13.75,"attacker":"Assault Cannon"}},{"Timestamp":67.10152,"Name":"UnitDamage","Data":{"unit":"Hovercopter(Clone)","damage":12.0,"hp":13.5,"attacker":"Plasma Lance"}},{"Timestamp":67.10155,"Name":"UnitDamage","Data":{"unit":"Hovercopter(Clone)","damage":0.25,"hp":1.5,"attacker":"Assault Cannon"}},{"Timestamp":67.12579,"Name":"UnitDamage","Data":{"unit":"Hovercopter(Clone)","damage":0.25,"hp":1.25,"attacker":"Assault Cannon"}},{"Timestamp":67.2608643,"Name":"UnitDamage","Data":{"unit":"Hovercopter(Clone)","damage":0.25,"hp":1.0,"attacker":"Assault Cannon"}},{"Timestamp":67.2609,"Name":"UnitDamage","Data":{"unit":"Hovercopter(Clone)","damage":0.25,"hp":0.75,"attacker":"Assault Cannon"}},{"Timestamp":67.26093,"Name":"UnitDamage","Data":{"unit":"Hovercopter(Clone)","damage":0.25,"hp":0.5,"attacker":"Assault Cannon"}},{"Timestamp":67.3624344,"Name":"UnitDamage","Data":{"unit":"Hovercopter(Clone)","damage":0.25,"hp":0.25,"attacker":"Assault Cannon"}},{"Timestamp":67.36245,"Name":"UnitDeath","Data":{"unit":"Hovercopter(Clone)","overkillDamage":0.0,"killTower":"Assault Cannon"}},{"Timestamp":67.38653,"Name":"UnitDamage","Data":{"unit":"Hovercopter(Clone)","damage":0.25,"hp":0.0,"attacker":"Assault Cannon"}},{"Timestamp":68.0096359,"Name":"UnitDamage","Data":{"unit":"Hovertank(Clone)","damage":12.0,"hp":35.0,"attacker":"Plasma Lance"}},{"Timestamp":68.4864,"Name":"UnitSpawn","Data":{"unitSpawned":"Hovertank","unitCount":28}},{"Timestamp":68.58071,"Name":"UnitDamage","Data":{"unit":"Hovertank(Clone)","damage":0.25,"hp":23.0,"attacker":"Assault Cannon"}},{"Timestamp":68.70215,"Name":"UnitDamage","Data":{"unit":"Hovertank(Clone)","damage":12.0,"hp":22.75,"attacker":"Plasma Lance"}},{"Timestamp":68.82215,"Name":"UnitDamage","Data":{"unit":"Hovertank(Clone)","damage":0.25,"hp":10.75,"attacker":"Assault Cannon"}},{"Timestamp":68.9732361,"Name":"UnitDamage","Data":{"unit":"Hovertank(Clone)","damage":0.25,"hp":10.5,"attacker":"Assault Cannon"}},{"Timestamp":69.07452,"Name":"UnitDamage","Data":{"unit":"Hovertank(Clone)","damage":0.25,"hp":10.25,"attacker":"Assault Cannon"}},{"Timestamp":69.0745544,"Name":"UnitDamage","Data":{"unit":"Hovertank(Clone)","damage":0.25,"hp":10.0,"attacker":"Assault Cannon"}},{"Timestamp":69.24382,"Name":"UnitDamage","Data":{"unit":"Hovertank(Clone)","damage":0.25,"hp":9.75,"attacker":"Assault Cannon"}},{"Timestamp":69.32339,"Name":"UnitDamage","Data":{"unit":"Hovertank(Clone)","damage":0.25,"hp":9.5,"attacker":"Assault Cannon"}},{"Timestamp":69.34651,"Name":"UnitDamage","Data":{"unit":"Hovertank(Clone)","damage":0.25,"hp":9.25,"attacker":"Assault Cannon"}},{"Timestamp":69.4662,"Name":"UnitDamage","Data":{"unit":"Hovertank(Clone)","damage":0.25,"hp":9.0,"attacker":"Assault Cannon"}},{"Timestamp":69.48373,"Name":"UnitDamage","Data":{"unit":"Hovertank(Clone)","damage":0.25,"hp":8.75,"attacker":"Assault Cannon"}},{"Timestamp":69.58461,"Name":"UnitDamage","Data":{"unit":"Hovertank(Clone)","damage":0.25,"hp":8.5,"attacker":"Assault Cannon"}},{"Timestamp":69.6190643,"Name":"UnitDamage","Data":{"unit":"Hovertank(Clone)","damage":0.25,"hp":8.25,"attacker":"Assault Cannon"}},{"Timestamp":69.7367,"Name":"UnitDamage","Data":{"unit":"Hovertank(Clone)","damage":0.25,"hp":8.0,"attacker":"Assault Cannon"}},{"Timestamp":69.74911,"Name":"UnitDamage","Data":{"unit":"Hovertank(Clone)","damage":0.25,"hp":7.75,"attacker":"Assault Cannon"}},{"Timestamp":69.8404846,"Name":"UnitDamage","Data":{"unit":"Hovertank(Clone)","damage":0.25,"hp":7.5,"attacker":"Assault Cannon"}},{"Timestamp":69.8654861,"Name":"UnitDamage","Data":{"unit":"Hovertank(Clone)","damage":0.25,"hp":7.25,"attacker":"Assault Cannon"}},{"Timestamp":69.97668,"Name":"UnitDamage","Data":{"unit":"Hovertank(Clone)","damage":0.25,"hp":7.0,"attacker":"Assault Cannon"}},{"Timestamp":70.01129,"Name":"UnitDamage","Data":{"unit":"Hovertank(Clone)","damage":0.25,"hp":6.75,"attacker":"Assault Cannon"}},{"Timestamp":70.0197144,"Name":"Economy","Data":{"team":"Defender","currency":6.0,"income":0.0}},{"Timestamp":70.01973,"Name":"Economy","Data":{"team":"Attacker","currency":85.0,"income":85.0}},{"Timestamp":70.06646,"Name":"UnitDamage","Data":{"unit":"Hovertank(Clone)","damage":0.25,"hp":6.5,"attacker":"Assault Cannon"}},{"Timestamp":70.09981,"Name":"UnitDamage","Data":{"unit":"Hovertank(Clone)","damage":0.25,"hp":6.25,"attacker":"Assault Cannon"}},{"Timestamp":70.126,"Name":"UnitDamage","Data":{"unit":"Hovertank(Clone)","damage":0.25,"hp":6.0,"attacker":"Assault Cannon"}},{"Timestamp":70.23841,"Name":"UnitDamage","Data":{"unit":"Hovertank(Clone)","damage":0.25,"hp":5.75,"attacker":"Assault Cannon"}},{"Timestamp":70.26367,"Name":"UnitDamage","Data":{"unit":"Hovertank(Clone)","damage":0.25,"hp":5.5,"attacker":"Assault Cannon"}},{"Timestamp":70.3155,"Name":"UnitDamage","Data":{"unit":"Hovertank(Clone)","damage":0.25,"hp":5.25,"attacker":"Assault Cannon"}},{"Timestamp":70.35804,"Name":"UnitDamage","Data":{"unit":"Hovertank(Clone)","damage":0.25,"hp":5.0,"attacker":"Assault Cannon"}},{"Timestamp":70.3865356,"Name":"UnitDamage","Data":{"unit":"Hovertank(Clone)","damage":0.25,"hp":4.75,"attacker":"Assault Cannon"}},{"Timestamp":70.43205,"Name":"UnitDamage","Data":{"unit":"Hovertank(Clone)","damage":12.0,"hp":4.5,"attacker":"Plasma Lance"}},{"Timestamp":70.43207,"Name":"UnitDeath","Data":{"unit":"Hovertank(Clone)","overkillDamage":7.5,"killTower":"Plasma Lance"}},{"Timestamp":70.4901352,"Name":"UnitSpawn","Data":{"unitSpawned":"Hovercopter","unitCount":29}},{"Timestamp":70.4979553,"Name":"UnitDamage","Data":{"unit":"Hovertank(Clone)","damage":0.25,"hp":0.0,"attacker":"Assault Cannon"}},{"Timestamp":70.51627,"Name":"UnitDamage","Data":{"unit":"Hovertank(Clone)","damage":0.25,"hp":0.0,"attacker":"Assault Cannon"}},{"Timestamp":70.6302,"Name":"UnitDamage","Data":{"unit":"Hovertank(Clone)","damage":0.25,"hp":35.0,"attacker":"Assault Cannon"}},{"Timestamp":70.89578,"Name":"UnitDamage","Data":{"unit":"Hovertank(Clone)","damage":0.25,"hp":34.75,"attacker":"Assault Cannon"}},{"Timestamp":70.89582,"Name":"UnitDamage","Data":{"unit":"Hovertank(Clone)","damage":0.25,"hp":34.5,"attacker":"Assault Cannon"}},{"Timestamp":71.00301,"Name":"UnitDamage","Data":{"unit":"Hovertank(Clone)","damage":0.25,"hp":34.25,"attacker":"Assault Cannon"}},{"Timestamp":71.13111,"Name":"UnitDamage","Data":{"unit":"Hovertank(Clone)","damage":0.25,"hp":34.0,"attacker":"Assault Cannon"}},{"Timestamp":71.13115,"Name":"UnitDamage","Data":{"unit":"Hovertank(Clone)","damage":0.25,"hp":33.75,"attacker":"Assault Cannon"}},{"Timestamp":71.2529449,"Name":"UnitDamage","Data":{"unit":"Hovertank(Clone)","damage":0.25,"hp":33.5,"attacker":"Assault Cannon"}},{"Timestamp":71.34481,"Name":"UnitDamage","Data":{"unit":"Hovertank(Clone)","damage":12.0,"hp":33.25,"attacker":"Plasma Lance"}},{"Timestamp":71.39524,"Name":"UnitDamage","Data":{"unit":"Hovertank(Clone)","damage":0.25,"hp":21.25,"attacker":"Assault Cannon"}},{"Timestamp":71.39526,"Name":"UnitDamage","Data":{"unit":"Hovertank(Clone)","damage":0.25,"hp":21.0,"attacker":"Assault Cannon"}},{"Timestamp":71.41716,"Name":"UnitDamage","Data":{"unit":"Hovertank(Clone)","damage":0.25,"hp":20.75,"attacker":"Assault Cannon"}},{"Timestamp":71.5085449,"Name":"UnitDamage","Data":{"unit":"Hovertank(Clone)","damage":0.25,"hp":20.5,"attacker":"Assault Cannon"}},{"Timestamp":71.55058,"Name":"TowerBuilding","Data":{"tower":"Assault Cannon","X":1,"Y":0}},{"Timestamp":71.64496,"Name":"UnitDamage","Data":{"unit":"Hovertank(Clone)","damage":0.25,"hp":20.25,"attacker":"Assault Cannon"}},{"Timestamp":71.645,"Name":"UnitDamage","Data":{"unit":"Hovertank(Clone)","damage":0.25,"hp":20.0,"attacker":"Assault Cannon"}},{"Timestamp":71.6714554,"Name":"UnitDamage","Data":{"unit":"Hovertank(Clone)","damage":0.25,"hp":19.75,"attacker":"Assault Cannon"}},{"Timestamp":71.7644653,"Name":"UnitDamage","Data":{"unit":"Hovertank(Clone)","damage":0.25,"hp":19.5,"attacker":"Assault Cannon"}},{"Timestamp":71.9,"Name":"UnitDamage","Data":{"unit":"Hovertank(Clone)","damage":0.25,"hp":19.25,"attacker":"Assault Cannon"}},{"Timestamp":71.90003,"Name":"UnitDamage","Data":{"unit":"Hovertank(Clone)","damage":0.25,"hp":19.0,"attacker":"Assault Cannon"}},{"Timestamp":71.9000549,"Name":"UnitDamage","Data":{"unit":"Hovertank(Clone)","damage":0.25,"hp":18.75,"attacker":"Assault Cannon"}},{"Timestamp":71.92351,"Name":"UnitDamage","Data":{"unit":"Hovertank(Clone)","damage":0.25,"hp":18.5,"attacker":"Assault Cannon"}},{"Timestamp":72.01716,"Name":"UnitDamage","Data":{"unit":"Hovertank(Clone)","damage":0.25,"hp":18.25,"attacker":"Assault Cannon"}},{"Timestamp":72.0172,"Name":"UnitDamage","Data":{"unit":"Hovertank(Clone)","damage":0.25,"hp":18.0,"attacker":"Assault Cannon"}},{"Timestamp":72.0476456,"Name":"UnitDamage","Data":{"unit":"Hovertank(Clone)","damage":12.0,"hp":17.75,"attacker":"Plasma Lance"}},{"Timestamp":72.15476,"Name":"UnitDamage","Data":{"unit":"Hovertank(Clone)","damage":0.25,"hp":5.75,"attacker":"Assault Cannon"}},{"Timestamp":72.15479,"Name":"UnitDamage","Data":{"unit":"Hovertank(Clone)","damage":0.25,"hp":5.5,"attacker":"Assault Cannon"}},{"Timestamp":72.1548157,"Name":"UnitDamage","Data":{"unit":"Hovertank(Clone)","damage":0.25,"hp":5.25,"attacker":"Assault Cannon"}},{"Timestamp":72.1770554,"Name":"UnitDamage","Data":{"unit":"Hovertank(Clone)","damage":0.25,"hp":5.0,"attacker":"Assault Cannon"}},{"Timestamp":72.26708,"Name":"UnitDamage","Data":{"unit":"Hovertank(Clone)","damage":0.25,"hp":4.75,"attacker":"Assault Cannon"}},{"Timestamp":72.26713,"Name":"UnitDamage","Data":{"unit":"Hovertank(Clone)","damage":0.25,"hp":4.5,"attacker":"Assault Cannon"}},{"Timestamp":72.40682,"Name":"UnitDamage","Data":{"unit":"Hovertank(Clone)","damage":0.25,"hp":4.25,"attacker":"Assault Cannon"}},{"Timestamp":72.40686,"Name":"UnitDamage","Data":{"unit":"Hovertank(Clone)","damage":0.25,"hp":4.0,"attacker":"Assault Cannon"}},{"Timestamp":72.40688,"Name":"UnitDamage","Data":{"unit":"Hovertank(Clone)","damage":0.25,"hp":3.75,"attacker":"Assault Cannon"}},{"Timestamp":72.43426,"Name":"UnitDamage","Data":{"unit":"Hovertank(Clone)","damage":0.25,"hp":3.5,"attacker":"Assault Cannon"}},{"Timestamp":72.49393,"Name":"UnitSpawn","Data":{"unitSpawned":"Hovercopter","unitCount":30}},{"Timestamp":72.54563,"Name":"UnitDamage","Data":{"unit":"Hovertank(Clone)","damage":0.25,"hp":3.25,"attacker":"Assault Cannon"}},{"Timestamp":72.5456848,"Name":"UnitDamage","Data":{"unit":"Hovertank(Clone)","damage":0.25,"hp":3.0,"attacker":"Assault Cannon"}},{"Timestamp":72.6669159,"Name":"UnitDamage","Data":{"unit":"Hovertank(Clone)","damage":0.25,"hp":2.75,"attacker":"Assault Cannon"}},{"Timestamp":72.666954,"Name":"UnitDamage","Data":{"unit":"Hovertank(Clone)","damage":0.25,"hp":2.5,"attacker":"Assault Cannon"}},{"Timestamp":72.66697,"Name":"UnitDamage","Data":{"unit":"Hovertank(Clone)","damage":0.25,"hp":2.25,"attacker":"Assault Cannon"}},{"Timestamp":72.69553,"Name":"UnitDamage","Data":{"unit":"Hovertank(Clone)","damage":0.25,"hp":2.0,"attacker":"Assault Cannon"}},{"Timestamp":72.7761841,"Name":"UnitDamage","Data":{"unit":"Hovertank(Clone)","damage":0.25,"hp":1.75,"attacker":"Assault Cannon"}},{"Timestamp":72.7762146,"Name":"UnitDamage","Data":{"unit":"Hovertank(Clone)","damage":0.25,"hp":1.5,"attacker":"Assault Cannon"}},{"Timestamp":72.92124,"Name":"UnitDamage","Data":{"unit":"Hovertank(Clone)","damage":0.25,"hp":1.25,"attacker":"Assault Cannon"}},{"Timestamp":72.92127,"Name":"UnitDamage","Data":{"unit":"Hovertank(Clone)","damage":0.25,"hp":1.0,"attacker":"Assault Cannon"}},{"Timestamp":72.9212952,"Name":"UnitDamage","Data":{"unit":"Hovertank(Clone)","damage":0.25,"hp":0.75,"attacker":"Assault Cannon"}},{"Timestamp":72.94576,"Name":"UnitDamage","Data":{"unit":"Hovertank(Clone)","damage":0.25,"hp":0.5,"attacker":"Assault Cannon"}},{"Timestamp":73.0363159,"Name":"UnitDamage","Data":{"unit":"Hovertank(Clone)","damage":0.25,"hp":0.25,"attacker":"Assault Cannon"}},{"Timestamp":73.03634,"Name":"UnitDeath","Data":{"unit":"Hovertank(Clone)","overkillDamage":0.0,"killTower":"Assault Cannon"}},{"Timestamp":73.0363541,"Name":"UnitDamage","Data":{"unit":"Hovertank(Clone)","damage":0.25,"hp":0.0,"attacker":"Assault Cannon"}},{"Timestamp":73.1703644,"Name":"UnitDamage","Data":{"unit":"Hovercopter(Clone)","damage":0.25,"hp":16.0,"attacker":"Assault Cannon"}},{"Timestamp":73.17041,"Name":"UnitDamage","Data":{"unit":"Hovercopter(Clone)","damage":0.25,"hp":15.75,"attacker":"Assault Cannon"}},{"Timestamp":73.1704254,"Name":"UnitDamage","Data":{"unit":"Hovercopter(Clone)","damage":0.25,"hp":15.5,"attacker":"Assault Cannon"}},{"Timestamp":73.1991,"Name":"UnitDamage","Data":{"unit":"Hovercopter(Clone)","damage":0.25,"hp":15.25,"attacker":"Assault Cannon"}},{"Timestamp":73.3055,"Name":"UnitDamage","Data":{"unit":"Hovercopter(Clone)","damage":0.25,"hp":15.0,"attacker":"Assault Cannon"}},{"Timestamp":73.30553,"Name":"UnitDamage","Data":{"unit":"Hovercopter(Clone)","damage":0.25,"hp":14.75,"attacker":"Assault Cannon"}},{"Timestamp":73.358696,"Name":"TowerBuilding","Data":{"tower":"Assault Cannon","X":0,"Y":1}},{"Timestamp":73.42868,"Name":"UnitDamage","Data":{"unit":"Hovercopter(Clone)","damage":0.25,"hp":14.5,"attacker":"Assault Cannon"}},{"Timestamp":73.42872,"Name":"UnitDamage","Data":{"unit":"Hovercopter(Clone)","damage":0.25,"hp":14.25,"attacker":"Assault Cannon"}},{"Timestamp":73.4287338,"Name":"UnitDamage","Data":{"unit":"Hovercopter(Clone)","damage":0.25,"hp":14.0,"attacker":"Assault Cannon"}},{"Timestamp":73.4539,"Name":"UnitDamage","Data":{"unit":"Hovercopter(Clone)","damage":0.25,"hp":13.75,"attacker":"Assault Cannon"}},{"Timestamp":73.55718,"Name":"UnitDamage","Data":{"unit":"Hovercopter(Clone)","damage":0.25,"hp":13.5,"attacker":"Assault Cannon"}},{"Timestamp":73.55721,"Name":"UnitDamage","Data":{"unit":"Hovercopter(Clone)","damage":0.25,"hp":13.25,"attacker":"Assault Cannon"}},{"Timestamp":73.6946259,"Name":"UnitDamage","Data":{"unit":"Hovercopter(Clone)","damage":0.25,"hp":13.0,"attacker":"Assault Cannon"}},{"Timestamp":73.69466,"Name":"UnitDamage","Data":{"unit":"Hovercopter(Clone)","damage":0.25,"hp":12.75,"attacker":"Assault Cannon"}},{"Timestamp":73.69467,"Name":"UnitDamage","Data":{"unit":"Hovercopter(Clone)","damage":0.25,"hp":12.5,"attacker":"Assault Cannon"}},{"Timestamp":73.70901,"Name":"UnitDamage","Data":{"unit":"Hovercopter(Clone)","damage":0.25,"hp":12.25,"attacker":"Assault Cannon"}},{"Timestamp":73.70904,"Name":"UnitDamage","Data":{"unit":"Hovercopter(Clone)","damage":0.25,"hp":12.0,"attacker":"Assault Cannon"}},{"Timestamp":73.76237,"Name":"UnitDamage","Data":{"unit":"Hovercopter(Clone)","damage":12.0,"hp":11.75,"attacker":"Plasma Lance"}},{"Timestamp":73.76238,"Name":"UnitDeath","Data":{"unit":"Hovercopter(Clone)","overkillDamage":0.25,"killTower":"Plasma Lance"}},{"Timestamp":73.81242,"Name":"UnitDamage","Data":{"unit":"Hovercopter(Clone)","damage":0.25,"hp":0.0,"attacker":"Assault Cannon"}},{"Timestamp":73.8124542,"Name":"UnitDamage","Data":{"unit":"Hovercopter(Clone)","damage":0.25,"hp":0.0,"attacker":"Assault Cannon"}},{"Timestamp":73.93815,"Name":"UnitDamage","Data":{"unit":"Hovercopter(Clone)","damage":0.25,"hp":16.0,"attacker":"Assault Cannon"}},{"Timestamp":73.9381943,"Name":"UnitDamage","Data":{"unit":"Hovercopter(Clone)","damage":0.25,"hp":15.75,"attacker":"Assault Cannon"}},{"Timestamp":73.98039,"Name":"UnitDamage","Data":{"unit":"Hovercopter(Clone)","damage":0.25,"hp":15.5,"attacker":"Assault Cannon"}},{"Timestamp":74.02845,"Name":"UnitDamage","Data":{"unit":"Hovercopter(Clone)","damage":0.25,"hp":15.25,"attacker":"Assault Cannon"}},{"Timestamp":74.08455,"Name":"UnitDamage","Data":{"unit":"Hovercopter(Clone)","damage":0.25,"hp":15.0,"attacker":"Assault Cannon"}},{"Timestamp":74.1923752,"Name":"UnitDamage","Data":{"unit":"Hovercopter(Clone)","damage":0.25,"hp":14.75,"attacker":"Assault Cannon"}},{"Timestamp":74.19241,"Name":"UnitDamage","Data":{"unit":"Hovercopter(Clone)","damage":0.25,"hp":14.5,"attacker":"Assault Cannon"}},{"Timestamp":74.23326,"Name":"UnitDamage","Data":{"unit":"Hovercopter(Clone)","damage":0.25,"hp":14.25,"attacker":"Assault Cannon"}},{"Timestamp":74.2760239,"Name":"UnitDamage","Data":{"unit":"Hovercopter(Clone)","damage":0.25,"hp":14.0,"attacker":"Assault Cannon"}},{"Timestamp":74.3482056,"Name":"UnitDamage","Data":{"unit":"Hovercopter(Clone)","damage":0.25,"hp":13.75,"attacker":"Assault Cannon"}},{"Timestamp":74.35778,"Name":"UnitDamage","Data":{"unit":"Hovercopter(Clone)","damage":0.25,"hp":13.5,"attacker":"Assault Cannon"}},{"Timestamp":74.44176,"Name":"UnitDamage","Data":{"unit":"Hovercopter(Clone)","damage":0.25,"hp":13.25,"attacker":"Assault Cannon"}},{"Timestamp":74.4417953,"Name":"UnitDamage","Data":{"unit":"Hovercopter(Clone)","damage":0.25,"hp":13.0,"attacker":"Assault Cannon"}},{"Timestamp":74.4841461,"Name":"UnitDamage","Data":{"unit":"Hovercopter(Clone)","damage":0.25,"hp":12.75,"attacker":"Assault Cannon"}},{"Timestamp":74.52172,"Name":"UnitSpawn","Data":{"unitSpawned":"Hovercopter","unitCount":31}},{"Timestamp":74.53639,"Name":"UnitDamage","Data":{"unit":"Hovercopter(Clone)","damage":0.25,"hp":12.5,"attacker":"Assault Cannon"}},{"Timestamp":74.58421,"Name":"UnitDamage","Data":{"unit":"Hovercopter(Clone)","damage":0.25,"hp":12.25,"attacker":"Assault Cannon"}},{"Timestamp":74.62597,"Name":"UnitDamage","Data":{"unit":"Hovercopter(Clone)","damage":0.25,"hp":12.0,"attacker":"Assault Cannon"}},{"Timestamp":74.69118,"Name":"UnitDamage","Data":{"unit":"Hovercopter(Clone)","damage":12.0,"hp":11.75,"attacker":"Plasma Lance"}},{"Timestamp":74.69119,"Name":"UnitDeath","Data":{"unit":"Hovercopter(Clone)","overkillDamage":0.25,"killTower":"Plasma Lance"}},{"Timestamp":74.70591,"Name":"UnitDamage","Data":{"unit":"Hovercopter(Clone)","damage":0.25,"hp":0.0,"attacker":"Assault Cannon"}},{"Timestamp":74.70594,"Name":"UnitDamage","Data":{"unit":"Hovercopter(Clone)","damage":0.25,"hp":0.0,"attacker":"Assault Cannon"}},{"Timestamp":74.7361755,"Name":"UnitDamage","Data":{"unit":"Hovercopter(Clone)","damage":0.25,"hp":0.0,"attacker":"Assault Cannon"}},{"Timestamp":74.7535248,"Name":"UnitDamage","Data":{"unit":"Hovercopter(Clone)","damage":0.25,"hp":0.0,"attacker":"Assault Cannon"}},{"Timestamp":74.79289,"Name":"UnitDamage","Data":{"unit":"Hovercopter(Clone)","damage":0.25,"hp":0.0,"attacker":"Assault Cannon"}},{"Timestamp":75.0203857,"Name":"Economy","Data":{"team":"Defender","currency":4.0,"income":0.0}},{"Timestamp":75.02039,"Name":"Economy","Data":{"team":"Attacker","currency":88.0,"income":85.0}},{"Timestamp":75.3997,"Name":"UnitDamage","Data":{"unit":"Hovercopter(Clone)","damage":0.25,"hp":16.0,"attacker":"Assault Cannon"}},{"Timestamp":75.66658,"Name":"UnitDamage","Data":{"unit":"Hovercopter(Clone)","damage":0.25,"hp":15.75,"attacker":"Assault Cannon"}},{"Timestamp":75.84433,"Name":"UnitDamage","Data":{"unit":"Hovercopter(Clone)","damage":0.25,"hp":15.5,"attacker":"Assault Cannon"}},{"Timestamp":75.9114,"Name":"UnitDamage","Data":{"unit":"Hovercopter(Clone)","damage":0.25,"hp":15.25,"attacker":"Assault Cannon"}},{"Timestamp":76.09222,"Name":"UnitDamage","Data":{"unit":"Hovercopter(Clone)","damage":0.25,"hp":15.0,"attacker":"Assault Cannon"}},{"Timestamp":76.17464,"Name":"UnitDamage","Data":{"unit":"Hovercopter(Clone)","damage":0.25,"hp":14.75,"attacker":"Assault Cannon"}},{"Timestamp":76.174675,"Name":"UnitDamage","Data":{"unit":"Hovercopter(Clone)","damage":0.25,"hp":14.5,"attacker":"Assault Cannon"}},{"Timestamp":76.28538,"Name":"UnitDamage","Data":{"unit":"Hovercopter(Clone)","damage":12.0,"hp":14.25,"attacker":"Plasma Lance"}},{"Timestamp":76.33853,"Name":"UnitDamage","Data":{"unit":"Hovercopter(Clone)","damage":0.25,"hp":2.25,"attacker":"Assault Cannon"}},{"Timestamp":76.4203,"Name":"UnitDamage","Data":{"unit":"Hovercopter(Clone)","damage":0.25,"hp":2.0,"attacker":"Assault Cannon"}},{"Timestamp":76.42034,"Name":"UnitDamage","Data":{"unit":"Hovercopter(Clone)","damage":0.25,"hp":1.75,"attacker":"Assault Cannon"}},{"Timestamp":76.44646,"Name":"UnitDamage","Data":{"unit":"Hovercopter(Clone)","damage":0.25,"hp":1.5,"attacker":"Assault Cannon"}},{"Timestamp":76.50524,"Name":"UnitDamage","Data":{"unit":"Hovercopter(Clone)","damage":0.25,"hp":1.25,"attacker":"Assault Cannon"}},{"Timestamp":76.53153,"Name":"UnitSpawn","Data":{"unitSpawned":"Hoverbuggy","unitCount":32}},{"Timestamp":76.605896,"Name":"UnitDamage","Data":{"unit":"Hovercopter(Clone)","damage":0.25,"hp":1.0,"attacker":"Assault Cannon"}},{"Timestamp":76.68235,"Name":"UnitDamage","Data":{"unit":"Hovercopter(Clone)","damage":0.25,"hp":0.75,"attacker":"Assault Cannon"}},{"Timestamp":76.68238,"Name":"UnitDamage","Data":{"unit":"Hovercopter(Clone)","damage":0.25,"hp":0.5,"attacker":"Assault Cannon"}},{"Timestamp":76.69421,"Name":"UnitDamage","Data":{"unit":"Hovercopter(Clone)","damage":0.25,"hp":0.25,"attacker":"Assault Cannon"}},{"Timestamp":76.69422,"Name":"UnitDeath","Data":{"unit":"Hovercopter(Clone)","overkillDamage":0.0,"killTower":"Assault Cannon"}},{"Timestamp":76.74177,"Name":"UnitDamage","Data":{"unit":"Hovercopter(Clone)","damage":0.25,"hp":0.0,"attacker":"Assault Cannon"}},{"Timestamp":76.7739639,"Name":"UnitDamage","Data":{"unit":"Hovercopter(Clone)","damage":0.25,"hp":0.0,"attacker":"Assault Cannon"}},{"Timestamp":77.10309,"Name":"UnitDamage","Data":{"unit":"Hoverbuggy(Clone)","damage":12.0,"hp":6.0,"attacker":"Plasma Lance"}},{"Timestamp":77.1031,"Name":"UnitDeath","Data":{"unit":"Hoverbuggy(Clone)","overkillDamage":6.0,"killTower":"Plasma Lance"}},{"Timestamp":77.1608658,"Name":"UnitDamage","Data":{"unit":"Hoverbuggy(Clone)","damage":0.25,"hp":0.0,"attacker":"Assault Cannon"}},{"Timestamp":78.53291,"Name":"UnitSpawn","Data":{"unitSpawned":"Hovercopter","unitCount":33}},{"Timestamp":78.90653,"Name":"UnitDamage","Data":{"unit":"Hovercopter(Clone)","damage":12.0,"hp":16.0,"attacker":"Plasma Lance"}},{"Timestamp":79.36727,"Name":"UnitDamage","Data":{"unit":"Hovercopter(Clone)","damage":0.25,"hp":4.0,"attacker":"Assault Cannon"}},{"Timestamp":79.6264648,"Name":"UnitDamage","Data":{"unit":"Hovercopter(Clone)","damage":0.25,"hp":3.75,"attacker":"Assault Cannon"}},{"Timestamp":79.80057,"Name":"UnitDamage","Data":{"unit":"Hovercopter(Clone)","damage":0.25,"hp":3.5,"attacker":"Assault Cannon"}},{"Timestamp":79.8724747,"Name":"UnitDamage","Data":{"unit":"Hovercopter(Clone)","damage":0.25,"hp":3.25,"attacker":"Assault Cannon"}},{"Timestamp":80.02271,"Name":"Economy","Data":{"team":"Defender","currency":7.0,"income":0.0}},{"Timestamp":80.02272,"Name":"Economy","Data":{"team":"Attacker","currency":88.0,"income":85.0}},{"Timestamp":80.04966,"Name":"UnitDamage","Data":{"unit":"Hovercopter(Clone)","damage":0.25,"hp":3.0,"attacker":"Assault Cannon"}},{"Timestamp":80.13298,"Name":"UnitDamage","Data":{"unit":"Hovercopter(Clone)","damage":0.25,"hp":2.75,"attacker":"Assault Cannon"}},{"Timestamp":80.13301,"Name":"UnitDamage","Data":{"unit":"Hovercopter(Clone)","damage":0.25,"hp":2.5,"attacker":"Assault Cannon"}},{"Timestamp":80.2401047,"Name":"UnitDamage","Data":{"unit":"Hovercopter(Clone)","damage":12.0,"hp":2.25,"attacker":"Plasma Lance"}},{"Timestamp":80.24016,"Name":"UnitDeath","Data":{"unit":"Hovercopter(Clone)","overkillDamage":9.75,"killTower":"Plasma Lance"}},{"Timestamp":80.29823,"Name":"UnitDamage","Data":{"unit":"Hovercopter(Clone)","damage":0.25,"hp":0.0,"attacker":"Assault Cannon"}},{"Timestamp":80.43635,"Name":"UnitDamage","Data":{"unit":"Hovercopter(Clone)","damage":12.0,"hp":0.0,"attacker":"Plasma Lance"}},{"Timestamp":80.53664,"Name":"UnitSpawn","Data":{"unitSpawned":"Hovercopter","unitCount":34}},{"Timestamp":81.24551,"Name":"UnitDamage","Data":{"unit":"Hovercopter(Clone)","damage":0.25,"hp":16.0,"attacker":"Assault Cannon"}},{"Timestamp":81.5004349,"Name":"UnitDamage","Data":{"unit":"Hovercopter(Clone)","damage":0.25,"hp":15.75,"attacker":"Assault Cannon"}},{"Timestamp":81.61805,"Name":"UnitDamage","Data":{"unit":"Hovercopter(Clone)","damage":0.25,"hp":15.5,"attacker":"Assault Cannon"}},{"Timestamp":81.75528,"Name":"UnitDamage","Data":{"unit":"Hovercopter(Clone)","damage":0.25,"hp":15.25,"attacker":"Assault Cannon"}},{"Timestamp":81.86677,"Name":"UnitDamage","Data":{"unit":"Hovercopter(Clone)","damage":0.25,"hp":15.0,"attacker":"Assault Cannon"}},{"Timestamp":81.97526,"Name":"UnitDamage","Data":{"unit":"Hovercopter(Clone)","damage":0.25,"hp":14.75,"attacker":"Assault Cannon"}},{"Timestamp":82.00318,"Name":"UnitDamage","Data":{"unit":"Hovercopter(Clone)","damage":0.25,"hp":14.5,"attacker":"Assault Cannon"}},{"Timestamp":82.1000443,"Name":"TowerBuilding","Data":{"tower":"Assault Cannon","X":0,"Y":2}},{"Timestamp":82.12641,"Name":"UnitDamage","Data":{"unit":"Hovercopter(Clone)","damage":0.25,"hp":14.25,"attacker":"Assault Cannon"}},{"Timestamp":82.23107,"Name":"UnitDamage","Data":{"unit":"Hovercopter(Clone)","damage":0.25,"hp":14.0,"attacker":"Assault Cannon"}},{"Timestamp":82.23908,"Name":"UnitDamage","Data":{"unit":"Hovercopter(Clone)","damage":12.0,"hp":13.75,"attacker":"Plasma Lance"}},{"Timestamp":82.2734146,"Name":"UnitDamage","Data":{"unit":"Hovercopter(Clone)","damage":0.25,"hp":1.75,"attacker":"Assault Cannon"}},{"Timestamp":82.28351,"Name":"UnitDamage","Data":{"unit":"Hovercopter(Clone)","damage":0.25,"hp":1.5,"attacker":"Assault Cannon"}},{"Timestamp":82.33505,"Name":"UnitDamage","Data":{"unit":"Hovercopter(Clone)","damage":0.25,"hp":1.25,"attacker":"Assault Cannon"}},{"Timestamp":82.38366,"Name":"UnitDamage","Data":{"unit":"Hovercopter(Clone)","damage":0.25,"hp":1.0,"attacker":"Assault Cannon"}},{"Timestamp":82.4547958,"Name":"UnitDamage","Data":{"unit":"Hovercopter(Clone)","damage":0.25,"hp":0.75,"attacker":"Assault Cannon"}},{"Timestamp":82.48317,"Name":"UnitDamage","Data":{"unit":"Hovercopter(Clone)","damage":0.25,"hp":0.5,"attacker":"Assault Cannon"}},{"Timestamp":82.51599,"Name":"UnitDamage","Data":{"unit":"Hovercopter(Clone)","damage":0.25,"hp":0.25,"attacker":"Assault Cannon"}},{"Timestamp":82.516,"Name":"UnitDeath","Data":{"unit":"Hovercopter(Clone)","overkillDamage":0.0,"killTower":"Assault Cannon"}},{"Timestamp":82.54024,"Name":"UnitSpawn","Data":{"unitSpawned":"Hovercopter","unitCount":35}},{"Timestamp":82.54814,"Name":"UnitDamage","Data":{"unit":"Hovercopter(Clone)","damage":0.25,"hp":16.0,"attacker":"Assault Cannon"}},{"Timestamp":82.59907,"Name":"UnitDamage","Data":{"unit":"Hovercopter(Clone)","damage":0.25,"hp":15.75,"attacker":"Assault Cannon"}},{"Timestamp":82.60924,"Name":"UnitDamage","Data":{"unit":"Hovercopter(Clone)","damage":0.25,"hp":15.5,"attacker":"Assault Cannon"}},{"Timestamp":83.4943,"Name":"UnitDamage","Data":{"unit":"Hovercopter(Clone)","damage":0.25,"hp":15.25,"attacker":"Assault Cannon"}},{"Timestamp":83.54775,"Name":"UnitDamage","Data":{"unit":"Hovercopter(Clone)","damage":0.25,"hp":15.0,"attacker":"Assault Cannon"}},{"Timestamp":83.76115,"Name":"UnitDamage","Data":{"unit":"Hovercopter(Clone)","damage":0.25,"hp":14.75,"attacker":"Assault Cannon"}},{"Timestamp":83.77426,"Name":"UnitDamage","Data":{"unit":"Hovercopter(Clone)","damage":12.0,"hp":14.5,"attacker":"Plasma Lance"}},{"Timestamp":83.80385,"Name":"UnitDamage","Data":{"unit":"Hovercopter(Clone)","damage":0.25,"hp":2.5,"attacker":"Assault Cannon"}},{"Timestamp":83.8921356,"Name":"UnitDamage","Data":{"unit":"Hovercopter(Clone)","damage":0.25,"hp":2.25,"attacker":"Assault Cannon"}},{"Timestamp":84.00572,"Name":"UnitDamage","Data":{"unit":"Hovercopter(Clone)","damage":0.25,"hp":2.0,"attacker":"Assault Cannon"}},{"Timestamp":84.05537,"Name":"UnitDamage","Data":{"unit":"Hovercopter(Clone)","damage":0.25,"hp":1.75,"attacker":"Assault Cannon"}},{"Timestamp":84.15047,"Name":"UnitDamage","Data":{"unit":"Hovercopter(Clone)","damage":0.25,"hp":1.5,"attacker":"Assault Cannon"}},{"Timestamp":84.21999,"Name":"UnitDamage","Data":{"unit":"Hovercopter(Clone)","damage":0.25,"hp":1.25,"attacker":"Assault Cannon"}},{"Timestamp":84.25721,"Name":"UnitDamage","Data":{"unit":"Hovercopter(Clone)","damage":0.25,"hp":1.0,"attacker":"Assault Cannon"}},{"Timestamp":84.3044052,"Name":"UnitDamage","Data":{"unit":"Hovercopter(Clone)","damage":0.25,"hp":0.75,"attacker":"Assault Cannon"}},{"Timestamp":84.35006,"Name":"UnitDamage","Data":{"unit":"Hovercopter(Clone)","damage":12.0,"hp":0.5,"attacker":"Plasma Lance"}},{"Timestamp":84.3500748,"Name":"UnitDeath","Data":{"unit":"Hovercopter(Clone)","overkillDamage":11.5,"killTower":"Plasma Lance"}},{"Timestamp":84.4221039,"Name":"UnitDamage","Data":{"unit":"Hovercopter(Clone)","damage":0.25,"hp":0.0,"attacker":"Assault Cannon"}},{"Timestamp":84.54588,"Name":"UnitSpawn","Data":{"unitSpawned":"Hovercopter","unitCount":36}},{"Timestamp":85.02864,"Name":"Economy","Data":{"team":"Defender","currency":6.0,"income":0.0}},{"Timestamp":85.02865,"Name":"Economy","Data":{"team":"Attacker","currency":91.0,"income":85.0}},{"Timestamp":85.18678,"Name":"UnitDamage","Data":{"unit":"Hovercopter(Clone)","damage":0.25,"hp":16.0,"attacker":"Assault Cannon"}},{"Timestamp":85.21038,"Name":"UnitDamage","Data":{"unit":"Hovercopter(Clone)","damage":0.25,"hp":15.75,"attacker":"Assault Cannon"}},{"Timestamp":85.4471359,"Name":"UnitDamage","Data":{"unit":"Hovercopter(Clone)","damage":0.25,"hp":15.5,"attacker":"Assault Cannon"}},{"Timestamp":85.47236,"Name":"UnitDamage","Data":{"unit":"Hovercopter(Clone)","damage":0.25,"hp":15.25,"attacker":"Assault Cannon"}},{"Timestamp":85.51901,"Name":"UnitDamage","Data":{"unit":"Hovercopter(Clone)","damage":0.25,"hp":15.0,"attacker":"Assault Cannon"}},{"Timestamp":85.57955,"Name":"UnitDamage","Data":{"unit":"Hovercopter(Clone)","damage":12.0,"hp":14.75,"attacker":"Plasma Lance"}},{"Timestamp":85.6942139,"Name":"UnitDamage","Data":{"unit":"Hovercopter(Clone)","damage":0.25,"hp":2.75,"attacker":"Assault Cannon"}},{"Timestamp":85.7402344,"Name":"UnitDamage","Data":{"unit":"Hovercopter(Clone)","damage":0.25,"hp":2.5,"attacker":"Assault Cannon"}},{"Timestamp":85.77421,"Name":"UnitDamage","Data":{"unit":"Hovercopter(Clone)","damage":0.25,"hp":2.25,"attacker":"Assault Cannon"}},{"Timestamp":85.87151,"Name":"UnitDamage","Data":{"unit":"Hovercopter(Clone)","damage":0.25,"hp":2.0,"attacker":"Assault Cannon"}},{"Timestamp":85.9463043,"Name":"UnitDamage","Data":{"unit":"Hovercopter(Clone)","damage":0.25,"hp":1.75,"attacker":"Assault Cannon"}},{"Timestamp":85.97165,"Name":"UnitDamage","Data":{"unit":"Hovercopter(Clone)","damage":0.25,"hp":1.5,"attacker":"Assault Cannon"}},{"Timestamp":86.03604,"Name":"UnitDamage","Data":{"unit":"Hovercopter(Clone)","damage":0.25,"hp":1.25,"attacker":"Assault Cannon"}},{"Timestamp":86.12545,"Name":"UnitDamage","Data":{"unit":"Hovercopter(Clone)","damage":0.25,"hp":1.0,"attacker":"Assault Cannon"}},{"Timestamp":86.181076,"Name":"UnitDamage","Data":{"unit":"Hovercopter(Clone)","damage":0.25,"hp":0.75,"attacker":"Assault Cannon"}},{"Timestamp":86.2101059,"Name":"UnitDamage","Data":{"unit":"Hovercopter(Clone)","damage":0.25,"hp":0.5,"attacker":"Assault Cannon"}},{"Timestamp":86.21028,"Name":"UnitDamage","Data":{"unit":"Hovercopter(Clone)","damage":0.25,"hp":0.25,"attacker":"Assault Cannon"}},{"Timestamp":86.21029,"Name":"UnitDeath","Data":{"unit":"Hovercopter(Clone)","overkillDamage":0.0,"killTower":"Assault Cannon"}},{"Timestamp":86.2411957,"Name":"UnitDamage","Data":{"unit":"Hovercopter(Clone)","damage":0.25,"hp":0.0,"attacker":"Assault Cannon"}},{"Timestamp":86.28181,"Name":"UnitDamage","Data":{"unit":"Hovercopter(Clone)","damage":0.25,"hp":0.0,"attacker":"Assault Cannon"}},{"Timestamp":86.55962,"Name":"UnitSpawn","Data":{"unitSpawned":"Hovertank","unitCount":37}},{"Timestamp":86.7227554,"Name":"TowerBuilding","Data":{"tower":"Assault Cannon","X":3,"Y":2}},{"Timestamp":87.79549,"Name":"TowerDamaged","Data":{"damagedTower":"MachineGunTower(Clone)","X":0,"Y":2,"towerDamage":2.0,"hp":5.0}},{"Timestamp":88.55871,"Name":"UnitSpawn","Data":{"unitSpawned":"Hovercopter","unitCount":38}},{"Timestamp":88.79607,"Name":"TowerDamaged","Data":{"damagedTower":"MachineGunTower(Clone)","X":0,"Y":2,"towerDamage":2.0,"hp":3.0}},{"Timestamp":88.88802,"Name":"UnitDamage","Data":{"unit":"Hovercopter(Clone)","damage":12.0,"hp":16.0,"attacker":"Plasma Lance"}},{"Timestamp":88.92385,"Name":"UnitDamage","Data":{"unit":"Hovercopter(Clone)","damage":12.0,"hp":4.0,"attacker":"Plasma Lance"}},{"Timestamp":88.92387,"Name":"UnitDeath","Data":{"unit":"Hovercopter(Clone)","overkillDamage":8.0,"killTower":"Plasma Lance"}},{"Timestamp":89.8027649,"Name":"TowerDamaged","Data":{"damagedTower":"MachineGunTower(Clone)","X":0,"Y":2,"towerDamage":2.0,"hp":1.0}},{"Timestamp":89.8028259,"Name":"TowerDestroyed","Data":{"destroyedTower":"MachineGunTower(Clone)","X":0,"Y":2}},{"Timestamp":90.03986,"Name":"Economy","Data":{"team":"Defender","currency":3.0,"income":0.0}},{"Timestamp":90.03987,"Name":"Economy","Data":{"team":"Attacker","currency":87.0,"income":85.0}},{"Timestamp":90.56604,"Name":"UnitSpawn","Data":{"unitSpawned":"Hovercopter","unitCount":39}},{"Timestamp":90.82896,"Name":"TowerDamaged","Data":{"damagedTower":"MachineGunTower(Clone)","X":0,"Y":1,"towerDamage":2.0,"hp":5.0}},{"Timestamp":91.4578552,"Name":"UnitDamage","Data":{"unit":"Hovercopter(Clone)","damage":0.25,"hp":16.0,"attacker":"Assault Cannon"}},{"Timestamp":91.71503,"Name":"UnitDamage","Data":{"unit":"Hovercopter(Clone)","damage":0.25,"hp":15.75,"attacker":"Assault Cannon"}},{"Timestamp":91.8384247,"Name":"TowerDamaged","Data":{"damagedTower":"MachineGunTower(Clone)","X":0,"Y":1,"towerDamage":2.0,"hp":3.0}},{"Timestamp":91.84757,"Name":"UnitDamage","Data":{"unit":"Hovercopter(Clone)","damage":0.25,"hp":15.5,"attacker":"Assault Cannon"}},{"Timestamp":91.96118,"Name":"UnitDamage","Data":{"unit":"Hovercopter(Clone)","damage":0.25,"hp":15.25,"attacker":"Assault Cannon"}},{"Timestamp":92.0983047,"Name":"UnitDamage","Data":{"unit":"Hovercopter(Clone)","damage":0.25,"hp":15.0,"attacker":"Assault Cannon"}},{"Timestamp":92.2008743,"Name":"UnitDamage","Data":{"unit":"Hovercopter(Clone)","damage":0.25,"hp":14.75,"attacker":"Assault Cannon"}},{"Timestamp":92.21779,"Name":"UnitDamage","Data":{"unit":"Hovercopter(Clone)","damage":0.25,"hp":14.5,"attacker":"Assault Cannon"}},{"Timestamp":92.2269745,"Name":"UnitDamage","Data":{"unit":"Hovercopter(Clone)","damage":12.0,"hp":14.25,"attacker":"Plasma Lance"}},{"Timestamp":92.2690353,"Name":"UnitDamage","Data":{"unit":"Hovercopter(Clone)","damage":12.0,"hp":2.25,"attacker":"Plasma Lance"}},{"Timestamp":92.26905,"Name":"UnitDeath","Data":{"unit":"Hovercopter(Clone)","overkillDamage":9.75,"killTower":"Plasma Lance"}},{"Timestamp":92.2942047,"Name":"UnitDamage","Data":{"unit":"Hovercopter(Clone)","damage":12.0,"hp":0.0,"attacker":"Plasma Lance"}},{"Timestamp":92.34607,"Name":"UnitDamage","Data":{"unit":"Hovercopter(Clone)","damage":0.25,"hp":0.0,"attacker":"Assault Cannon"}},{"Timestamp":92.56712,"Name":"UnitSpawn","Data":{"unitSpawned":"Hovercopter","unitCount":40}},{"Timestamp":92.8409,"Name":"TowerDamaged","Data":{"damagedTower":"MachineGunTower(Clone)","X":0,"Y":1,"towerDamage":2.0,"hp":1.0}},{"Timestamp":92.84091,"Name":"TowerDestroyed","Data":{"destroyedTower":"MachineGunTower(Clone)","X":0,"Y":1}},{"Timestamp":93.4302,"Name":"UnitDamage","Data":{"unit":"Hovercopter(Clone)","damage":0.25,"hp":16.0,"attacker":"Assault Cannon"}},{"Timestamp":93.6884155,"Name":"UnitDamage","Data":{"unit":"Hovercopter(Clone)","damage":0.25,"hp":15.75,"attacker":"Assault Cannon"}},{"Timestamp":93.76612,"Name":"UnitDamage","Data":{"unit":"Hovercopter(Clone)","damage":0.25,"hp":15.5,"attacker":"Assault Cannon"}},{"Timestamp":93.87009,"Name":"TowerDamaged","Data":{"damagedTower":"LaserTower(Clone)","X":0,"Y":0,"towerDamage":2.0,"hp":5.0}},{"Timestamp":93.94416,"Name":"UnitDamage","Data":{"unit":"Hovercopter(Clone)","damage":0.25,"hp":15.25,"attacker":"Assault Cannon"}},{"Timestamp":94.0159,"Name":"UnitDamage","Data":{"unit":"Hovercopter(Clone)","damage":0.25,"hp":15.0,"attacker":"Assault Cannon"}},{"Timestamp":94.02307,"Name":"UnitDamage","Data":{"unit":"Hovercopter(Clone)","damage":0.25,"hp":14.75,"attacker":"Assault Cannon"}},{"Timestamp":94.05032,"Name":"UnitDamage","Data":{"unit":"Hovercopter(Clone)","damage":0.25,"hp":14.5,"attacker":"Assault Cannon"}},{"Timestamp":94.09149,"Name":"UnitDamage","Data":{"unit":"Hovercopter(Clone)","damage":0.25,"hp":14.25,"attacker":"Assault Cannon"}},{"Timestamp":94.19465,"Name":"UnitDamage","Data":{"unit":"Hovercopter(Clone)","damage":0.25,"hp":14.0,"attacker":"Assault Cannon"}},{"Timestamp":94.2694,"Name":"UnitDamage","Data":{"unit":"Hovercopter(Clone)","damage":0.25,"hp":13.75,"attacker":"Assault Cannon"}},{"Timestamp":94.27676,"Name":"UnitDamage","Data":{"unit":"Hovercopter(Clone)","damage":0.25,"hp":13.5,"attacker":"Assault Cannon"}},{"Timestamp":94.31274,"Name":"UnitDamage","Data":{"unit":"Hovercopter(Clone)","damage":0.25,"hp":13.25,"attacker":"Assault Cannon"}},{"Timestamp":94.34786,"Name":"UnitDamage","Data":{"unit":"Hovercopter(Clone)","damage":0.25,"hp":13.0,"attacker":"Assault Cannon"}},{"Timestamp":94.38092,"Name":"UnitDamage","Data":{"unit":"Hovercopter(Clone)","damage":0.25,"hp":12.75,"attacker":"Assault Cannon"}},{"Timestamp":94.4551239,"Name":"UnitDamage","Data":{"unit":"Hovercopter(Clone)","damage":0.25,"hp":12.5,"attacker":"Assault Cannon"}},{"Timestamp":94.51798,"Name":"UnitDamage","Data":{"unit":"Hovercopter(Clone)","damage":0.25,"hp":12.25,"attacker":"Assault Cannon"}},{"Timestamp":94.53502,"Name":"UnitDamage","Data":{"unit":"Hovercopter(Clone)","damage":0.25,"hp":12.0,"attacker":"Assault Cannon"}},{"Timestamp":94.55147,"Name":"UnitDamage","Data":{"unit":"Hovercopter(Clone)","damage":0.25,"hp":11.75,"attacker":"Assault Cannon"}},{"Timestamp":94.56821,"Name":"UnitSpawn","Data":{"unitSpawned":"Hoverbuggy","unitCount":41}},{"Timestamp":94.6015,"Name":"UnitDamage","Data":{"unit":"Hovercopter(Clone)","damage":0.25,"hp":11.5,"attacker":"Assault Cannon"}},{"Timestamp":94.6567,"Name":"UnitDamage","Data":{"unit":"Hovercopter(Clone)","damage":0.25,"hp":11.25,"attacker":"Assault Cannon"}},{"Timestamp":94.70191,"Name":"UnitDamage","Data":{"unit":"Hovercopter(Clone)","damage":0.25,"hp":11.0,"attacker":"Assault Cannon"}},{"Timestamp":94.77829,"Name":"UnitDamage","Data":{"unit":"Hovercopter(Clone)","damage":0.25,"hp":10.75,"attacker":"Assault Cannon"}},{"Timestamp":94.78576,"Name":"UnitDamage","Data":{"unit":"Hovercopter(Clone)","damage":0.25,"hp":10.5,"attacker":"Assault Cannon"}},{"Timestamp":94.78579,"Name":"UnitDamage","Data":{"unit":"Hovercopter(Clone)","damage":0.25,"hp":10.25,"attacker":"Assault Cannon"}},{"Timestamp":94.81664,"Name":"UnitDamage","Data":{"unit":"Hovercopter(Clone)","damage":0.25,"hp":10.0,"attacker":"Assault Cannon"}},{"Timestamp":94.8574142,"Name":"UnitDamage","Data":{"unit":"Hovercopter(Clone)","damage":0.25,"hp":9.75,"attacker":"Assault Cannon"}},{"Timestamp":94.87471,"Name":"TowerDamaged","Data":{"damagedTower":"LaserTower(Clone)","X":0,"Y":0,"towerDamage":2.0,"hp":3.0}},{"Timestamp":94.89093,"Name":"UnitDamage","Data":{"unit":"Hovercopter(Clone)","damage":0.25,"hp":9.5,"attacker":"Assault Cannon"}},{"Timestamp":94.97455,"Name":"UnitDamage","Data":{"unit":"Hovercopter(Clone)","damage":0.25,"hp":9.25,"attacker":"Assault Cannon"}},{"Timestamp":95.0275345,"Name":"UnitDamage","Data":{"unit":"Hovercopter(Clone)","damage":0.25,"hp":9.0,"attacker":"Assault Cannon"}},{"Timestamp":95.04342,"Name":"Economy","Data":{"team":"Defender","currency":5.0,"income":0.0}},{"Timestamp":95.0434341,"Name":"Economy","Data":{"team":"Attacker","currency":88.0,"income":85.0}},{"Timestamp":95.0436249,"Name":"UnitDamage","Data":{"unit":"Hovercopter(Clone)","damage":0.25,"hp":8.75,"attacker":"Assault Cannon"}},{"Timestamp":95.0436554,"Name":"UnitDamage","Data":{"unit":"Hovercopter(Clone)","damage":0.25,"hp":8.5,"attacker":"Assault Cannon"}},{"Timestamp":95.05989,"Name":"UnitDamage","Data":{"unit":"Hovercopter(Clone)","damage":0.25,"hp":8.25,"attacker":"Assault Cannon"}},{"Timestamp":95.11694,"Name":"UnitDamage","Data":{"unit":"Hovercopter(Clone)","damage":0.25,"hp":8.0,"attacker":"Assault Cannon"}},{"Timestamp":95.1476,"Name":"UnitDamage","Data":{"unit":"Hovercopter(Clone)","damage":0.25,"hp":7.75,"attacker":"Assault Cannon"}},{"Timestamp":95.21361,"Name":"UnitDamage","Data":{"unit":"Hovercopter(Clone)","damage":0.25,"hp":7.5,"attacker":"Assault Cannon"}},{"Timestamp":95.28687,"Name":"UnitDamage","Data":{"unit":"Hovercopter(Clone)","damage":0.25,"hp":7.25,"attacker":"Assault Cannon"}},{"Timestamp":95.31541,"Name":"UnitDamage","Data":{"unit":"Hovercopter(Clone)","damage":0.25,"hp":7.0,"attacker":"Assault Cannon"}},{"Timestamp":95.3154449,"Name":"UnitDamage","Data":{"unit":"Hovercopter(Clone)","damage":0.25,"hp":6.75,"attacker":"Assault Cannon"}},{"Timestamp":95.31546,"Name":"UnitDamage","Data":{"unit":"Hovercopter(Clone)","damage":0.25,"hp":6.5,"attacker":"Assault Cannon"}},{"Timestamp":95.36766,"Name":"UnitDamage","Data":{"unit":"Hovercopter(Clone)","damage":0.25,"hp":6.25,"attacker":"Assault Cannon"}},{"Timestamp":95.40086,"Name":"UnitDamage","Data":{"unit":"Hovercopter(Clone)","damage":0.25,"hp":6.0,"attacker":"Assault Cannon"}},{"Timestamp":95.47851,"Name":"UnitDamage","Data":{"unit":"Hovercopter(Clone)","damage":0.25,"hp":5.75,"attacker":"Assault Cannon"}},{"Timestamp":95.53834,"Name":"UnitDamage","Data":{"unit":"Hovercopter(Clone)","damage":0.25,"hp":5.5,"attacker":"Assault Cannon"}},{"Timestamp":95.55541,"Name":"UnitDamage","Data":{"unit":"Hovercopter(Clone)","damage":0.25,"hp":5.25,"attacker":"Assault Cannon"}},{"Timestamp":95.55544,"Name":"UnitDamage","Data":{"unit":"Hovercopter(Clone)","damage":0.25,"hp":5.0,"attacker":"Assault Cannon"}},{"Timestamp":95.57337,"Name":"UnitDamage","Data":{"unit":"Hovercopter(Clone)","damage":12.0,"hp":4.75,"attacker":"Plasma Lance"}},{"Timestamp":95.57339,"Name":"UnitDeath","Data":{"unit":"Hovercopter(Clone)","overkillDamage":7.25,"killTower":"Plasma Lance"}},{"Timestamp":95.5806656,"Name":"UnitDamage","Data":{"unit":"Hovercopter(Clone)","damage":0.25,"hp":0.0,"attacker":"Assault Cannon"}},{"Timestamp":95.60626,"Name":"UnitDamage","Data":{"unit":"Hovercopter(Clone)","damage":12.0,"hp":0.0,"attacker":"Plasma Lance"}},{"Timestamp":95.61321,"Name":"UnitDamage","Data":{"unit":"Hovercopter(Clone)","damage":0.25,"hp":0.0,"attacker":"Assault Cannon"}},{"Timestamp":95.6433945,"Name":"UnitDamage","Data":{"unit":"Hovercopter(Clone)","damage":12.0,"hp":0.0,"attacker":"Plasma Lance"}},{"Timestamp":95.65773,"Name":"UnitDamage","Data":{"unit":"Hovercopter(Clone)","damage":0.25,"hp":0.0,"attacker":"Assault Cannon"}},{"Timestamp":95.7309341,"Name":"UnitDamage","Data":{"unit":"Hoverbuggy(Clone)","damage":0.25,"hp":6.0,"attacker":"Assault Cannon"}},{"Timestamp":95.8125839,"Name":"UnitDamage","Data":{"unit":"Hoverbuggy(Clone)","damage":0.25,"hp":5.75,"attacker":"Assault Cannon"}},{"Timestamp":95.81262,"Name":"UnitDamage","Data":{"unit":"Hoverbuggy(Clone)","damage":0.25,"hp":5.5,"attacker":"Assault Cannon"}},{"Timestamp":95.83952,"Name":"UnitDamage","Data":{"unit":"Hoverbuggy(Clone)","damage":0.25,"hp":5.25,"attacker":"Assault Cannon"}},{"Timestamp":95.87337,"Name":"TowerDamaged","Data":{"damagedTower":"LaserTower(Clone)","X":0,"Y":0,"towerDamage":2.0,"hp":1.0}},{"Timestamp":95.87339,"Name":"TowerDestroyed","Data":{"destroyedTower":"LaserTower(Clone)","X":0,"Y":0}},{"Timestamp":95.87341,"Name":"UnitDamage","Data":{"unit":"Hoverbuggy(Clone)","damage":0.25,"hp":5.0,"attacker":"Assault Cannon"}},{"Timestamp":95.9972839,"Name":"UnitDamage","Data":{"unit":"Hoverbuggy(Clone)","damage":0.25,"hp":4.75,"attacker":"Assault Cannon"}},{"Timestamp":96.06115,"Name":"UnitDamage","Data":{"unit":"Hoverbuggy(Clone)","damage":0.25,"hp":4.5,"attacker":"Assault Cannon"}},{"Timestamp":96.08505,"Name":"UnitDamage","Data":{"unit":"Hoverbuggy(Clone)","damage":0.25,"hp":4.25,"attacker":"Assault Cannon"}},{"Timestamp":96.10142,"Name":"UnitDamage","Data":{"unit":"Hoverbuggy(Clone)","damage":0.25,"hp":4.0,"attacker":"Assault Cannon"}},{"Timestamp":96.1296158,"Name":"UnitDamage","Data":{"unit":"Hoverbuggy(Clone)","damage":0.25,"hp":3.75,"attacker":"Assault Cannon"}},{"Timestamp":96.1401,"Name":"UnitDamage","Data":{"unit":"Hoverbuggy(Clone)","damage":0.25,"hp":3.5,"attacker":"Assault Cannon"}},{"Timestamp":96.242485,"Name":"UnitDamage","Data":{"unit":"Hoverbuggy(Clone)","damage":0.25,"hp":3.25,"attacker":"Assault Cannon"}},{"Timestamp":96.318924,"Name":"UnitDamage","Data":{"unit":"Hoverbuggy(Clone)","damage":0.25,"hp":3.0,"attacker":"Assault Cannon"}},{"Timestamp":96.33869,"Name":"UnitDamage","Data":{"unit":"Hoverbuggy(Clone)","damage":0.25,"hp":2.75,"attacker":"Assault Cannon"}},{"Timestamp":96.35593,"Name":"UnitDamage","Data":{"unit":"Hoverbuggy(Clone)","damage":0.25,"hp":2.5,"attacker":"Assault Cannon"}},{"Timestamp":96.37181,"Name":"UnitDamage","Data":{"unit":"Hoverbuggy(Clone)","damage":0.25,"hp":2.25,"attacker":"Assault Cannon"}},{"Timestamp":96.3801651,"Name":"UnitDamage","Data":{"unit":"Hoverbuggy(Clone)","damage":0.25,"hp":2.0,"attacker":"Assault Cannon"}},{"Timestamp":96.50326,"Name":"UnitDamage","Data":{"unit":"Hoverbuggy(Clone)","damage":0.25,"hp":1.75,"attacker":"Assault Cannon"}},{"Timestamp":96.56956,"Name":"UnitSpawn","Data":{"unitSpawned":"Hovercopter","unitCount":42}},{"Timestamp":96.57864,"Name":"UnitDamage","Data":{"unit":"Hoverbuggy(Clone)","damage":0.25,"hp":1.5,"attacker":"Assault Cannon"}},{"Timestamp":96.5962753,"Name":"UnitDamage","Data":{"unit":"Hoverbuggy(Clone)","damage":0.25,"hp":1.25,"attacker":"Assault Cannon"}},{"Timestamp":96.6035156,"Name":"UnitDamage","Data":{"unit":"Hoverbuggy(Clone)","damage":0.25,"hp":1.0,"attacker":"Assault Cannon"}},{"Timestamp":96.63329,"Name":"UnitDamage","Data":{"unit":"Hoverbuggy(Clone)","damage":0.25,"hp":0.75,"attacker":"Assault Cannon"}},{"Timestamp":96.63333,"Name":"UnitDamage","Data":{"unit":"Hoverbuggy(Clone)","damage":0.25,"hp":0.5,"attacker":"Assault Cannon"}},{"Timestamp":96.7648,"Name":"UnitDamage","Data":{"unit":"Hoverbuggy(Clone)","damage":0.25,"hp":0.25,"attacker":"Assault Cannon"}},{"Timestamp":96.76482,"Name":"UnitDeath","Data":{"unit":"Hoverbuggy(Clone)","overkillDamage":0.0,"killTower":"Assault Cannon"}},{"Timestamp":96.82698,"Name":"UnitDamage","Data":{"unit":"Hoverbuggy(Clone)","damage":0.25,"hp":0.0,"attacker":"Assault Cannon"}},{"Timestamp":96.85244,"Name":"UnitDamage","Data":{"unit":"Hoverbuggy(Clone)","damage":0.25,"hp":0.0,"attacker":"Assault Cannon"}},{"Timestamp":96.85948,"Name":"UnitDamage","Data":{"unit":"Hoverbuggy(Clone)","damage":0.25,"hp":0.0,"attacker":"Assault Cannon"}},{"Timestamp":96.9071,"Name":"TowerDamaged","Data":{"damagedTower":"LaserTower(Clone)","X":1,"Y":1,"towerDamage":2.0,"hp":5.0}},{"Timestamp":97.74478,"Name":"UnitDamage","Data":{"unit":"Hovercopter(Clone)","damage":0.25,"hp":16.0,"attacker":"Assault Cannon"}},{"Timestamp":97.9181747,"Name":"TowerDamaged","Data":{"damagedTower":"LaserTower(Clone)","X":1,"Y":1,"towerDamage":2.0,"hp":3.0}},{"Timestamp":98.00786,"Name":"UnitDamage","Data":{"unit":"Hovercopter(Clone)","damage":0.25,"hp":15.75,"attacker":"Assault Cannon"}},{"Timestamp":98.0568848,"Name":"UnitDamage","Data":{"unit":"Hovercopter(Clone)","damage":0.25,"hp":15.5,"attacker":"Assault Cannon"}},{"Timestamp":98.26961,"Name":"UnitDamage","Data":{"unit":"Hovercopter(Clone)","damage":0.25,"hp":15.25,"attacker":"Assault Cannon"}},{"Timestamp":98.31115,"Name":"UnitDamage","Data":{"unit":"Hovercopter(Clone)","damage":0.25,"hp":15.0,"attacker":"Assault Cannon"}},{"Timestamp":98.31119,"Name":"UnitDamage","Data":{"unit":"Hovercopter(Clone)","damage":0.25,"hp":14.75,"attacker":"Assault Cannon"}},{"Timestamp":98.3203659,"Name":"UnitDamage","Data":{"unit":"Hovercopter(Clone)","damage":0.25,"hp":14.5,"attacker":"Assault Cannon"}},{"Timestamp":98.40984,"Name":"UnitDamage","Data":{"unit":"Hovercopter(Clone)","damage":0.25,"hp":14.25,"attacker":"Assault Cannon"}},{"Timestamp":98.51513,"Name":"UnitDamage","Data":{"unit":"Hovercopter(Clone)","damage":0.25,"hp":14.0,"attacker":"Assault Cannon"}},{"Timestamp":98.5684738,"Name":"UnitDamage","Data":{"unit":"Hovercopter(Clone)","damage":0.25,"hp":13.75,"attacker":"Assault Cannon"}},{"Timestamp":98.56851,"Name":"UnitDamage","Data":{"unit":"Hovercopter(Clone)","damage":0.25,"hp":13.5,"attacker":"Assault Cannon"}},{"Timestamp":98.57754,"Name":"UnitSpawn","Data":{"unitSpawned":"Hovercopter","unitCount":43}},{"Timestamp":98.57762,"Name":"UnitDamage","Data":{"unit":"Hovercopter(Clone)","damage":0.25,"hp":13.25,"attacker":"Assault Cannon"}},{"Timestamp":98.64268,"Name":"UnitDamage","Data":{"unit":"Hovercopter(Clone)","damage":0.25,"hp":13.0,"attacker":"Assault Cannon"}},{"Timestamp":98.661644,"Name":"UnitDamage","Data":{"unit":"Hovercopter(Clone)","damage":0.25,"hp":12.75,"attacker":"Assault Cannon"}},{"Timestamp":98.77841,"Name":"UnitDamage","Data":{"unit":"Hovercopter(Clone)","damage":0.25,"hp":12.5,"attacker":"Assault Cannon"}},{"Timestamp":98.81524,"Name":"UnitDamage","Data":{"unit":"Hovercopter(Clone)","damage":0.25,"hp":12.25,"attacker":"Assault Cannon"}},{"Timestamp":98.81527,"Name":"UnitDamage","Data":{"unit":"Hovercopter(Clone)","damage":0.25,"hp":12.0,"attacker":"Assault Cannon"}},{"Timestamp":98.833374,"Name":"UnitDamage","Data":{"unit":"Hovercopter(Clone)","damage":0.25,"hp":11.75,"attacker":"Assault Cannon"}},{"Timestamp":98.89961,"Name":"UnitDamage","Data":{"unit":"Hovercopter(Clone)","damage":0.25,"hp":11.5,"attacker":"Assault Cannon"}},{"Timestamp":98.9086,"Name":"UnitDamage","Data":{"unit":"Hovercopter(Clone)","damage":12.0,"hp":11.25,"attacker":"Plasma Lance"}},{"Timestamp":98.9086151,"Name":"UnitDeath","Data":{"unit":"Hovercopter(Clone)","overkillDamage":0.75,"killTower":"Plasma Lance"}},{"Timestamp":98.91755,"Name":"TowerDamaged","Data":{"damagedTower":"LaserTower(Clone)","X":1,"Y":1,"towerDamage":2.0,"hp":1.0}},{"Timestamp":98.9175644,"Name":"TowerDestroyed","Data":{"destroyedTower":"LaserTower(Clone)","X":1,"Y":1}},{"Timestamp":98.91759,"Name":"UnitDamage","Data":{"unit":"Hovercopter(Clone)","damage":0.25,"hp":0.0,"attacker":"Assault Cannon"}},{"Timestamp":98.96491,"Name":"UnitDamage","Data":{"unit":"Hovercopter(Clone)","damage":12.0,"hp":0.0,"attacker":"Plasma Lance"}},{"Timestamp":99.82789,"Name":"UnitDamage","Data":{"unit":"Hovercopter(Clone)","damage":0.25,"hp":16.0,"attacker":"Assault Cannon"}},{"Timestamp":99.94837,"Name":"TowerDamaged","Data":{"damagedTower":"MachineGunTower(Clone)","X":1,"Y":0,"towerDamage":2.0,"hp":5.0}},{"Timestamp":100.296478,"Name":"Economy","Data":{"team":"Defender","currency":10.0,"income":0.0}},{"Timestamp":100.296494,"Name":"Economy","Data":{"team":"Attacker","currency":87.0,"income":85.0}},{"Timestamp":100.377426,"Name":"UnitDamage","Data":{"unit":"Hovercopter(Clone)","damage":0.25,"hp":15.75,"attacker":"Assault Cannon"}},{"Timestamp":100.441582,"Name":"UnitDamage","Data":{"unit":"Hovercopter(Clone)","damage":0.25,"hp":15.5,"attacker":"Assault Cannon"}},{"Timestamp":100.462959,"Name":"UnitDamage","Data":{"unit":"Hovercopter(Clone)","damage":0.25,"hp":15.25,"attacker":"Assault Cannon"}},{"Timestamp":100.48909,"Name":"UnitDamage","Data":{"unit":"Hovercopter(Clone)","damage":0.25,"hp":15.0,"attacker":"Assault Cannon"}},{"Timestamp":100.531418,"Name":"UnitDamage","Data":{"unit":"Hovercopter(Clone)","damage":0.25,"hp":14.75,"attacker":"Assault Cannon"}},{"Timestamp":100.594833,"Name":"UnitSpawn","Data":{"unitSpawned":"Hovertank","unitCount":44}},{"Timestamp":100.630424,"Name":"UnitDamage","Data":{"unit":"Hovercopter(Clone)","damage":0.25,"hp":14.5,"attacker":"Assault Cannon"}},{"Timestamp":100.699867,"Name":"UnitDamage","Data":{"unit":"Hovercopter(Clone)","damage":0.25,"hp":14.25,"attacker":"Assault Cannon"}},{"Timestamp":100.708321,"Name":"UnitDamage","Data":{"unit":"Hovercopter(Clone)","damage":0.25,"hp":14.0,"attacker":"Assault Cannon"}},{"Timestamp":100.758217,"Name":"UnitDamage","Data":{"unit":"Hovercopter(Clone)","damage":0.25,"hp":13.75,"attacker":"Assault Cannon"}},{"Timestamp":100.7859,"Name":"UnitDamage","Data":{"unit":"Hovercopter(Clone)","damage":0.25,"hp":13.5,"attacker":"Assault Cannon"}},{"Timestamp":100.820641,"Name":"UnitDamage","Data":{"unit":"Hovercopter(Clone)","damage":0.25,"hp":13.25,"attacker":"Assault Cannon"}},{"Timestamp":100.888405,"Name":"UnitDamage","Data":{"unit":"Hovercopter(Clone)","damage":0.25,"hp":13.0,"attacker":"Assault Cannon"}},{"Timestamp":100.953117,"Name":"UnitDamage","Data":{"unit":"Hovercopter(Clone)","damage":0.25,"hp":12.75,"attacker":"Assault Cannon"}},{"Timestamp":100.962074,"Name":"TowerDamaged","Data":{"damagedTower":"MachineGunTower(Clone)","X":1,"Y":0,"towerDamage":2.0,"hp":3.0}},{"Timestamp":100.972572,"Name":"UnitDamage","Data":{"unit":"Hovercopter(Clone)","damage":0.25,"hp":12.5,"attacker":"Assault Cannon"}},{"Timestamp":100.990883,"Name":"UnitDamage","Data":{"unit":"Hovercopter(Clone)","damage":0.25,"hp":12.25,"attacker":"Assault Cannon"}},{"Timestamp":101.048241,"Name":"UnitDamage","Data":{"unit":"Hovercopter(Clone)","damage":0.25,"hp":12.0,"attacker":"Assault Cannon"}},{"Timestamp":101.087837,"Name":"UnitDamage","Data":{"unit":"Hovercopter(Clone)","damage":0.25,"hp":11.75,"attacker":"Assault Cannon"}},{"Timestamp":101.142593,"Name":"UnitDamage","Data":{"unit":"Hovercopter(Clone)","damage":0.25,"hp":11.5,"attacker":"Assault Cannon"}},{"Timestamp":101.142632,"Name":"UnitDamage","Data":{"unit":"Hovercopter(Clone)","damage":0.25,"hp":11.25,"attacker":"Assault Cannon"}},{"Timestamp":101.202065,"Name":"UnitDamage","Data":{"unit":"Hovercopter(Clone)","damage":0.25,"hp":11.0,"attacker":"Assault Cannon"}},{"Timestamp":101.221458,"Name":"UnitDamage","Data":{"unit":"Hovercopter(Clone)","damage":0.25,"hp":10.75,"attacker":"Assault Cannon"}},{"Timestamp":101.25132,"Name":"UnitDamage","Data":{"unit":"Hovercopter(Clone)","damage":0.25,"hp":10.5,"attacker":"Assault Cannon"}},{"Timestamp":101.293396,"Name":"UnitDamage","Data":{"unit":"Hovercopter(Clone)","damage":0.25,"hp":10.25,"attacker":"Assault Cannon"}},{"Timestamp":101.335449,"Name":"UnitDamage","Data":{"unit":"Hovercopter(Clone)","damage":0.25,"hp":10.0,"attacker":"Assault Cannon"}},{"Timestamp":101.408051,"Name":"UnitDamage","Data":{"unit":"Hovercopter(Clone)","damage":0.25,"hp":9.75,"attacker":"Assault Cannon"}},{"Timestamp":101.4081,"Name":"UnitDamage","Data":{"unit":"Hovercopter(Clone)","damage":0.25,"hp":9.5,"attacker":"Assault Cannon"}},{"Timestamp":101.458122,"Name":"UnitDamage","Data":{"unit":"Hovercopter(Clone)","damage":0.25,"hp":9.25,"attacker":"Assault Cannon"}},{"Timestamp":101.477074,"Name":"UnitDamage","Data":{"unit":"Hovercopter(Clone)","damage":0.25,"hp":9.0,"attacker":"Assault Cannon"}},{"Timestamp":101.50296,"Name":"UnitDamage","Data":{"unit":"Hovercopter(Clone)","damage":0.25,"hp":8.75,"attacker":"Assault Cannon"}},{"Timestamp":101.552361,"Name":"UnitDamage","Data":{"unit":"Hovercopter(Clone)","damage":0.25,"hp":8.5,"attacker":"Assault Cannon"}},{"Timestamp":101.59819,"Name":"UnitDamage","Data":{"unit":"Hovercopter(Clone)","damage":0.25,"hp":8.25,"attacker":"Assault Cannon"}},{"Timestamp":101.645958,"Name":"UnitDamage","Data":{"unit":"Hovercopter(Clone)","damage":0.25,"hp":8.0,"attacker":"Assault Cannon"}},{"Timestamp":101.645988,"Name":"UnitDamage","Data":{"unit":"Hovercopter(Clone)","damage":0.25,"hp":7.75,"attacker":"Assault Cannon"}},{"Timestamp":101.714493,"Name":"UnitDamage","Data":{"unit":"Hovercopter(Clone)","damage":0.25,"hp":7.5,"attacker":"Assault Cannon"}},{"Timestamp":101.736374,"Name":"TowerBuilding","Data":{"tower":"Assault Cannon","X":5,"Y":1}},{"Timestamp":101.748352,"Name":"UnitDamage","Data":{"unit":"Hovercopter(Clone)","damage":0.25,"hp":7.25,"attacker":"Assault Cannon"}},{"Timestamp":101.764244,"Name":"UnitDamage","Data":{"unit":"Hovercopter(Clone)","damage":0.25,"hp":7.0,"attacker":"Assault Cannon"}},{"Timestamp":101.815208,"Name":"UnitDamage","Data":{"unit":"Hovercopter(Clone)","damage":0.25,"hp":6.75,"attacker":"Assault Cannon"}},{"Timestamp":101.834167,"Name":"TowerDamaged","Data":{"damagedTower":"MachineGunTower(Clone)","X":1,"Y":0,"towerDamage":2.0,"hp":1.0}},{"Timestamp":101.834183,"Name":"TowerDestroyed","Data":{"destroyedTower":"MachineGunTower(Clone)","X":1,"Y":0}},{"Timestamp":101.857422,"Name":"UnitDamage","Data":{"unit":"Hovercopter(Clone)","damage":0.25,"hp":6.5,"attacker":"Assault Cannon"}},{"Timestamp":101.911369,"Name":"UnitDamage","Data":{"unit":"Hovercopter(Clone)","damage":0.25,"hp":6.25,"attacker":"Assault Cannon"}},{"Timestamp":101.911407,"Name":"UnitDamage","Data":{"unit":"Hovercopter(Clone)","damage":0.25,"hp":6.0,"attacker":"Assault Cannon"}},{"Timestamp":101.978745,"Name":"UnitDamage","Data":{"unit":"Hovercopter(Clone)","damage":0.25,"hp":5.75,"attacker":"Assault Cannon"}},{"Timestamp":101.98835,"Name":"UnitDamage","Data":{"unit":"Hovercopter(Clone)","damage":0.25,"hp":5.5,"attacker":"Assault Cannon"}},{"Timestamp":102.015343,"Name":"UnitDamage","Data":{"unit":"Hovercopter(Clone)","damage":0.25,"hp":5.25,"attacker":"Assault Cannon"}},{"Timestamp":102.078766,"Name":"UnitDamage","Data":{"unit":"Hovercopter(Clone)","damage":0.25,"hp":5.0,"attacker":"Assault Cannon"}},{"Timestamp":102.0788,"Name":"UnitDamage","Data":{"unit":"Hovercopter(Clone)","damage":0.25,"hp":4.75,"attacker":"Assault Cannon"}},{"Timestamp":102.113106,"Name":"UnitDamage","Data":{"unit":"Hovercopter(Clone)","damage":0.25,"hp":4.5,"attacker":"Assault Cannon"}},{"Timestamp":102.151855,"Name":"UnitDamage","Data":{"unit":"Hovercopter(Clone)","damage":0.25,"hp":4.25,"attacker":"Assault Cannon"}},{"Timestamp":102.235085,"Name":"UnitDamage","Data":{"unit":"Hovercopter(Clone)","damage":0.25,"hp":4.0,"attacker":"Assault Cannon"}},{"Timestamp":102.24482,"Name":"UnitDamage","Data":{"unit":"Hovercopter(Clone)","damage":0.25,"hp":3.75,"attacker":"Assault Cannon"}},{"Timestamp":102.270973,"Name":"UnitDamage","Data":{"unit":"Hovercopter(Clone)","damage":0.25,"hp":3.5,"attacker":"Assault Cannon"}},{"Timestamp":102.30674,"Name":"UnitDamage","Data":{"unit":"Hovercopter(Clone)","damage":12.0,"hp":3.25,"attacker":"Plasma Lance"}},{"Timestamp":102.306755,"Name":"UnitDeath","Data":{"unit":"Hovercopter(Clone)","overkillDamage":8.75,"killTower":"Plasma Lance"}},{"Timestamp":102.314171,"Name":"UnitDamage","Data":{"unit":"Hovercopter(Clone)","damage":0.25,"hp":0.0,"attacker":"Assault Cannon"}},{"Timestamp":102.348953,"Name":"UnitDamage","Data":{"unit":"Hovercopter(Clone)","damage":0.25,"hp":0.0,"attacker":"Assault Cannon"}},{"Timestamp":102.366287,"Name":"UnitDamage","Data":{"unit":"Hovercopter(Clone)","damage":0.25,"hp":0.0,"attacker":"Assault Cannon"}},{"Timestamp":102.412338,"Name":"UnitDamage","Data":{"unit":"Hovercopter(Clone)","damage":0.25,"hp":0.0,"attacker":"Assault Cannon"}},{"Timestamp":102.598091,"Name":"UnitSpawn","Data":{"unitSpawned":"Hovercopter","unitCount":45}},{"Timestamp":102.85585,"Name":"TowerDamaged","Data":{"damagedTower":"MachineGunTower(Clone)","X":2,"Y":0,"towerDamage":2.0,"hp":5.0}},{"Timestamp":103.00103,"Name":"TowerDamaged","Data":{"damagedTower":"MachineGunTower(Clone)","X":2,"Y":0,"towerDamage":2.0,"hp":3.0}},{"Timestamp":103.859322,"Name":"TowerDamaged","Data":{"damagedTower":"MachineGunTower(Clone)","X":2,"Y":0,"towerDamage":2.0,"hp":1.0}},{"Timestamp":103.859337,"Name":"TowerDestroyed","Data":{"destroyedTower":"MachineGunTower(Clone)","X":2,"Y":0}},{"Timestamp":104.34819,"Name":"UnitDamage","Data":{"unit":"Hovercopter(Clone)","damage":0.25,"hp":16.0,"attacker":"Assault Cannon"}},{"Timestamp":104.348213,"Name":"UnitDamage","Data":{"unit":"Hovercopter(Clone)","damage":0.25,"hp":15.75,"attacker":"Assault Cannon"}},{"Timestamp":104.390739,"Name":"UnitDamage","Data":{"unit":"Hovercopter(Clone)","damage":0.25,"hp":15.5,"attacker":"Assault Cannon"}},{"Timestamp":104.608376,"Name":"UnitDamage","Data":{"unit":"Hovercopter(Clone)","damage":0.25,"hp":15.25,"attacker":"Assault Cannon"}},{"Timestamp":104.608414,"Name":"UnitDamage","Data":{"unit":"Hovercopter(Clone)","damage":0.25,"hp":15.0,"attacker":"Assault Cannon"}},{"Timestamp":104.639847,"Name":"UnitDamage","Data":{"unit":"Hovercopter(Clone)","damage":0.25,"hp":14.75,"attacker":"Assault Cannon"}},{"Timestamp":104.678795,"Name":"UnitDamage","Data":{"unit":"Hovercopter(Clone)","damage":0.25,"hp":14.5,"attacker":"Assault Cannon"}},{"Timestamp":104.856544,"Name":"UnitDamage","Data":{"unit":"Hovercopter(Clone)","damage":0.25,"hp":14.25,"attacker":"Assault Cannon"}},{"Timestamp":104.856575,"Name":"UnitDamage","Data":{"unit":"Hovercopter(Clone)","damage":0.25,"hp":14.0,"attacker":"Assault Cannon"}},{"Timestamp":104.8971,"Name":"TowerDamaged","Data":{"damagedTower":"MachineGunTower(Clone)","X":3,"Y":0,"towerDamage":2.0,"hp":5.0}},{"Timestamp":104.897125,"Name":"UnitDamage","Data":{"unit":"Hovercopter(Clone)","damage":0.25,"hp":13.75,"attacker":"Assault Cannon"}},{"Timestamp":104.932022,"Name":"UnitDamage","Data":{"unit":"Hovercopter(Clone)","damage":0.25,"hp":13.5,"attacker":"Assault Cannon"}},{"Timestamp":105.009415,"Name":"UnitDamage","Data":{"unit":"Hovercopter(Clone)","damage":0.25,"hp":13.25,"attacker":"Assault Cannon"}},{"Timestamp":105.036667,"Name":"TowerDamaged","Data":{"damagedTower":"MachineGunTower(Clone)","X":3,"Y":2,"towerDamage":2.0,"hp":5.0}},{"Timestamp":105.076286,"Name":"UnitDamage","Data":{"unit":"Hovercopter(Clone)","damage":0.25,"hp":13.0,"attacker":"Assault Cannon"}},{"Timestamp":105.116768,"Name":"UnitDamage","Data":{"unit":"Hovercopter(Clone)","damage":0.25,"hp":12.75,"attacker":"Assault Cannon"}},{"Timestamp":105.116806,"Name":"UnitDamage","Data":{"unit":"Hovercopter(Clone)","damage":0.25,"hp":12.5,"attacker":"Assault Cannon"}},{"Timestamp":105.146835,"Name":"UnitDamage","Data":{"unit":"Hovercopter(Clone)","damage":0.25,"hp":12.25,"attacker":"Assault Cannon"}},{"Timestamp":105.199333,"Name":"UnitDamage","Data":{"unit":"Hovercopter(Clone)","damage":0.25,"hp":12.0,"attacker":"Assault Cannon"}},{"Timestamp":105.264626,"Name":"UnitDamage","Data":{"unit":"Hovercopter(Clone)","damage":0.25,"hp":11.75,"attacker":"Assault Cannon"}},{"Timestamp":105.272827,"Name":"Economy","Data":{"team":"Defender","currency":5.0,"income":0.0}},{"Timestamp":105.272842,"Name":"Economy","Data":{"team":"Attacker","currency":85.0,"income":85.0}},{"Timestamp":105.334488,"Name":"UnitDamage","Data":{"unit":"Hovercopter(Clone)","damage":0.25,"hp":11.5,"attacker":"Assault Cannon"}},{"Timestamp":105.379112,"Name":"UnitDamage","Data":{"unit":"Hovercopter(Clone)","damage":0.25,"hp":11.25,"attacker":"Assault Cannon"}},{"Timestamp":105.37915,"Name":"UnitDamage","Data":{"unit":"Hovercopter(Clone)","damage":0.25,"hp":11.0,"attacker":"Assault Cannon"}},{"Timestamp":105.402763,"Name":"UnitDamage","Data":{"unit":"Hovercopter(Clone)","damage":0.25,"hp":10.75,"attacker":"Assault Cannon"}},{"Timestamp":105.442078,"Name":"UnitDamage","Data":{"unit":"Hovercopter(Clone)","damage":0.25,"hp":10.5,"attacker":"Assault Cannon"}},{"Timestamp":105.533089,"Name":"UnitDamage","Data":{"unit":"Hovercopter(Clone)","damage":0.25,"hp":10.25,"attacker":"Assault Cannon"}},{"Timestamp":105.593338,"Name":"UnitDamage","Data":{"unit":"Hovercopter(Clone)","damage":0.25,"hp":10.0,"attacker":"Assault Cannon"}},{"Timestamp":105.619339,"Name":"UnitDamage","Data":{"unit":"Hovercopter(Clone)","damage":0.25,"hp":9.75,"attacker":"Assault Cannon"}},{"Timestamp":105.61937,"Name":"UnitDamage","Data":{"unit":"Hovercopter(Clone)","damage":0.25,"hp":9.5,"attacker":"Assault Cannon"}},{"Timestamp":105.643463,"Name":"UnitDamage","Data":{"unit":"Hovercopter(Clone)","damage":12.0,"hp":9.25,"attacker":"Plasma Lance"}},{"Timestamp":105.643478,"Name":"UnitDeath","Data":{"unit":"Hovercopter(Clone)","overkillDamage":2.75,"killTower":"Plasma Lance"}},{"Timestamp":105.659439,"Name":"UnitDamage","Data":{"unit":"Hovercopter(Clone)","damage":0.25,"hp":0.0,"attacker":"Assault Cannon"}},{"Timestamp":105.709366,"Name":"UnitDamage","Data":{"unit":"Hovercopter(Clone)","damage":0.25,"hp":0.0,"attacker":"Assault Cannon"}},{"Timestamp":105.892319,"Name":"TowerDamaged","Data":{"damagedTower":"MachineGunTower(Clone)","X":3,"Y":0,"towerDamage":2.0,"hp":3.0}},{"Timestamp":106.03566,"Name":"TowerDamaged","Data":{"damagedTower":"MachineGunTower(Clone)","X":3,"Y":2,"towerDamage":2.0,"hp":3.0}},{"Timestamp":106.195412,"Name":"TowerBuilding","Data":{"tower":"Assault Cannon","X":5,"Y":2}},{"Timestamp":106.903084,"Name":"TowerDamaged","Data":{"damagedTower":"MachineGunTower(Clone)","X":3,"Y":0,"towerDamage":2.0,"hp":1.0}},{"Timestamp":106.9031,"Name":"TowerDestroyed","Data":{"destroyedTower":"MachineGunTower(Clone)","X":3,"Y":0}},{"Timestamp":107.036156,"Name":"TowerDamaged","Data":{"damagedTower":"MachineGunTower(Clone)","X":3,"Y":2,"towerDamage":2.0,"hp":1.0}},{"Timestamp":107.036171,"Name":"TowerDestroyed","Data":{"destroyedTower":"MachineGunTower(Clone)","X":3,"Y":2}},{"Timestamp":107.928665,"Name":"TowerDamaged","Data":{"damagedTower":"MachineGunTower(Clone)","X":3,"Y":1,"towerDamage":2.0,"hp":5.0}},{"Timestamp":108.066093,"Name":"TowerDamaged","Data":{"damagedTower":"MachineGunTower(Clone)","X":3,"Y":1,"towerDamage":2.0,"hp":3.0}},{"Timestamp":108.937508,"Name":"TowerDamaged","Data":{"damagedTower":"MachineGunTower(Clone)","X":3,"Y":1,"towerDamage":2.0,"hp":1.0}},{"Timestamp":108.937531,"Name":"TowerDestroyed","Data":{"destroyedTower":"MachineGunTower(Clone)","X":3,"Y":1}},{"Timestamp":109.956604,"Name":"TowerDamaged","Data":{"damagedTower":"LaserTower(Clone)","X":4,"Y":0,"towerDamage":2.0,"hp":5.0}},{"Timestamp":110.0898,"Name":"TowerDamaged","Data":{"damagedTower":"MachineGunTower(Clone)","X":4,"Y":1,"towerDamage":2.0,"hp":5.0}},{"Timestamp":110.278687,"Name":"Economy","Data":{"team":"Defender","currency":0.0,"income":0.0}},{"Timestamp":110.278694,"Name":"Economy","Data":{"team":"Attacker","currency":85.0,"income":85.0}},{"Timestamp":110.975082,"Name":"TowerDamaged","Data":{"damagedTower":"LaserTower(Clone)","X":4,"Y":0,"towerDamage":2.0,"hp":3.0}},{"Timestamp":111.093849,"Name":"TowerDamaged","Data":{"damagedTower":"MachineGunTower(Clone)","X":4,"Y":1,"towerDamage":2.0,"hp":3.0}},{"Timestamp":111.979546,"Name":"TowerDamaged","Data":{"damagedTower":"LaserTower(Clone)","X":4,"Y":0,"towerDamage":2.0,"hp":1.0}},{"Timestamp":111.979568,"Name":"TowerDestroyed","Data":{"destroyedTower":"LaserTower(Clone)","X":4,"Y":0}},{"Timestamp":112.094063,"Name":"TowerDamaged","Data":{"damagedTower":"MachineGunTower(Clone)","X":4,"Y":1,"towerDamage":2.0,"hp":1.0}},{"Timestamp":112.094078,"Name":"TowerDestroyed","Data":{"destroyedTower":"MachineGunTower(Clone)","X":4,"Y":1}},{"Timestamp":113.133911,"Name":"TowerDamaged","Data":{"damagedTower":"MachineGunTower(Clone)","X":5,"Y":2,"towerDamage":2.0,"hp":5.0}},{"Timestamp":113.899857,"Name":"TowerDamaged","Data":{"damagedTower":"MachineGunTower(Clone)","X":5,"Y":1,"towerDamage":2.0,"hp":5.0}},{"Timestamp":114.123665,"Name":"TowerDamaged","Data":{"damagedTower":"MachineGunTower(Clone)","X":5,"Y":2,"towerDamage":2.0,"hp":3.0}},{"Timestamp":114.911171,"Name":"TowerDamaged","Data":{"damagedTower":"MachineGunTower(Clone)","X":5,"Y":1,"towerDamage":2.0,"hp":3.0}},{"Timestamp":115.134438,"Name":"TowerDamaged","Data":{"damagedTower":"MachineGunTower(Clone)","X":5,"Y":2,"towerDamage":2.0,"hp":1.0}},{"Timestamp":115.134453,"Name":"TowerDestroyed","Data":{"destroyedTower":"MachineGunTower(Clone)","X":5,"Y":2}},{"Timestamp":115.285095,"Name":"Economy","Data":{"team":"Defender","currency":0.0,"income":0.0}},{"Timestamp":115.2851,"Name":"Economy","Data":{"team":"Attacker","currency":85.0,"income":85.0}},{"Timestamp":115.924965,"Name":"TowerDamaged","Data":{"damagedTower":"MachineGunTower(Clone)","X":5,"Y":1,"towerDamage":2.0,"hp":1.0}},{"Timestamp":115.924988,"Name":"TowerDestroyed","Data":{"destroyedTower":"MachineGunTower(Clone)","X":5,"Y":1}},{"Timestamp":118.5387,"Name":"UnitDamage","Data":{"unit":"Hovertank(Clone)","damage":0.25,"hp":35.0,"attacker":"Assault Cannon"}},{"Timestamp":118.788239,"Name":"UnitDamage","Data":{"unit":"Hovertank(Clone)","damage":0.25,"hp":34.75,"attacker":"Assault Cannon"}},{"Timestamp":119.04306,"Name":"UnitDamage","Data":{"unit":"Hovertank(Clone)","damage":0.25,"hp":34.5,"attacker":"Assault Cannon"}},{"Timestamp":119.298218,"Name":"UnitDamage","Data":{"unit":"Hovertank(Clone)","damage":0.25,"hp":34.25,"attacker":"Assault Cannon"}},{"Timestamp":119.562973,"Name":"UnitDamage","Data":{"unit":"Hovertank(Clone)","damage":0.25,"hp":34.0,"attacker":"Assault Cannon"}},{"Timestamp":119.798668,"Name":"UnitDamage","Data":{"unit":"Hovertank(Clone)","damage":0.25,"hp":33.75,"attacker":"Assault Cannon"}},{"Timestamp":120.063759,"Name":"UnitDamage","Data":{"unit":"Hovertank(Clone)","damage":0.25,"hp":33.5,"attacker":"Assault Cannon"}},{"Timestamp":120.290504,"Name":"Economy","Data":{"team":"Defender","currency":0.0,"income":0.0}},{"Timestamp":120.29052,"Name":"Economy","Data":{"team":"Attacker","currency":85.0,"income":85.0}},{"Timestamp":120.310287,"Name":"UnitDamage","Data":{"unit":"Hovertank(Clone)","damage":0.25,"hp":33.25,"attacker":"Assault Cannon"}},{"Timestamp":120.569878,"Name":"UnitDamage","Data":{"unit":"Hovertank(Clone)","damage":0.25,"hp":33.0,"attacker":"Assault Cannon"}},{"Timestamp":120.824936,"Name":"UnitDamage","Data":{"unit":"Hovertank(Clone)","damage":0.25,"hp":32.75,"attacker":"Assault Cannon"}},{"Timestamp":121.07338,"Name":"UnitDamage","Data":{"unit":"Hovertank(Clone)","damage":0.25,"hp":32.5,"attacker":"Assault Cannon"}},{"Timestamp":121.326973,"Name":"UnitDamage","Data":{"unit":"Hovertank(Clone)","damage":0.25,"hp":32.25,"attacker":"Assault Cannon"}},{"Timestamp":121.586472,"Name":"UnitDamage","Data":{"unit":"Hovertank(Clone)","damage":0.25,"hp":32.0,"attacker":"Assault Cannon"}},{"Timestamp":121.837,"Name":"UnitDamage","Data":{"unit":"Hovertank(Clone)","damage":0.25,"hp":31.75,"attacker":"Assault Cannon"}},{"Timestamp":122.092964,"Name":"UnitDamage","Data":{"unit":"Hovertank(Clone)","damage":0.25,"hp":31.5,"attacker":"Assault Cannon"}},{"Timestamp":122.342735,"Name":"UnitDamage","Data":{"unit":"Hovertank(Clone)","damage":0.25,"hp":31.25,"attacker":"Assault Cannon"}},{"Timestamp":122.592369,"Name":"UnitDamage","Data":{"unit":"Hovertank(Clone)","damage":0.25,"hp":31.0,"attacker":"Assault Cannon"}},{"Timestamp":122.856224,"Name":"UnitDamage","Data":{"unit":"Hovertank(Clone)","damage":0.25,"hp":30.75,"attacker":"Assault Cannon"}},{"Timestamp":125.295807,"Name":"Economy","Data":{"team":"Defender","currency":0.0,"income":0.0}},{"Timestamp":125.295815,"Name":"Economy","Data":{"team":"Attacker","currency":85.0,"income":85.0}},{"Timestamp":127.544228,"Name":"BaseDamage","Data":{"damage":1.0,"unitDamaged":"Hovertank(Clone)"}},{"Timestamp":127.814186,"Name":"BaseDamage","Data":{"damage":1.0,"unitDamaged":"Hovertank(Clone)"}},{"Timestamp":127.815369,"Name":"GameEnd","Data":{"winner":1}}]