[{"Timestamp":103.441193,"Name":"RoundStart","Data":{"gameCount":1}},{"Timestamp":103.486954,"Name":"TowerBuilding","Data":{"tower":"Rocket Platform","X":0,"Y":0}},{"Timestamp":103.487045,"Name":"UnitBuying","Data":{"unitBought":"Hovercopter","currentIncome":2}},{"Timestamp":103.503059,"Name":"TowerBuilding","Data":{"tower":"Rocket Platform","X":2,"Y":0}},{"Timestamp":103.503075,"Name":"UnitBuying","Data":{"unitBought":"Hoverbuggy","currentIncome":3}},{"Timestamp":103.504593,"Name":"UnitDamage","Data":{"unit":"Hovercopter(Clone)","damage":0.25,"hp":0.0,"attacker":"Assault Cannon"}},{"Timestamp":103.606804,"Name":"TowerBuilding","Data":{"tower":"Plasma Lance","X":3,"Y":0}},{"Timestamp":103.606827,"Name":"UnitBuying","Data":{"unitBought":"Hoverbuggy","currentIncome":4}},{"Timestamp":103.768478,"Name":"TowerBuilding","Data":{"tower":"Assault Cannon","X":1,"Y":0}},{"Timestamp":103.7685,"Name":"UnitBuying","Data":{"unitBought":"Hovercopter","currentIncome":6}},{"Timestamp":103.933105,"Name":"UnitBuying","Data":{"unitBought":"Hoverbuggy","currentIncome":7}},{"Timestamp":104.102051,"Name":"UnitBuying","Data":{"unitBought":"Hoverbuggy","currentIncome":8}},{"Timestamp":104.108093,"Name":"Economy","Data":{"team":"Defender","currency":1.0,"income":0.0}},{"Timestamp":104.108109,"Name":"Economy","Data":{"team":"Attacker","currency":60.0,"income":8.0}},{"Timestamp":104.266846,"Name":"UnitBuying","Data":{"unitBought":"Hoverbuggy","currentIncome":9}},{"Timestamp":104.429657,"Name":"UnitBuying","Data":{"unitBought":"Hovercopter","currentIncome":11}},{"Timestamp":104.593872,"Name":"UnitBuying","Data":{"unitBought":"Hovercopter","currentIncome":13}},{"Timestamp":104.757629,"Name":"UnitBuying","Data":{"unitBought":"Hoverbuggy","currentIncome":14}},{"Timestamp":104.924164,"Name":"UnitBuying","Data":{"unitBought":"Hoverbuggy","currentIncome":15}},{"Timestamp":105.088455,"Name":"UnitBuying","Data":{"unitBought":"Hoverbuggy","currentIncome":16}},{"Timestamp":105.252007,"Name":"UnitBuying","Data":{"unitBought":"Hoverbuggy","currentIncome":17}},{"Timestamp":105.418045,"Name":"UnitBuying","Data":{"unitBought":"Hoverbuggy","currentIncome":18}},{"Timestamp":105.584061,"Name":"UnitBuying","Data":{"unitBought":"Hovercopter","currentIncome":20}},{"Timestamp":107.570404,"Name":"UnitSpawn","Data":{"unitSpawned":"Hovercopter","unitCount":1}},{"Timestamp":108.224007,"Name":"UnitBuying","Data":{"unitBought":"Hoverbuggy","currentIncome":21}},{"Timestamp":108.387932,"Name":"UnitBuying","Data":{"unitBought":"Hovercopter","currentIncome":23}},{"Timestamp":108.551331,"Name":"UnitBuying","Data":{"unitBought":"Hoverbuggy","currentIncome":24}},{"Timestamp":108.613243,"Name":"UnitDamage","Data":{"unit":"Hovercopter(Clone)","damage":0.25,"hp":16.0,"attacker":"Assault Cannon"}},{"Timestamp":108.765129,"Name":"UnitDamage","Data":{"unit":"Hovercopter(Clone)","damage":12.0,"hp":15.75,"attacker":"Plasma Lance"}},{"Timestamp":108.869423,"Name":"UnitDamage","Data":{"unit":"Hovercopter(Clone)","damage":0.25,"hp":3.75,"attacker":"Assault Cannon"}},{"Timestamp":109.110878,"Name":"Economy","Data":{"team":"Defender","currency":1.0,"income":0.0}},{"Timestamp":109.110886,"Name":"Economy","Data":{"team":"Attacker","currency":0.0,"income":24.0}},{"Timestamp":109.11763,"Name":"UnitDamage","Data":{"unit":"Hovercopter(Clone)","damage":0.25,"hp":3.5,"attacker":"Assault Cannon"}},{"Timestamp":109.383377,"Name":"UnitDamage","Data":{"unit":"Hovercopter(Clone)","damage":0.25,"hp":3.25,"attacker":"Assault Cannon"}},{"Timestamp":109.571434,"Name":"UnitSpawn","Data":{"unitSpawned":"Hoverbuggy","unitCount":2}},{"Timestamp":109.621468,"Name":"UnitDamage","Data":{"unit":"Hovercopter(Clone)","damage":0.25,"hp":3.0,"attacker":"Assault Cannon"}},{"Timestamp":109.881058,"Name":"UnitDamage","Data":{"unit":"Hovercopter(Clone)","damage":0.25,"hp":2.75,"attacker":"Assault Cannon"}},{"Timestamp":110.099388,"Name":"UnitDamage","Data":{"unit":"Hoverbuggy(Clone)","damage":1.5,"hp":6.0,"attacker":"Rocket Platform"}},{"Timestamp":110.099419,"Name":"UnitDamage","Data":{"unit":"Hoverbuggy(Clone)","damage":3.0,"hp":4.5,"attacker":"Rocket Platform"}},{"Timestamp":110.123047,"Name":"UnitDamage","Data":{"unit":"Hovercopter(Clone)","damage":0.25,"hp":2.5,"attacker":"Assault Cannon"}},{"Timestamp":110.381241,"Name":"UnitDamage","Data":{"unit":"Hovercopter(Clone)","damage":0.25,"hp":2.25,"attacker":"Assault Cannon"}},{"Timestamp":110.491341,"Name":"UnitDamage","Data":{"unit":"Hoverbuggy(Clone)","damage":1.5,"hp":1.5,"attacker":"Rocket Platform"}},{"Timestamp":110.491356,"Name":"UnitDeath","Data":{"unit":"Hoverbuggy(Clone)","overkillDamage":0.0,"killTower":"Rocket Platform"}},{"Timestamp":110.491371,"Name":"UnitDamage","Data":{"unit":"Hoverbuggy(Clone)","damage":3.0,"hp":0.0,"attacker":"Rocket Platform"}},{"Timestamp":110.641937,"Name":"UnitDamage","Data":{"unit":"Hovercopter(Clone)","damage":0.25,"hp":2.0,"attacker":"Assault Cannon"}},{"Timestamp":110.892754,"Name":"UnitDamage","Data":{"unit":"Hovercopter(Clone)","damage":0.25,"hp":1.75,"attacker":"Assault Cannon"}},{"Timestamp":111.143867,"Name":"UnitDamage","Data":{"unit":"Hovercopter(Clone)","damage":0.25,"hp":1.5,"attacker":"Assault Cannon"}},{"Timestamp":111.39608,"Name":"UnitDamage","Data":{"unit":"Hovercopter(Clone)","damage":0.25,"hp":1.25,"attacker":"Assault Cannon"}},{"Timestamp":111.572891,"Name":"UnitSpawn","Data":{"unitSpawned":"Hoverbuggy","unitCount":3}},{"Timestamp":112.113617,"Name":"UnitDamage","Data":{"unit":"Hovercopter(Clone)","damage":12.0,"hp":1.0,"attacker":"Plasma Lance"}},{"Timestamp":112.113625,"Name":"UnitDeath","Data":{"unit":"Hovercopter(Clone)","overkillDamage":11.0,"killTower":"Plasma Lance"}},{"Timestamp":112.2724,"Name":"UnitDamage","Data":{"unit":"Hoverbuggy(Clone)","damage":3.0,"hp":6.0,"attacker":"Rocket Platform"}},{"Timestamp":112.27253,"Name":"UnitDamage","Data":{"unit":"Hoverbuggy(Clone)","damage":1.5,"hp":3.0,"attacker":"Rocket Platform"}},{"Timestamp":112.409325,"Name":"UnitDamage","Data":{"unit":"Hoverbuggy(Clone)","damage":0.25,"hp":1.5,"attacker":"Assault Cannon"}},{"Timestamp":112.664,"Name":"UnitDamage","Data":{"unit":"Hoverbuggy(Clone)","damage":0.25,"hp":1.25,"attacker":"Assault Cannon"}},{"Timestamp":112.680794,"Name":"UnitDamage","Data":{"unit":"Hoverbuggy(Clone)","damage":3.0,"hp":1.0,"attacker":"Rocket Platform"}},{"Timestamp":112.680809,"Name":"UnitDeath","Data":{"unit":"Hoverbuggy(Clone)","overkillDamage":2.0,"killTower":"Rocket Platform"}},{"Timestamp":112.84671,"Name":"TowerBuilding","Data":{"tower":"Assault Cannon","X":6,"Y":0}},{"Timestamp":113.173714,"Name":"UnitBuying","Data":{"unitBought":"Hoverbuggy","currentIncome":25}},{"Timestamp":113.572937,"Name":"UnitSpawn","Data":{"unitSpawned":"Hovercopter","unitCount":4}},{"Timestamp":113.6755,"Name":"UnitBuying","Data":{"unitBought":"Hoverbuggy","currentIncome":26}},{"Timestamp":113.8382,"Name":"UnitBuying","Data":{"unitBought":"Hoverbuggy","currentIncome":27}},{"Timestamp":113.996284,"Name":"UnitBuying","Data":{"unitBought":"Hoverbuggy","currentIncome":28}},{"Timestamp":114.111076,"Name":"Economy","Data":{"team":"Defender","currency":0.0,"income":0.0}},{"Timestamp":114.111084,"Name":"Economy","Data":{"team":"Attacker","currency":4.0,"income":28.0}},{"Timestamp":114.442169,"Name":"UnitDamage","Data":{"unit":"Hovercopter(Clone)","damage":0.25,"hp":16.0,"attacker":"Assault Cannon"}},{"Timestamp":114.69532,"Name":"UnitDamage","Data":{"unit":"Hovercopter(Clone)","damage":0.25,"hp":15.75,"attacker":"Assault Cannon"}},{"Timestamp":114.948563,"Name":"UnitDamage","Data":{"unit":"Hovercopter(Clone)","damage":0.25,"hp":15.5,"attacker":"Assault Cannon"}},{"Timestamp":115.2001,"Name":"UnitDamage","Data":{"unit":"Hovercopter(Clone)","damage":0.25,"hp":15.25,"attacker":"Assault Cannon"}},{"Timestamp":115.450363,"Name":"UnitDamage","Data":{"unit":"Hovercopter(Clone)","damage":12.0,"hp":15.0,"attacker":"Plasma Lance"}},{"Timestamp":115.4504,"Name":"UnitDamage","Data":{"unit":"Hovercopter(Clone)","damage":0.25,"hp":3.0,"attacker":"Assault Cannon"}},{"Timestamp":115.576378,"Name":"UnitSpawn","Data":{"unitSpawned":"Hoverbuggy","unitCount":5}},{"Timestamp":115.71553,"Name":"UnitDamage","Data":{"unit":"Hovercopter(Clone)","damage":0.25,"hp":2.75,"attacker":"Assault Cannon"}},{"Timestamp":115.97802,"Name":"UnitDamage","Data":{"unit":"Hovercopter(Clone)","damage":0.25,"hp":2.5,"attacker":"Assault Cannon"}},{"Timestamp":116.107208,"Name":"UnitDamage","Data":{"unit":"Hovercopter(Clone)","damage":0.25,"hp":2.25,"attacker":"Assault Cannon"}},{"Timestamp":116.145012,"Name":"UnitDamage","Data":{"unit":"Hoverbuggy(Clone)","damage":1.5,"hp":6.0,"attacker":"Rocket Platform"}},{"Timestamp":116.14505,"Name":"UnitDamage","Data":{"unit":"Hoverbuggy(Clone)","damage":3.0,"hp":4.5,"attacker":"Rocket Platform"}},{"Timestamp":116.218155,"Name":"UnitDamage","Data":{"unit":"Hovercopter(Clone)","damage":0.25,"hp":2.0,"attacker":"Assault Cannon"}},{"Timestamp":116.3594,"Name":"UnitDamage","Data":{"unit":"Hovercopter(Clone)","damage":0.25,"hp":1.75,"attacker":"Assault Cannon"}},{"Timestamp":116.47995,"Name":"UnitDamage","Data":{"unit":"Hovercopter(Clone)","damage":0.25,"hp":1.5,"attacker":"Assault Cannon"}},{"Timestamp":116.562416,"Name":"UnitDamage","Data":{"unit":"Hoverbuggy(Clone)","damage":1.5,"hp":1.5,"attacker":"Rocket Platform"}},{"Timestamp":116.562431,"Name":"UnitDeath","Data":{"unit":"Hoverbuggy(Clone)","overkillDamage":0.0,"killTower":"Rocket Platform"}},{"Timestamp":116.562454,"Name":"UnitDamage","Data":{"unit":"Hoverbuggy(Clone)","damage":3.0,"hp":0.0,"attacker":"Rocket Platform"}},{"Timestamp":116.612762,"Name":"UnitDamage","Data":{"unit":"Hovercopter(Clone)","damage":0.25,"hp":1.25,"attacker":"Assault Cannon"}},{"Timestamp":116.723648,"Name":"UnitDamage","Data":{"unit":"Hovercopter(Clone)","damage":0.25,"hp":1.0,"attacker":"Assault Cannon"}},{"Timestamp":116.863182,"Name":"UnitDamage","Data":{"unit":"Hovercopter(Clone)","damage":0.25,"hp":0.75,"attacker":"Assault Cannon"}},{"Timestamp":116.984268,"Name":"UnitDamage","Data":{"unit":"Hovercopter(Clone)","damage":0.25,"hp":0.5,"attacker":"Assault Cannon"}},{"Timestamp":117.119514,"Name":"UnitDamage","Data":{"unit":"Hovercopter(Clone)","damage":0.25,"hp":0.25,"attacker":"Assault Cannon"}},{"Timestamp":117.119537,"Name":"UnitDeath","Data":{"unit":"Hovercopter(Clone)","overkillDamage":0.0,"killTower":"Assault Cannon"}},{"Timestamp":117.578888,"Name":"UnitSpawn","Data":{"unitSpawned":"Hoverbuggy","unitCount":6}},{"Timestamp":118.124008,"Name":"UnitDamage","Data":{"unit":"Hoverbuggy(Clone)","damage":1.5,"hp":6.0,"attacker":"Rocket Platform"}},{"Timestamp":118.124046,"Name":"UnitDamage","Data":{"unit":"Hoverbuggy(Clone)","damage":3.0,"hp":4.5,"attacker":"Rocket Platform"}},{"Timestamp":118.286407,"Name":"UnitBuying","Data":{"unitBought":"Hoverbuggy","currentIncome":29}},{"Timestamp":118.293945,"Name":"UnitDamage","Data":{"unit":"Hoverbuggy(Clone)","damage":0.25,"hp":1.5,"attacker":"Assault Cannon"}},{"Timestamp":118.452606,"Name":"UnitBuying","Data":{"unitBought":"Hoverbuggy","currentIncome":30}},{"Timestamp":118.534874,"Name":"UnitDamage","Data":{"unit":"Hoverbuggy(Clone)","damage":0.25,"hp":1.25,"attacker":"Assault Cannon"}},{"Timestamp":118.54184,"Name":"UnitDamage","Data":{"unit":"Hoverbuggy(Clone)","damage":1.5,"hp":1.0,"attacker":"Rocket Platform"}},{"Timestamp":118.541855,"Name":"UnitDeath","Data":{"unit":"Hoverbuggy(Clone)","overkillDamage":0.5,"killTower":"Rocket Platform"}},{"Timestamp":118.541878,"Name":"UnitDamage","Data":{"unit":"Hoverbuggy(Clone)","damage":3.0,"hp":0.0,"attacker":"Rocket Platform"}},{"Timestamp":118.620964,"Name":"UnitBuying","Data":{"unitBought":"Hoverbuggy","currentIncome":31}},{"Timestamp":118.787949,"Name":"UnitBuying","Data":{"unitBought":"Hoverbuggy","currentIncome":32}},{"Timestamp":118.795158,"Name":"UnitDamage","Data":{"unit":"Hoverbuggy(Clone)","damage":12.0,"hp":0.0,"attacker":"Plasma Lance"}},{"Timestamp":119.113258,"Name":"UnitBuying","Data":{"unitBought":"Hoverbuggy","currentIncome":33}},{"Timestamp":119.11924,"Name":"Economy","Data":{"team":"Defender","currency":4.0,"income":0.0}},{"Timestamp":119.119247,"Name":"Economy","Data":{"team":"Attacker","currency":7.0,"income":33.0}},{"Timestamp":119.279266,"Name":"UnitBuying","Data":{"unitBought":"Hoverbuggy","currentIncome":34}},{"Timestamp":119.583168,"Name":"UnitSpawn","Data":{"unitSpawned":"Hoverbuggy","unitCount":7}},{"Timestamp":120.125832,"Name":"UnitDamage","Data":{"unit":"Hoverbuggy(Clone)","damage":1.5,"hp":6.0,"attacker":"Rocket Platform"}},{"Timestamp":120.12587,"Name":"UnitDamage","Data":{"unit":"Hoverbuggy(Clone)","damage":3.0,"hp":4.5,"attacker":"Rocket Platform"}},{"Timestamp":120.274025,"Name":"UnitDamage","Data":{"unit":"Hoverbuggy(Clone)","damage":0.25,"hp":1.5,"attacker":"Assault Cannon"}},{"Timestamp":120.515579,"Name":"UnitDamage","Data":{"unit":"Hoverbuggy(Clone)","damage":0.25,"hp":1.25,"attacker":"Assault Cannon"}},{"Timestamp":120.520775,"Name":"UnitDamage","Data":{"unit":"Hoverbuggy(Clone)","damage":1.5,"hp":1.0,"attacker":"Rocket Platform"}},{"Timestamp":120.52079,"Name":"UnitDeath","Data":{"unit":"Hoverbuggy(Clone)","overkillDamage":0.5,"killTower":"Rocket Platform"}},{"Timestamp":120.520813,"Name":"UnitDamage","Data":{"unit":"Hoverbuggy(Clone)","damage":3.0,"hp":0.0,"attacker":"Rocket Platform"}},{"Timestamp":120.931068,"Name":"TowerBuilding","Data":{"tower":"Assault Cannon","X":4,"Y":0}},{"Timestamp":121.594292,"Name":"UnitSpawn","Data":{"unitSpawned":"Hovercopter","unitCount":8}},{"Timestamp":122.807709,"Name":"UnitDamage","Data":{"unit":"Hovercopter(Clone)","damage":0.25,"hp":16.0,"attacker":"Assault Cannon"}},{"Timestamp":122.956375,"Name":"UnitDamage","Data":{"unit":"Hovercopter(Clone)","damage":12.0,"hp":15.75,"attacker":"Plasma Lance"}},{"Timestamp":123.057495,"Name":"UnitDamage","Data":{"unit":"Hovercopter(Clone)","damage":0.25,"hp":3.75,"attacker":"Assault Cannon"}},{"Timestamp":123.239105,"Name":"UnitBuying","Data":{"unitBought":"Hoverbuggy","currentIncome":35}},{"Timestamp":123.309639,"Name":"UnitDamage","Data":{"unit":"Hovercopter(Clone)","damage":0.25,"hp":3.5,"attacker":"Assault Cannon"}},{"Timestamp":123.404663,"Name":"UnitBuying","Data":{"unitBought":"Hoverbuggy","currentIncome":36}},{"Timestamp":123.5745,"Name":"UnitDamage","Data":{"unit":"Hovercopter(Clone)","damage":0.25,"hp":3.25,"attacker":"Assault Cannon"}},{"Timestamp":123.596283,"Name":"UnitSpawn","Data":{"unitSpawned":"Hovercopter","unitCount":9}},{"Timestamp":123.816353,"Name":"UnitDamage","Data":{"unit":"Hovercopter(Clone)","damage":0.25,"hp":3.0,"attacker":"Assault Cannon"}},{"Timestamp":123.855011,"Name":"UnitDamage","Data":{"unit":"Hovercopter(Clone)","damage":0.25,"hp":2.75,"attacker":"Assault Cannon"}},{"Timestamp":124.0711,"Name":"UnitDamage","Data":{"unit":"Hovercopter(Clone)","damage":0.25,"hp":2.5,"attacker":"Assault Cannon"}},{"Timestamp":124.109276,"Name":"UnitDamage","Data":{"unit":"Hovercopter(Clone)","damage":0.25,"hp":2.25,"attacker":"Assault Cannon"}},{"Timestamp":124.12291,"Name":"Economy","Data":{"team":"Defender","currency":0.0,"income":0.0}},{"Timestamp":124.122917,"Name":"Economy","Data":{"team":"Attacker","currency":6.0,"income":36.0}},{"Timestamp":124.341125,"Name":"UnitDamage","Data":{"unit":"Hovercopter(Clone)","damage":0.25,"hp":2.0,"attacker":"Assault Cannon"}},{"Timestamp":124.363327,"Name":"UnitDamage","Data":{"unit":"Hovercopter(Clone)","damage":0.25,"hp":1.75,"attacker":"Assault Cannon"}},{"Timestamp":124.499962,"Name":"UnitDamage","Data":{"unit":"Hovercopter(Clone)","damage":0.25,"hp":1.5,"attacker":"Assault Cannon"}},{"Timestamp":124.586754,"Name":"UnitDamage","Data":{"unit":"Hovercopter(Clone)","damage":0.25,"hp":1.25,"attacker":"Assault Cannon"}},{"Timestamp":124.616379,"Name":"UnitDamage","Data":{"unit":"Hovercopter(Clone)","damage":0.25,"hp":1.0,"attacker":"Assault Cannon"}},{"Timestamp":124.754684,"Name":"UnitDamage","Data":{"unit":"Hovercopter(Clone)","damage":0.25,"hp":0.75,"attacker":"Assault Cannon"}},{"Timestamp":124.839615,"Name":"UnitDamage","Data":{"unit":"Hovercopter(Clone)","damage":0.25,"hp":0.5,"attacker":"Assault Cannon"}},{"Timestamp":124.866,"Name":"UnitDamage","Data":{"unit":"Hovercopter(Clone)","damage":0.25,"hp":0.25,"attacker":"Assault Cannon"}},{"Timestamp":124.86602,"Name":"UnitDeath","Data":{"unit":"Hovercopter(Clone)","overkillDamage":0.0,"killTower":"Assault Cannon"}},{"Timestamp":125.091042,"Name":"UnitDamage","Data":{"unit":"Hovercopter(Clone)","damage":0.25,"hp":16.0,"attacker":"Assault Cannon"}},{"Timestamp":125.341354,"Name":"UnitDamage","Data":{"unit":"Hovercopter(Clone)","damage":0.25,"hp":15.75,"attacker":"Assault Cannon"}},{"Timestamp":125.591774,"Name":"UnitDamage","Data":{"unit":"Hovercopter(Clone)","damage":0.25,"hp":15.5,"attacker":"Assault Cannon"}},{"Timestamp":125.600494,"Name":"UnitSpawn","Data":{"unitSpawned":"Hoverbuggy","unitCount":10}},{"Timestamp":125.823456,"Name":"UnitDamage","Data":{"unit":"Hovercopter(Clone)","damage":0.25,"hp":15.25,"attacker":"Assault Cannon"}},{"Timestamp":125.851379,"Name":"UnitDamage","Data":{"unit":"Hovercopter(Clone)","damage":0.25,"hp":15.0,"attacker":"Assault Cannon"}},{"Timestamp":126.076576,"Name":"UnitDamage","Data":{"unit":"Hovercopter(Clone)","damage":0.25,"hp":14.75,"attacker":"Assault Cannon"}},{"Timestamp":126.103767,"Name":"UnitDamage","Data":{"unit":"Hovercopter(Clone)","damage":0.25,"hp":14.5,"attacker":"Assault Cannon"}},{"Timestamp":126.209755,"Name":"UnitDamage","Data":{"unit":"Hoverbuggy(Clone)","damage":1.5,"hp":6.0,"attacker":"Rocket Platform"}},{"Timestamp":126.209793,"Name":"UnitDamage","Data":{"unit":"Hoverbuggy(Clone)","damage":3.0,"hp":4.5,"attacker":"Rocket Platform"}},{"Timestamp":126.305855,"Name":"UnitDamage","Data":{"unit":"Hovercopter(Clone)","damage":12.0,"hp":14.25,"attacker":"Plasma Lance"}},{"Timestamp":126.329109,"Name":"UnitDamage","Data":{"unit":"Hovercopter(Clone)","damage":0.25,"hp":2.25,"attacker":"Assault Cannon"}},{"Timestamp":126.356255,"Name":"UnitDamage","Data":{"unit":"Hovercopter(Clone)","damage":0.25,"hp":2.0,"attacker":"Assault Cannon"}},{"Timestamp":126.480293,"Name":"UnitDamage","Data":{"unit":"Hovercopter(Clone)","damage":0.25,"hp":1.75,"attacker":"Assault Cannon"}},{"Timestamp":126.583488,"Name":"UnitDamage","Data":{"unit":"Hovercopter(Clone)","damage":0.25,"hp":1.5,"attacker":"Assault Cannon"}},{"Timestamp":126.5936,"Name":"UnitDamage","Data":{"unit":"Hoverbuggy(Clone)","damage":1.5,"hp":1.5,"attacker":"Rocket Platform"}},{"Timestamp":126.593613,"Name":"UnitDeath","Data":{"unit":"Hoverbuggy(Clone)","overkillDamage":0.0,"killTower":"Rocket Platform"}},{"Timestamp":126.593628,"Name":"UnitDamage","Data":{"unit":"Hoverbuggy(Clone)","damage":3.0,"hp":0.0,"attacker":"Rocket Platform"}},{"Timestamp":126.609093,"Name":"UnitDamage","Data":{"unit":"Hovercopter(Clone)","damage":0.25,"hp":1.25,"attacker":"Assault Cannon"}},{"Timestamp":126.737534,"Name":"UnitDamage","Data":{"unit":"Hovercopter(Clone)","damage":0.25,"hp":1.0,"attacker":"Assault Cannon"}},{"Timestamp":126.838943,"Name":"UnitDamage","Data":{"unit":"Hovercopter(Clone)","damage":0.25,"hp":0.75,"attacker":"Assault Cannon"}},{"Timestamp":126.869438,"Name":"UnitDamage","Data":{"unit":"Hovercopter(Clone)","damage":0.25,"hp":0.5,"attacker":"Assault Cannon"}},{"Timestamp":126.985321,"Name":"UnitDamage","Data":{"unit":"Hovercopter(Clone)","damage":0.25,"hp":0.25,"attacker":"Assault Cannon"}},{"Timestamp":126.985336,"Name":"UnitDeath","Data":{"unit":"Hovercopter(Clone)","overkillDamage":0.0,"killTower":"Assault Cannon"}},{"Timestamp":127.603752,"Name":"UnitSpawn","Data":{"unitSpawned":"Hoverbuggy","unitCount":11}},{"Timestamp":128.211411,"Name":"UnitDamage","Data":{"unit":"Hoverbuggy(Clone)","damage":1.5,"hp":6.0,"attacker":"Rocket Platform"}},{"Timestamp":128.211456,"Name":"UnitDamage","Data":{"unit":"Hoverbuggy(Clone)","damage":3.0,"hp":4.5,"attacker":"Rocket Platform"}},{"Timestamp":128.3593,"Name":"UnitDamage","Data":{"unit":"Hoverbuggy(Clone)","damage":0.25,"hp":1.5,"attacker":"Assault Cannon"}},{"Timestamp":128.6015,"Name":"UnitDamage","Data":{"unit":"Hoverbuggy(Clone)","damage":0.25,"hp":1.25,"attacker":"Assault Cannon"}},{"Timestamp":128.611511,"Name":"UnitDamage","Data":{"unit":"Hoverbuggy(Clone)","damage":1.5,"hp":1.0,"attacker":"Rocket Platform"}},{"Timestamp":128.611511,"Name":"UnitDeath","Data":{"unit":"Hoverbuggy(Clone)","overkillDamage":0.5,"killTower":"Rocket Platform"}},{"Timestamp":128.611542,"Name":"UnitDamage","Data":{"unit":"Hoverbuggy(Clone)","damage":3.0,"hp":0.0,"attacker":"Rocket Platform"}},{"Timestamp":129.126053,"Name":"Economy","Data":{"team":"Defender","currency":6.0,"income":0.0}},{"Timestamp":129.126068,"Name":"Economy","Data":{"team":"Attacker","currency":7.0,"income":36.0}},{"Timestamp":129.182266,"Name":"TowerBuilding","Data":{"tower":"Assault Cannon","X":4,"Y":1}},{"Timestamp":129.60939,"Name":"UnitSpawn","Data":{"unitSpawned":"Hoverbuggy","unitCount":12}},{"Timestamp":130.388214,"Name":"UnitDamage","Data":{"unit":"Hoverbuggy(Clone)","damage":1.5,"hp":6.0,"attacker":"Rocket Platform"}},{"Timestamp":130.38826,"Name":"UnitDamage","Data":{"unit":"Hoverbuggy(Clone)","damage":3.0,"hp":4.5,"attacker":"Rocket Platform"}},{"Timestamp":130.5306,"Name":"UnitDamage","Data":{"unit":"Hoverbuggy(Clone)","damage":0.25,"hp":1.5,"attacker":"Assault Cannon"}},{"Timestamp":130.685852,"Name":"UnitDamage","Data":{"unit":"Hoverbuggy(Clone)","damage":12.0,"hp":1.25,"attacker":"Plasma Lance"}},{"Timestamp":130.685867,"Name":"UnitDeath","Data":{"unit":"Hoverbuggy(Clone)","overkillDamage":10.75,"killTower":"Plasma Lance"}},{"Timestamp":130.791916,"Name":"UnitDamage","Data":{"unit":"Hoverbuggy(Clone)","damage":0.25,"hp":0.0,"attacker":"Assault Cannon"}},{"Timestamp":131.617157,"Name":"UnitSpawn","Data":{"unitSpawned":"Hoverbuggy","unitCount":13}},{"Timestamp":132.269562,"Name":"UnitDamage","Data":{"unit":"Hoverbuggy(Clone)","damage":1.5,"hp":6.0,"attacker":"Rocket Platform"}},{"Timestamp":132.269592,"Name":"UnitDamage","Data":{"unit":"Hoverbuggy(Clone)","damage":3.0,"hp":4.5,"attacker":"Rocket Platform"}},{"Timestamp":132.445114,"Name":"UnitDamage","Data":{"unit":"Hoverbuggy(Clone)","damage":0.25,"hp":1.5,"attacker":"Assault Cannon"}},{"Timestamp":132.694717,"Name":"UnitDamage","Data":{"unit":"Hoverbuggy(Clone)","damage":0.25,"hp":1.25,"attacker":"Assault Cannon"}},{"Timestamp":132.698959,"Name":"UnitDamage","Data":{"unit":"Hoverbuggy(Clone)","damage":3.0,"hp":1.0,"attacker":"Rocket Platform"}},{"Timestamp":132.698975,"Name":"UnitDeath","Data":{"unit":"Hoverbuggy(Clone)","overkillDamage":2.0,"killTower":"Rocket Platform"}},{"Timestamp":133.619858,"Name":"UnitSpawn","Data":{"unitSpawned":"Hoverbuggy","unitCount":14}},{"Timestamp":134.1347,"Name":"Economy","Data":{"team":"Defender","currency":3.0,"income":0.0}},{"Timestamp":134.1347,"Name":"Economy","Data":{"team":"Attacker","currency":13.0,"income":36.0}},{"Timestamp":134.38266,"Name":"UnitDamage","Data":{"unit":"Hoverbuggy(Clone)","damage":1.5,"hp":6.0,"attacker":"Rocket Platform"}},{"Timestamp":134.38269,"Name":"UnitDamage","Data":{"unit":"Hoverbuggy(Clone)","damage":3.0,"hp":4.5,"attacker":"Rocket Platform"}},{"Timestamp":134.520889,"Name":"UnitDamage","Data":{"unit":"Hoverbuggy(Clone)","damage":0.25,"hp":1.5,"attacker":"Assault Cannon"}},{"Timestamp":134.675079,"Name":"UnitDamage","Data":{"unit":"Hoverbuggy(Clone)","damage":12.0,"hp":1.25,"attacker":"Plasma Lance"}},{"Timestamp":134.6751,"Name":"UnitDeath","Data":{"unit":"Hoverbuggy(Clone)","overkillDamage":10.75,"killTower":"Plasma Lance"}},{"Timestamp":134.774948,"Name":"UnitDamage","Data":{"unit":"Hoverbuggy(Clone)","damage":0.25,"hp":0.0,"attacker":"Assault Cannon"}},{"Timestamp":135.626862,"Name":"UnitSpawn","Data":{"unitSpawned":"Hovercopter","unitCount":15}},{"Timestamp":136.63942,"Name":"UnitDamage","Data":{"unit":"Hovercopter(Clone)","damage":0.25,"hp":16.0,"attacker":"Assault Cannon"}},{"Timestamp":136.886978,"Name":"UnitDamage","Data":{"unit":"Hovercopter(Clone)","damage":0.25,"hp":15.75,"attacker":"Assault Cannon"}},{"Timestamp":137.139114,"Name":"UnitDamage","Data":{"unit":"Hovercopter(Clone)","damage":0.25,"hp":15.5,"attacker":"Assault Cannon"}},{"Timestamp":137.394043,"Name":"UnitDamage","Data":{"unit":"Hovercopter(Clone)","damage":0.25,"hp":15.25,"attacker":"Assault Cannon"}},{"Timestamp":137.557816,"Name":"UnitDamage","Data":{"unit":"Hovercopter(Clone)","damage":0.25,"hp":15.0,"attacker":"Assault Cannon"}},{"Timestamp":137.621353,"Name":"UnitDamage","Data":{"unit":"Hovercopter(Clone)","damage":0.25,"hp":14.75,"attacker":"Assault Cannon"}},{"Timestamp":137.636276,"Name":"UnitSpawn","Data":{"unitSpawned":"Hoverbuggy","unitCount":16}},{"Timestamp":137.6481,"Name":"UnitDamage","Data":{"unit":"Hovercopter(Clone)","damage":0.25,"hp":14.5,"attacker":"Assault Cannon"}},{"Timestamp":137.8092,"Name":"UnitDamage","Data":{"unit":"Hovercopter(Clone)","damage":0.25,"hp":14.25,"attacker":"Assault Cannon"}},{"Timestamp":137.872223,"Name":"UnitDamage","Data":{"unit":"Hovercopter(Clone)","damage":0.25,"hp":14.0,"attacker":"Assault Cannon"}},{"Timestamp":137.894913,"Name":"UnitDamage","Data":{"unit":"Hovercopter(Clone)","damage":0.25,"hp":13.75,"attacker":"Assault Cannon"}},{"Timestamp":138.005081,"Name":"UnitDamage","Data":{"unit":"Hovercopter(Clone)","damage":12.0,"hp":13.5,"attacker":"Plasma Lance"}},{"Timestamp":138.063141,"Name":"UnitDamage","Data":{"unit":"Hovercopter(Clone)","damage":0.25,"hp":1.5,"attacker":"Assault Cannon"}},{"Timestamp":138.124023,"Name":"UnitDamage","Data":{"unit":"Hovercopter(Clone)","damage":0.25,"hp":1.25,"attacker":"Assault Cannon"}},{"Timestamp":138.15004,"Name":"UnitDamage","Data":{"unit":"Hovercopter(Clone)","damage":0.25,"hp":1.0,"attacker":"Assault Cannon"}},{"Timestamp":138.315475,"Name":"UnitDamage","Data":{"unit":"Hovercopter(Clone)","damage":0.25,"hp":0.75,"attacker":"Assault Cannon"}},{"Timestamp":138.320068,"Name":"UnitDamage","Data":{"unit":"Hovercopter(Clone)","damage":0.25,"hp":0.5,"attacker":"Assault Cannon"}},{"Timestamp":138.376617,"Name":"UnitDamage","Data":{"unit":"Hoverbuggy(Clone)","damage":1.5,"hp":6.0,"attacker":"Rocket Platform"}},{"Timestamp":138.376648,"Name":"UnitDamage","Data":{"unit":"Hoverbuggy(Clone)","damage":3.0,"hp":4.5,"attacker":"Rocket Platform"}},{"Timestamp":138.376953,"Name":"UnitDamage","Data":{"unit":"Hovercopter(Clone)","damage":0.25,"hp":0.25,"attacker":"Assault Cannon"}},{"Timestamp":138.376968,"Name":"UnitDeath","Data":{"unit":"Hovercopter(Clone)","overkillDamage":0.0,"killTower":"Assault Cannon"}},{"Timestamp":138.40007,"Name":"UnitDamage","Data":{"unit":"Hovercopter(Clone)","damage":0.25,"hp":0.0,"attacker":"Assault Cannon"}},{"Timestamp":138.657257,"Name":"UnitDamage","Data":{"unit":"Hoverbuggy(Clone)","damage":0.25,"hp":1.5,"attacker":"Assault Cannon"}},{"Timestamp":138.775421,"Name":"UnitDamage","Data":{"unit":"Hoverbuggy(Clone)","damage":3.0,"hp":1.25,"attacker":"Rocket Platform"}},{"Timestamp":138.775436,"Name":"UnitDeath","Data":{"unit":"Hoverbuggy(Clone)","overkillDamage":1.75,"killTower":"Rocket Platform"}},{"Timestamp":138.9143,"Name":"TowerBuilding","Data":{"tower":"Assault Cannon","X":4,"Y":2}},{"Timestamp":139.137878,"Name":"Economy","Data":{"team":"Defender","currency":2.0,"income":0.0}},{"Timestamp":139.1379,"Name":"Economy","Data":{"team":"Attacker","currency":2.0,"income":36.0}},{"Timestamp":139.6415,"Name":"UnitSpawn","Data":{"unitSpawned":"Hovercopter","unitCount":17}},{"Timestamp":140.835281,"Name":"UnitDamage","Data":{"unit":"Hovercopter(Clone)","damage":0.25,"hp":16.0,"attacker":"Assault Cannon"}},{"Timestamp":141.086731,"Name":"UnitDamage","Data":{"unit":"Hovercopter(Clone)","damage":0.25,"hp":15.75,"attacker":"Assault Cannon"}},{"Timestamp":141.33754,"Name":"UnitDamage","Data":{"unit":"Hovercopter(Clone)","damage":12.0,"hp":15.5,"attacker":"Plasma Lance"}},{"Timestamp":141.347458,"Name":"UnitDamage","Data":{"unit":"Hovercopter(Clone)","damage":0.25,"hp":3.5,"attacker":"Assault Cannon"}},{"Timestamp":141.596924,"Name":"UnitDamage","Data":{"unit":"Hovercopter(Clone)","damage":0.25,"hp":3.25,"attacker":"Assault Cannon"}},{"Timestamp":141.642349,"Name":"UnitSpawn","Data":{"unitSpawned":"Hoverbuggy","unitCount":18}},{"Timestamp":141.754,"Name":"UnitDamage","Data":{"unit":"Hovercopter(Clone)","damage":0.25,"hp":3.0,"attacker":"Assault Cannon"}},{"Timestamp":141.7968,"Name":"UnitDamage","Data":{"unit":"Hovercopter(Clone)","damage":0.25,"hp":2.75,"attacker":"Assault Cannon"}},{"Timestamp":141.828125,"Name":"UnitDamage","Data":{"unit":"Hovercopter(Clone)","damage":0.25,"hp":2.5,"attacker":"Assault Cannon"}},{"Timestamp":141.85463,"Name":"UnitDamage","Data":{"unit":"Hovercopter(Clone)","damage":0.25,"hp":2.25,"attacker":"Assault Cannon"}},{"Timestamp":142.00354,"Name":"UnitDamage","Data":{"unit":"Hovercopter(Clone)","damage":0.25,"hp":2.0,"attacker":"Assault Cannon"}},{"Timestamp":142.0556,"Name":"UnitDamage","Data":{"unit":"Hovercopter(Clone)","damage":0.25,"hp":1.75,"attacker":"Assault Cannon"}},{"Timestamp":142.080078,"Name":"UnitDamage","Data":{"unit":"Hovercopter(Clone)","damage":0.25,"hp":1.5,"attacker":"Assault Cannon"}},{"Timestamp":142.108032,"Name":"UnitDamage","Data":{"unit":"Hovercopter(Clone)","damage":0.25,"hp":1.25,"attacker":"Assault Cannon"}},{"Timestamp":142.257477,"Name":"UnitDamage","Data":{"unit":"Hovercopter(Clone)","damage":0.25,"hp":1.0,"attacker":"Assault Cannon"}},{"Timestamp":142.301392,"Name":"UnitDamage","Data":{"unit":"Hovercopter(Clone)","damage":0.25,"hp":0.75,"attacker":"Assault Cannon"}},{"Timestamp":142.334137,"Name":"UnitDamage","Data":{"unit":"Hoverbuggy(Clone)","damage":1.5,"hp":6.0,"attacker":"Rocket Platform"}},{"Timestamp":142.334167,"Name":"UnitDamage","Data":{"unit":"Hoverbuggy(Clone)","damage":3.0,"hp":4.5,"attacker":"Rocket Platform"}},{"Timestamp":142.339279,"Name":"UnitDamage","Data":{"unit":"Hovercopter(Clone)","damage":0.25,"hp":0.5,"attacker":"Assault Cannon"}},{"Timestamp":142.36351,"Name":"UnitDamage","Data":{"unit":"Hovercopter(Clone)","damage":0.25,"hp":0.25,"attacker":"Assault Cannon"}},{"Timestamp":142.363525,"Name":"UnitDeath","Data":{"unit":"Hovercopter(Clone)","overkillDamage":0.0,"killTower":"Assault Cannon"}},{"Timestamp":142.617645,"Name":"UnitDamage","Data":{"unit":"Hoverbuggy(Clone)","damage":0.25,"hp":1.5,"attacker":"Assault Cannon"}},{"Timestamp":142.765442,"Name":"UnitDamage","Data":{"unit":"Hoverbuggy(Clone)","damage":1.5,"hp":1.25,"attacker":"Rocket Platform"}},{"Timestamp":142.765457,"Name":"UnitDeath","Data":{"unit":"Hoverbuggy(Clone)","overkillDamage":0.25,"killTower":"Rocket Platform"}},{"Timestamp":142.765472,"Name":"UnitDamage","Data":{"unit":"Hoverbuggy(Clone)","damage":3.0,"hp":0.0,"attacker":"Rocket Platform"}},{"Timestamp":143.641846,"Name":"UnitSpawn","Data":{"unitSpawned":"Hoverbuggy","unitCount":19}},{"Timestamp":144.028671,"Name":"TowerBuilding","Data":{"tower":"Assault Cannon","X":3,"Y":1}},{"Timestamp":144.14006,"Name":"Economy","Data":{"team":"Defender","currency":0.0,"income":0.0}},{"Timestamp":144.140076,"Name":"Economy","Data":{"team":"Attacker","currency":8.0,"income":36.0}},{"Timestamp":144.148468,"Name":"UnitDamage","Data":{"unit":"Hoverbuggy(Clone)","damage":1.5,"hp":6.0,"attacker":"Rocket Platform"}},{"Timestamp":144.148514,"Name":"UnitDamage","Data":{"unit":"Hoverbuggy(Clone)","damage":3.0,"hp":4.5,"attacker":"Rocket Platform"}},{"Timestamp":144.323929,"Name":"UnitDamage","Data":{"unit":"Hoverbuggy(Clone)","damage":0.25,"hp":1.5,"attacker":"Assault Cannon"}},{"Timestamp":144.577652,"Name":"UnitDamage","Data":{"unit":"Hoverbuggy(Clone)","damage":1.5,"hp":1.25,"attacker":"Rocket Platform"}},{"Timestamp":144.577667,"Name":"UnitDeath","Data":{"unit":"Hoverbuggy(Clone)","overkillDamage":0.25,"killTower":"Rocket Platform"}},{"Timestamp":144.577682,"Name":"UnitDamage","Data":{"unit":"Hoverbuggy(Clone)","damage":3.0,"hp":0.0,"attacker":"Rocket Platform"}},{"Timestamp":144.57782,"Name":"UnitDamage","Data":{"unit":"Hoverbuggy(Clone)","damage":0.25,"hp":0.0,"attacker":"Assault Cannon"}},{"Timestamp":144.691727,"Name":"UnitDamage","Data":{"unit":"Hoverbuggy(Clone)","damage":12.0,"hp":0.0,"attacker":"Plasma Lance"}},{"Timestamp":145.643219,"Name":"UnitSpawn","Data":{"unitSpawned":"Hoverbuggy","unitCount":20}},{"Timestamp":146.340454,"Name":"UnitDamage","Data":{"unit":"Hoverbuggy(Clone)","damage":1.5,"hp":6.0,"attacker":"Rocket Platform"}},{"Timestamp":146.3405,"Name":"UnitDamage","Data":{"unit":"Hoverbuggy(Clone)","damage":3.0,"hp":4.5,"attacker":"Rocket Platform"}},{"Timestamp":146.471832,"Name":"UnitDamage","Data":{"unit":"Hoverbuggy(Clone)","damage":0.25,"hp":1.5,"attacker":"Assault Cannon"}},{"Timestamp":146.725967,"Name":"UnitDamage","Data":{"unit":"Hoverbuggy(Clone)","damage":0.25,"hp":1.25,"attacker":"Assault Cannon"}},{"Timestamp":146.758713,"Name":"UnitDamage","Data":{"unit":"Hoverbuggy(Clone)","damage":1.5,"hp":1.0,"attacker":"Rocket Platform"}},{"Timestamp":146.758728,"Name":"UnitDeath","Data":{"unit":"Hoverbuggy(Clone)","overkillDamage":0.5,"killTower":"Rocket Platform"}},{"Timestamp":146.758743,"Name":"UnitDamage","Data":{"unit":"Hoverbuggy(Clone)","damage":3.0,"hp":0.0,"attacker":"Rocket Platform"}},{"Timestamp":147.644012,"Name":"UnitSpawn","Data":{"unitSpawned":"Hoverbuggy","unitCount":21}},{"Timestamp":148.180191,"Name":"UnitDamage","Data":{"unit":"Hoverbuggy(Clone)","damage":1.5,"hp":6.0,"attacker":"Rocket Platform"}},{"Timestamp":148.180237,"Name":"UnitDamage","Data":{"unit":"Hoverbuggy(Clone)","damage":3.0,"hp":4.5,"attacker":"Rocket Platform"}},{"Timestamp":148.331024,"Name":"UnitDamage","Data":{"unit":"Hoverbuggy(Clone)","damage":0.25,"hp":1.5,"attacker":"Assault Cannon"}},{"Timestamp":148.468842,"Name":"UnitDamage","Data":{"unit":"Hoverbuggy(Clone)","damage":12.0,"hp":1.25,"attacker":"Plasma Lance"}},{"Timestamp":148.468857,"Name":"UnitDeath","Data":{"unit":"Hoverbuggy(Clone)","overkillDamage":10.75,"killTower":"Plasma Lance"}},{"Timestamp":148.570755,"Name":"UnitDamage","Data":{"unit":"Hoverbuggy(Clone)","damage":0.25,"hp":0.0,"attacker":"Assault Cannon"}},{"Timestamp":149.152451,"Name":"Economy","Data":{"team":"Defender","currency":3.0,"income":0.0}},{"Timestamp":149.152466,"Name":"Economy","Data":{"team":"Attacker","currency":2.0,"income":36.0}},{"Timestamp":149.647034,"Name":"UnitSpawn","Data":{"unitSpawned":"Hoverbuggy","unitCount":22}},{"Timestamp":150.352844,"Name":"UnitDamage","Data":{"unit":"Hoverbuggy(Clone)","damage":3.0,"hp":6.0,"attacker":"Rocket Platform"}},{"Timestamp":150.352966,"Name":"UnitDamage","Data":{"unit":"Hoverbuggy(Clone)","damage":1.5,"hp":3.0,"attacker":"Rocket Platform"}},{"Timestamp":150.526154,"Name":"UnitDamage","Data":{"unit":"Hoverbuggy(Clone)","damage":0.25,"hp":1.5,"attacker":"Assault Cannon"}},{"Timestamp":150.79425,"Name":"UnitDamage","Data":{"unit":"Hoverbuggy(Clone)","damage":3.0,"hp":1.25,"attacker":"Rocket Platform"}},{"Timestamp":150.794266,"Name":"UnitDeath","Data":{"unit":"Hoverbuggy(Clone)","overkillDamage":1.75,"killTower":"Rocket Platform"}},{"Timestamp":150.794525,"Name":"UnitDamage","Data":{"unit":"Hoverbuggy(Clone)","damage":0.25,"hp":0.0,"attacker":"Assault Cannon"}},{"Timestamp":151.648026,"Name":"UnitSpawn","Data":{"unitSpawned":"Hoverbuggy","unitCount":23}},{"Timestamp":152.202835,"Name":"UnitDamage","Data":{"unit":"Hoverbuggy(Clone)","damage":1.5,"hp":6.0,"attacker":"Rocket Platform"}},{"Timestamp":152.202881,"Name":"UnitDamage","Data":{"unit":"Hoverbuggy(Clone)","damage":3.0,"hp":4.5,"attacker":"Rocket Platform"}},{"Timestamp":152.346466,"Name":"UnitDamage","Data":{"unit":"Hoverbuggy(Clone)","damage":0.25,"hp":1.5,"attacker":"Assault Cannon"}},{"Timestamp":152.496445,"Name":"UnitDamage","Data":{"unit":"Hoverbuggy(Clone)","damage":12.0,"hp":1.25,"attacker":"Plasma Lance"}},{"Timestamp":152.49646,"Name":"UnitDeath","Data":{"unit":"Hoverbuggy(Clone)","overkillDamage":10.75,"killTower":"Plasma Lance"}},{"Timestamp":152.613876,"Name":"UnitDamage","Data":{"unit":"Hoverbuggy(Clone)","damage":0.25,"hp":0.0,"attacker":"Assault Cannon"}},{"Timestamp":153.649673,"Name":"UnitSpawn","Data":{"unitSpawned":"Hoverbuggy","unitCount":24}},{"Timestamp":154.156158,"Name":"Economy","Data":{"team":"Defender","currency":5.0,"income":0.0}},{"Timestamp":154.156174,"Name":"Economy","Data":{"team":"Attacker","currency":1.0,"income":36.0}},{"Timestamp":154.346832,"Name":"UnitDamage","Data":{"unit":"Hoverbuggy(Clone)","damage":3.0,"hp":6.0,"attacker":"Rocket Platform"}},{"Timestamp":154.34697,"Name":"UnitDamage","Data":{"unit":"Hoverbuggy(Clone)","damage":1.5,"hp":3.0,"attacker":"Rocket Platform"}},{"Timestamp":154.489716,"Name":"UnitDamage","Data":{"unit":"Hoverbuggy(Clone)","damage":0.25,"hp":1.5,"attacker":"Assault Cannon"}},{"Timestamp":154.738876,"Name":"UnitDamage","Data":{"unit":"Hoverbuggy(Clone)","damage":0.25,"hp":1.25,"attacker":"Assault Cannon"}},{"Timestamp":154.75708,"Name":"UnitDamage","Data":{"unit":"Hoverbuggy(Clone)","damage":3.0,"hp":1.0,"attacker":"Rocket Platform"}},{"Timestamp":154.7571,"Name":"UnitDeath","Data":{"unit":"Hoverbuggy(Clone)","overkillDamage":2.0,"killTower":"Rocket Platform"}},{"Timestamp":155.650421,"Name":"UnitSpawn","Data":{"unitSpawned":"Hoverbuggy","unitCount":25}},{"Timestamp":156.458923,"Name":"UnitDamage","Data":{"unit":"Hoverbuggy(Clone)","damage":1.5,"hp":6.0,"attacker":"Rocket Platform"}},{"Timestamp":156.458969,"Name":"UnitDamage","Data":{"unit":"Hoverbuggy(Clone)","damage":3.0,"hp":4.5,"attacker":"Rocket Platform"}},{"Timestamp":156.602737,"Name":"UnitDamage","Data":{"unit":"Hoverbuggy(Clone)","damage":0.25,"hp":1.5,"attacker":"Assault Cannon"}},{"Timestamp":156.7567,"Name":"UnitDamage","Data":{"unit":"Hoverbuggy(Clone)","damage":12.0,"hp":1.25,"attacker":"Plasma Lance"}},{"Timestamp":156.756714,"Name":"UnitDeath","Data":{"unit":"Hoverbuggy(Clone)","overkillDamage":10.75,"killTower":"Plasma Lance"}},{"Timestamp":156.857681,"Name":"UnitDamage","Data":{"unit":"Hoverbuggy(Clone)","damage":0.25,"hp":0.0,"attacker":"Assault Cannon"}},{"Timestamp":157.651871,"Name":"UnitSpawn","Data":{"unitSpawned":"Hoverbuggy","unitCount":26}},{"Timestamp":158.2746,"Name":"UnitDamage","Data":{"unit":"Hoverbuggy(Clone)","damage":1.5,"hp":6.0,"attacker":"Rocket Platform"}},{"Timestamp":158.274643,"Name":"UnitDamage","Data":{"unit":"Hoverbuggy(Clone)","damage":3.0,"hp":4.5,"attacker":"Rocket Platform"}},{"Timestamp":158.413147,"Name":"UnitDamage","Data":{"unit":"Hoverbuggy(Clone)","damage":0.25,"hp":1.5,"attacker":"Assault Cannon"}},{"Timestamp":158.670975,"Name":"UnitDamage","Data":{"unit":"Hoverbuggy(Clone)","damage":1.5,"hp":1.25,"attacker":"Rocket Platform"}},{"Timestamp":158.67099,"Name":"UnitDeath","Data":{"unit":"Hoverbuggy(Clone)","overkillDamage":0.25,"killTower":"Rocket Platform"}},{"Timestamp":158.671,"Name":"UnitDamage","Data":{"unit":"Hoverbuggy(Clone)","damage":3.0,"hp":0.0,"attacker":"Rocket Platform"}},{"Timestamp":158.675919,"Name":"UnitDamage","Data":{"unit":"Hoverbuggy(Clone)","damage":0.25,"hp":0.0,"attacker":"Assault Cannon"}},{"Timestamp":159.04422,"Name":"TowerBuilding","Data":{"tower":"Assault Cannon","X":7,"Y":1}},{"Timestamp":159.156387,"Name":"Economy","Data":{"team":"Defender","currency":3.0,"income":0.0}},{"Timestamp":159.1564,"Name":"Economy","Data":{"team":"Attacker","currency":0.0,"income":36.0}},{"Timestamp":159.655624,"Name":"UnitSpawn","Data":{"unitSpawned":"Hoverbuggy","unitCount":27}},{"Timestamp":160.387619,"Name":"UnitDamage","Data":{"unit":"Hoverbuggy(Clone)","damage":1.5,"hp":6.0,"attacker":"Rocket Platform"}},{"Timestamp":160.38765,"Name":"UnitDamage","Data":{"unit":"Hoverbuggy(Clone)","damage":3.0,"hp":4.5,"attacker":"Rocket Platform"}},{"Timestamp":160.542343,"Name":"UnitDamage","Data":{"unit":"Hoverbuggy(Clone)","damage":0.25,"hp":1.5,"attacker":"Assault Cannon"}},{"Timestamp":160.646149,"Name":"UnitDamage","Data":{"unit":"Hoverbuggy(Clone)","damage":12.0,"hp":1.25,"attacker":"Plasma Lance"}},{"Timestamp":160.646164,"Name":"UnitDeath","Data":{"unit":"Hoverbuggy(Clone)","overkillDamage":10.75,"killTower":"Plasma Lance"}},{"Timestamp":161.659683,"Name":"UnitSpawn","Data":{"unitSpawned":"Hoverbuggy","unitCount":28}},{"Timestamp":162.178711,"Name":"UnitDamage","Data":{"unit":"Hoverbuggy(Clone)","damage":1.5,"hp":6.0,"attacker":"Rocket Platform"}},{"Timestamp":162.178757,"Name":"UnitDamage","Data":{"unit":"Hoverbuggy(Clone)","damage":3.0,"hp":4.5,"attacker":"Rocket Platform"}},{"Timestamp":162.3094,"Name":"UnitDamage","Data":{"unit":"Hoverbuggy(Clone)","damage":0.25,"hp":1.5,"attacker":"Assault Cannon"}},{"Timestamp":162.560455,"Name":"UnitDamage","Data":{"unit":"Hoverbuggy(Clone)","damage":0.25,"hp":1.25,"attacker":"Assault Cannon"}},{"Timestamp":162.566147,"Name":"UnitDamage","Data":{"unit":"Hoverbuggy(Clone)","damage":1.5,"hp":1.0,"attacker":"Rocket Platform"}},{"Timestamp":162.566162,"Name":"UnitDeath","Data":{"unit":"Hoverbuggy(Clone)","overkillDamage":0.5,"killTower":"Rocket Platform"}},{"Timestamp":162.5662,"Name":"UnitDamage","Data":{"unit":"Hoverbuggy(Clone)","damage":3.0,"hp":0.0,"attacker":"Rocket Platform"}},{"Timestamp":163.6701,"Name":"UnitSpawn","Data":{"unitSpawned":"Hoverbuggy","unitCount":29}},{"Timestamp":164.168259,"Name":"Economy","Data":{"team":"Defender","currency":5.0,"income":0.0}},{"Timestamp":164.168274,"Name":"Economy","Data":{"team":"Attacker","currency":4.0,"income":36.0}},{"Timestamp":164.2822,"Name":"UnitDamage","Data":{"unit":"Hoverbuggy(Clone)","damage":1.5,"hp":6.0,"attacker":"Rocket Platform"}},{"Timestamp":164.282227,"Name":"UnitDamage","Data":{"unit":"Hoverbuggy(Clone)","damage":3.0,"hp":4.5,"attacker":"Rocket Platform"}},{"Timestamp":164.457626,"Name":"UnitDamage","Data":{"unit":"Hoverbuggy(Clone)","damage":0.25,"hp":1.5,"attacker":"Assault Cannon"}},{"Timestamp":164.604187,"Name":"UnitDamage","Data":{"unit":"Hoverbuggy(Clone)","damage":12.0,"hp":1.25,"attacker":"Plasma Lance"}},{"Timestamp":164.6042,"Name":"UnitDeath","Data":{"unit":"Hoverbuggy(Clone)","overkillDamage":10.75,"killTower":"Plasma Lance"}},{"Timestamp":164.704941,"Name":"UnitDamage","Data":{"unit":"Hoverbuggy(Clone)","damage":0.25,"hp":0.0,"attacker":"Assault Cannon"}},{"Timestamp":165.672272,"Name":"UnitSpawn","Data":{"unitSpawned":"Hoverbuggy","unitCount":30}},{"Timestamp":166.139465,"Name":"TowerBuilding","Data":{"tower":"Assault Cannon","X":1,"Y":1}},{"Timestamp":166.494537,"Name":"UnitDamage","Data":{"unit":"Hoverbuggy(Clone)","damage":3.0,"hp":6.0,"attacker":"Rocket Platform"}},{"Timestamp":166.494629,"Name":"UnitDamage","Data":{"unit":"Hoverbuggy(Clone)","damage":1.5,"hp":3.0,"attacker":"Rocket Platform"}},{"Timestamp":166.598755,"Name":"UnitDamage","Data":{"unit":"Hoverbuggy(Clone)","damage":0.25,"hp":1.5,"attacker":"Assault Cannon"}},{"Timestamp":166.642776,"Name":"UnitDamage","Data":{"unit":"Hoverbuggy(Clone)","damage":0.25,"hp":1.25,"attacker":"Assault Cannon"}},{"Timestamp":166.852463,"Name":"UnitDamage","Data":{"unit":"Hoverbuggy(Clone)","damage":0.25,"hp":1.0,"attacker":"Assault Cannon"}},{"Timestamp":166.886444,"Name":"UnitDamage","Data":{"unit":"Hoverbuggy(Clone)","damage":0.25,"hp":0.75,"attacker":"Assault Cannon"}},{"Timestamp":166.920441,"Name":"UnitDamage","Data":{"unit":"Hoverbuggy(Clone)","damage":3.0,"hp":0.5,"attacker":"Rocket Platform"}},{"Timestamp":166.920471,"Name":"UnitDeath","Data":{"unit":"Hoverbuggy(Clone)","overkillDamage":2.5,"killTower":"Rocket Platform"}},{"Timestamp":166.920761,"Name":"GameEnd","Data":{"winner":1}}]