[{"Timestamp":7.341038,"Name":"RoundStart","Data":{"gameCount":1}},{"Timestamp":8.050691,"Name":"TowerBuilding","Data":{"tower":"Plasma Lance","X":0,"Y":0}},{"Timestamp":8.052125,"Name":"UnitBuying","Data":{"unitBought":"Hoverbuggy","currentIncome":1}},{"Timestamp":9.124643,"Name":"TowerBuilding","Data":{"tower":"Plasma Lance","X":4,"Y":0}},{"Timestamp":9.124679,"Name":"UnitBuying","Data":{"unitBought":"Hoverbuggy","currentIncome":2}},{"Timestamp":9.285591,"Name":"TowerBuilding","Data":{"tower":"Plasma Lance","X":1,"Y":0}},{"Timestamp":9.285604,"Name":"UnitBuying","Data":{"unitBought":"Hoverbuggy","currentIncome":3}},{"Timestamp":9.450337,"Name":"UnitBuying","Data":{"unitBought":"Hoverbuggy","currentIncome":4}},{"Timestamp":9.61501,"Name":"UnitBuying","Data":{"unitBought":"Hovercopter","currentIncome":6}},{"Timestamp":9.78064251,"Name":"UnitBuying","Data":{"unitBought":"Hoverbuggy","currentIncome":7}},{"Timestamp":9.94785,"Name":"UnitBuying","Data":{"unitBought":"Hoverbuggy","currentIncome":8}},{"Timestamp":10.1127548,"Name":"UnitBuying","Data":{"unitBought":"Hoverbuggy","currentIncome":9}},{"Timestamp":10.2756233,"Name":"UnitBuying","Data":{"unitBought":"Hoverbuggy","currentIncome":10}},{"Timestamp":10.4390507,"Name":"UnitBuying","Data":{"unitBought":"Hoverbuggy","currentIncome":11}},{"Timestamp":10.605855,"Name":"UnitBuying","Data":{"unitBought":"Hoverbuggy","currentIncome":12}},{"Timestamp":10.768405,"Name":"UnitBuying","Data":{"unitBought":"Hovercopter","currentIncome":14}},{"Timestamp":10.9344091,"Name":"UnitBuying","Data":{"unitBought":"Hoverbuggy","currentIncome":15}},{"Timestamp":11.1007481,"Name":"UnitBuying","Data":{"unitBought":"Hovercopter","currentIncome":17}},{"Timestamp":11.2652121,"Name":"UnitBuying","Data":{"unitBought":"Hoverbuggy","currentIncome":18}},{"Timestamp":11.4308023,"Name":"UnitBuying","Data":{"unitBought":"Hoverbuggy","currentIncome":19}},{"Timestamp":11.5959187,"Name":"UnitBuying","Data":{"unitBought":"Hoverbuggy","currentIncome":20}},{"Timestamp":13.2607136,"Name":"UnitSpawn","Data":{"unitSpawned":"Hoverbuggy","unitCount":1}},{"Timestamp":13.5365906,"Name":"UnitDamage","Data":{"unit":"Hoverbuggy(Clone)","damage":12.0,"hp":6.0,"attacker":"Plasma Lance"}},{"Timestamp":13.5372095,"Name":"UnitDeath","Data":{"unit":"Hoverbuggy(Clone)","overkillDamage":6.0,"killTower":"Plasma Lance"}},{"Timestamp":13.6704254,"Name":"UnitDamage","Data":{"unit":"Hoverbuggy(Clone)","damage":12.0,"hp":0.0,"attacker":"Plasma Lance"}},{"Timestamp":13.9261932,"Name":"Economy","Data":{"team":"Defender","currency":1.0,"income":0.0}},{"Timestamp":13.9264507,"Name":"Economy","Data":{"team":"Attacker","currency":20.0,"income":20.0}},{"Timestamp":14.0689669,"Name":"UnitBuying","Data":{"unitBought":"Hovercopter","currentIncome":22}},{"Timestamp":14.3990145,"Name":"UnitBuying","Data":{"unitBought":"Hoverbuggy","currentIncome":23}},{"Timestamp":14.731658,"Name":"UnitBuying","Data":{"unitBought":"Hoverbuggy","currentIncome":24}},{"Timestamp":15.2615194,"Name":"UnitSpawn","Data":{"unitSpawned":"Hoverbuggy","unitCount":2}},{"Timestamp":16.3622532,"Name":"UnitDamage","Data":{"unit":"Hoverbuggy(Clone)","damage":12.0,"hp":6.0,"attacker":"Plasma Lance"}},{"Timestamp":16.3622665,"Name":"UnitDeath","Data":{"unit":"Hoverbuggy(Clone)","overkillDamage":6.0,"killTower":"Plasma Lance"}},{"Timestamp":17.2631035,"Name":"UnitSpawn","Data":{"unitSpawned":"Hoverbuggy","unitCount":3}},{"Timestamp":17.5517616,"Name":"UnitDamage","Data":{"unit":"Hoverbuggy(Clone)","damage":12.0,"hp":6.0,"attacker":"Plasma Lance"}},{"Timestamp":17.551775,"Name":"UnitDeath","Data":{"unit":"Hoverbuggy(Clone)","overkillDamage":6.0,"killTower":"Plasma Lance"}},{"Timestamp":18.9270763,"Name":"Economy","Data":{"team":"Defender","currency":3.0,"income":0.0}},{"Timestamp":18.9270859,"Name":"Economy","Data":{"team":"Attacker","currency":24.0,"income":24.0}},{"Timestamp":19.0215168,"Name":"UnitBuying","Data":{"unitBought":"Hoverbuggy","currentIncome":25}},{"Timestamp":19.184824,"Name":"UnitBuying","Data":{"unitBought":"Hoverbuggy","currentIncome":26}},{"Timestamp":19.26506,"Name":"UnitSpawn","Data":{"unitSpawned":"Hoverbuggy","unitCount":4}},{"Timestamp":19.3508625,"Name":"UnitBuying","Data":{"unitBought":"Hovercopter","currentIncome":28}},{"Timestamp":19.8638325,"Name":"UnitDamage","Data":{"unit":"Hoverbuggy(Clone)","damage":12.0,"hp":6.0,"attacker":"Plasma Lance"}},{"Timestamp":19.8638535,"Name":"UnitDeath","Data":{"unit":"Hoverbuggy(Clone)","overkillDamage":6.0,"killTower":"Plasma Lance"}},{"Timestamp":21.2677765,"Name":"UnitSpawn","Data":{"unitSpawned":"Hovercopter","unitCount":5}},{"Timestamp":21.54573,"Name":"UnitDamage","Data":{"unit":"Hovercopter(Clone)","damage":12.0,"hp":16.0,"attacker":"Plasma Lance"}},{"Timestamp":22.79613,"Name":"UnitDamage","Data":{"unit":"Hovercopter(Clone)","damage":12.0,"hp":4.0,"attacker":"Plasma Lance"}},{"Timestamp":22.7961426,"Name":"UnitDeath","Data":{"unit":"Hovercopter(Clone)","overkillDamage":8.0,"killTower":"Plasma Lance"}},{"Timestamp":23.2705059,"Name":"UnitSpawn","Data":{"unitSpawned":"Hoverbuggy","unitCount":6}},{"Timestamp":23.64387,"Name":"TowerBuilding","Data":{"tower":"Assault Cannon","X":3,"Y":0}},{"Timestamp":23.75381,"Name":"UnitDamage","Data":{"unit":"Hoverbuggy(Clone)","damage":12.0,"hp":6.0,"attacker":"Plasma Lance"}},{"Timestamp":23.7538223,"Name":"UnitDeath","Data":{"unit":"Hoverbuggy(Clone)","overkillDamage":6.0,"killTower":"Plasma Lance"}},{"Timestamp":23.9283314,"Name":"Economy","Data":{"team":"Defender","currency":2.0,"income":0.0}},{"Timestamp":23.928339,"Name":"Economy","Data":{"team":"Attacker","currency":32.0,"income":28.0}},{"Timestamp":23.9721546,"Name":"UnitBuying","Data":{"unitBought":"Hovercopter","currentIncome":30}},{"Timestamp":24.13535,"Name":"UnitBuying","Data":{"unitBought":"Hoverbuggy","currentIncome":31}},{"Timestamp":24.299099,"Name":"UnitBuying","Data":{"unitBought":"Hovercopter","currentIncome":33}},{"Timestamp":24.4684486,"Name":"UnitBuying","Data":{"unitBought":"Hoverbuggy","currentIncome":34}},{"Timestamp":25.270649,"Name":"UnitSpawn","Data":{"unitSpawned":"Hoverbuggy","unitCount":7}},{"Timestamp":25.54736,"Name":"UnitDamage","Data":{"unit":"Hoverbuggy(Clone)","damage":12.0,"hp":6.0,"attacker":"Plasma Lance"}},{"Timestamp":25.5473728,"Name":"UnitDeath","Data":{"unit":"Hoverbuggy(Clone)","overkillDamage":6.0,"killTower":"Plasma Lance"}},{"Timestamp":27.2788124,"Name":"UnitSpawn","Data":{"unitSpawned":"Hoverbuggy","unitCount":8}},{"Timestamp":27.7461929,"Name":"UnitDamage","Data":{"unit":"Hoverbuggy(Clone)","damage":12.0,"hp":6.0,"attacker":"Plasma Lance"}},{"Timestamp":27.7462082,"Name":"UnitDeath","Data":{"unit":"Hoverbuggy(Clone)","overkillDamage":6.0,"killTower":"Plasma Lance"}},{"Timestamp":28.9287262,"Name":"Economy","Data":{"team":"Defender","currency":4.0,"income":0.0}},{"Timestamp":28.92874,"Name":"Economy","Data":{"team":"Attacker","currency":36.0,"income":34.0}},{"Timestamp":29.0860844,"Name":"UnitBuying","Data":{"unitBought":"Hovercopter","currentIncome":36}},{"Timestamp":29.2796841,"Name":"UnitSpawn","Data":{"unitSpawned":"Hoverbuggy","unitCount":9}},{"Timestamp":29.4148731,"Name":"UnitBuying","Data":{"unitBought":"Hoverbuggy","currentIncome":37}},{"Timestamp":29.7257042,"Name":"UnitDamage","Data":{"unit":"Hoverbuggy(Clone)","damage":12.0,"hp":6.0,"attacker":"Plasma Lance"}},{"Timestamp":29.7257156,"Name":"UnitDeath","Data":{"unit":"Hoverbuggy(Clone)","overkillDamage":6.0,"killTower":"Plasma Lance"}},{"Timestamp":29.9101715,"Name":"UnitBuying","Data":{"unitBought":"Hoverbuggy","currentIncome":38}},{"Timestamp":30.0778446,"Name":"UnitBuying","Data":{"unitBought":"Hoverbuggy","currentIncome":39}},{"Timestamp":30.2422962,"Name":"UnitBuying","Data":{"unitBought":"Hoverbuggy","currentIncome":40}},{"Timestamp":30.5719967,"Name":"UnitBuying","Data":{"unitBought":"Hoverbuggy","currentIncome":41}},{"Timestamp":30.7370739,"Name":"TowerBuilding","Data":{"tower":"Assault Cannon","X":7,"Y":0}},{"Timestamp":31.2800446,"Name":"UnitSpawn","Data":{"unitSpawned":"Hoverbuggy","unitCount":10}},{"Timestamp":31.8724651,"Name":"UnitDamage","Data":{"unit":"Hoverbuggy(Clone)","damage":12.0,"hp":6.0,"attacker":"Plasma Lance"}},{"Timestamp":31.8724785,"Name":"UnitDeath","Data":{"unit":"Hoverbuggy(Clone)","overkillDamage":6.0,"killTower":"Plasma Lance"}},{"Timestamp":33.2822838,"Name":"UnitSpawn","Data":{"unitSpawned":"Hoverbuggy","unitCount":11}},{"Timestamp":33.5569229,"Name":"UnitDamage","Data":{"unit":"Hoverbuggy(Clone)","damage":12.0,"hp":6.0,"attacker":"Plasma Lance"}},{"Timestamp":33.55694,"Name":"UnitDeath","Data":{"unit":"Hoverbuggy(Clone)","overkillDamage":6.0,"killTower":"Plasma Lance"}},{"Timestamp":33.9318,"Name":"Economy","Data":{"team":"Defender","currency":2.0,"income":0.0}},{"Timestamp":33.93181,"Name":"Economy","Data":{"team":"Attacker","currency":42.0,"income":41.0}},{"Timestamp":34.03586,"Name":"UnitBuying","Data":{"unitBought":"Hovercopter","currentIncome":43}},{"Timestamp":34.2006264,"Name":"UnitBuying","Data":{"unitBought":"Hovertank","currentIncome":47}},{"Timestamp":34.3671722,"Name":"UnitBuying","Data":{"unitBought":"Hoverbuggy","currentIncome":48}},{"Timestamp":35.2851067,"Name":"UnitSpawn","Data":{"unitSpawned":"Hovercopter","unitCount":12}},{"Timestamp":35.66863,"Name":"UnitDamage","Data":{"unit":"Hovercopter(Clone)","damage":12.0,"hp":16.0,"attacker":"Plasma Lance"}},{"Timestamp":36.6583748,"Name":"UnitDamage","Data":{"unit":"Hovercopter(Clone)","damage":12.0,"hp":4.0,"attacker":"Plasma Lance"}},{"Timestamp":36.6583862,"Name":"UnitDeath","Data":{"unit":"Hovercopter(Clone)","overkillDamage":8.0,"killTower":"Plasma Lance"}},{"Timestamp":36.8904457,"Name":"UnitDamage","Data":{"unit":"Hovercopter(Clone)","damage":12.0,"hp":0.0,"attacker":"Plasma Lance"}},{"Timestamp":37.2879066,"Name":"UnitSpawn","Data":{"unitSpawned":"Hoverbuggy","unitCount":13}},{"Timestamp":38.49855,"Name":"UnitDamage","Data":{"unit":"Hoverbuggy(Clone)","damage":0.25,"hp":6.0,"attacker":"Assault Cannon"}},{"Timestamp":38.7442932,"Name":"UnitDamage","Data":{"unit":"Hoverbuggy(Clone)","damage":0.25,"hp":5.75,"attacker":"Assault Cannon"}},{"Timestamp":38.9333344,"Name":"Economy","Data":{"team":"Defender","currency":4.0,"income":0.0}},{"Timestamp":38.933342,"Name":"Economy","Data":{"team":"Attacker","currency":48.0,"income":48.0}},{"Timestamp":38.987812,"Name":"UnitBuying","Data":{"unitBought":"Hovertank","currentIncome":52}},{"Timestamp":38.9954567,"Name":"UnitDamage","Data":{"unit":"Hoverbuggy(Clone)","damage":0.25,"hp":5.5,"attacker":"Assault Cannon"}},{"Timestamp":39.0036163,"Name":"UnitDamage","Data":{"unit":"Hoverbuggy(Clone)","damage":12.0,"hp":5.25,"attacker":"Plasma Lance"}},{"Timestamp":39.00363,"Name":"UnitDeath","Data":{"unit":"Hoverbuggy(Clone)","overkillDamage":6.75,"killTower":"Plasma Lance"}},{"Timestamp":39.1510048,"Name":"UnitBuying","Data":{"unitBought":"Hovercopter","currentIncome":54}},{"Timestamp":39.2896767,"Name":"UnitSpawn","Data":{"unitSpawned":"Hovercopter","unitCount":14}},{"Timestamp":39.4825363,"Name":"UnitBuying","Data":{"unitBought":"Hoverbuggy","currentIncome":55}},{"Timestamp":39.6488838,"Name":"UnitBuying","Data":{"unitBought":"Hoverbuggy","currentIncome":56}},{"Timestamp":40.23461,"Name":"UnitDamage","Data":{"unit":"Hovercopter(Clone)","damage":12.0,"hp":16.0,"attacker":"Plasma Lance"}},{"Timestamp":40.47411,"Name":"TowerBuilding","Data":{"tower":"Assault Cannon","X":7,"Y":1}},{"Timestamp":40.9826,"Name":"UnitDamage","Data":{"unit":"Hovercopter(Clone)","damage":12.0,"hp":4.0,"attacker":"Plasma Lance"}},{"Timestamp":40.9826126,"Name":"UnitDeath","Data":{"unit":"Hovercopter(Clone)","overkillDamage":8.0,"killTower":"Plasma Lance"}},{"Timestamp":41.31137,"Name":"UnitSpawn","Data":{"unitSpawned":"Hoverbuggy","unitCount":15}},{"Timestamp":42.3392525,"Name":"UnitDamage","Data":{"unit":"Hoverbuggy(Clone)","damage":12.0,"hp":6.0,"attacker":"Plasma Lance"}},{"Timestamp":42.3392639,"Name":"UnitDeath","Data":{"unit":"Hoverbuggy(Clone)","overkillDamage":6.0,"killTower":"Plasma Lance"}},{"Timestamp":43.327858,"Name":"UnitSpawn","Data":{"unitSpawned":"Hoverbuggy","unitCount":16}},{"Timestamp":43.81661,"Name":"UnitDamage","Data":{"unit":"Hoverbuggy(Clone)","damage":12.0,"hp":6.0,"attacker":"Plasma Lance"}},{"Timestamp":43.8166237,"Name":"UnitDeath","Data":{"unit":"Hoverbuggy(Clone)","overkillDamage":6.0,"killTower":"Plasma Lance"}},{"Timestamp":43.9444962,"Name":"Economy","Data":{"team":"Defender","currency":4.0,"income":0.0}},{"Timestamp":43.9445076,"Name":"Economy","Data":{"team":"Attacker","currency":57.0,"income":56.0}},{"Timestamp":44.1013756,"Name":"UnitBuying","Data":{"unitBought":"Hoverbuggy","currentIncome":57}},{"Timestamp":44.2665,"Name":"UnitBuying","Data":{"unitBought":"Hoverbuggy","currentIncome":58}},{"Timestamp":44.4304237,"Name":"UnitBuying","Data":{"unitBought":"Hoverbuggy","currentIncome":59}},{"Timestamp":44.5982552,"Name":"UnitBuying","Data":{"unitBought":"Hovercopter","currentIncome":61}},{"Timestamp":44.7599144,"Name":"UnitBuying","Data":{"unitBought":"Hovercopter","currentIncome":63}},{"Timestamp":45.32865,"Name":"UnitSpawn","Data":{"unitSpawned":"Hoverbuggy","unitCount":17}},{"Timestamp":45.9683723,"Name":"UnitDamage","Data":{"unit":"Hoverbuggy(Clone)","damage":12.0,"hp":6.0,"attacker":"Plasma Lance"}},{"Timestamp":45.9683876,"Name":"UnitDeath","Data":{"unit":"Hoverbuggy(Clone)","overkillDamage":6.0,"killTower":"Plasma Lance"}},{"Timestamp":46.58049,"Name":"TowerBuilding","Data":{"tower":"Assault Cannon","X":2,"Y":0}},{"Timestamp":47.3293571,"Name":"UnitSpawn","Data":{"unitSpawned":"Hovercopter","unitCount":18}},{"Timestamp":47.7778625,"Name":"UnitDamage","Data":{"unit":"Hovercopter(Clone)","damage":12.0,"hp":16.0,"attacker":"Plasma Lance"}},{"Timestamp":48.9464455,"Name":"Economy","Data":{"team":"Defender","currency":0.0,"income":0.0}},{"Timestamp":48.9464569,"Name":"Economy","Data":{"team":"Attacker","currency":65.0,"income":63.0}},{"Timestamp":48.99523,"Name":"UnitDamage","Data":{"unit":"Hovercopter(Clone)","damage":0.25,"hp":4.0,"attacker":"Assault Cannon"}},{"Timestamp":49.14761,"Name":"UnitDamage","Data":{"unit":"Hovercopter(Clone)","damage":12.0,"hp":3.75,"attacker":"Plasma Lance"}},{"Timestamp":49.14762,"Name":"UnitDeath","Data":{"unit":"Hovercopter(Clone)","overkillDamage":8.25,"killTower":"Plasma Lance"}},{"Timestamp":49.2560959,"Name":"UnitDamage","Data":{"unit":"Hovercopter(Clone)","damage":0.25,"hp":0.0,"attacker":"Assault Cannon"}},{"Timestamp":49.31208,"Name":"UnitDamage","Data":{"unit":"Hovercopter(Clone)","damage":12.0,"hp":0.0,"attacker":"Plasma Lance"}},{"Timestamp":49.33209,"Name":"UnitSpawn","Data":{"unitSpawned":"Hoverbuggy","unitCount":19}},{"Timestamp":50.2146645,"Name":"UnitDamage","Data":{"unit":"Hoverbuggy(Clone)","damage":0.25,"hp":6.0,"attacker":"Assault Cannon"}},{"Timestamp":50.4330254,"Name":"UnitDamage","Data":{"unit":"Hoverbuggy(Clone)","damage":0.25,"hp":5.75,"attacker":"Assault Cannon"}},{"Timestamp":50.4544373,"Name":"UnitDamage","Data":{"unit":"Hoverbuggy(Clone)","damage":0.25,"hp":5.5,"attacker":"Assault Cannon"}},{"Timestamp":50.6870422,"Name":"UnitDamage","Data":{"unit":"Hoverbuggy(Clone)","damage":0.25,"hp":5.25,"attacker":"Assault Cannon"}},{"Timestamp":50.7088547,"Name":"UnitDamage","Data":{"unit":"Hoverbuggy(Clone)","damage":0.25,"hp":5.0,"attacker":"Assault Cannon"}},{"Timestamp":50.9408951,"Name":"UnitDamage","Data":{"unit":"Hoverbuggy(Clone)","damage":0.25,"hp":4.75,"attacker":"Assault Cannon"}},{"Timestamp":50.9763947,"Name":"UnitDamage","Data":{"unit":"Hoverbuggy(Clone)","damage":0.25,"hp":4.5,"attacker":"Assault Cannon"}},{"Timestamp":51.12537,"Name":"UnitDamage","Data":{"unit":"Hoverbuggy(Clone)","damage":12.0,"hp":4.25,"attacker":"Plasma Lance"}},{"Timestamp":51.1253853,"Name":"UnitDeath","Data":{"unit":"Hoverbuggy(Clone)","overkillDamage":7.75,"killTower":"Plasma Lance"}},{"Timestamp":51.20698,"Name":"UnitDamage","Data":{"unit":"Hoverbuggy(Clone)","damage":0.25,"hp":0.0,"attacker":"Assault Cannon"}},{"Timestamp":51.2296066,"Name":"UnitDamage","Data":{"unit":"Hoverbuggy(Clone)","damage":0.25,"hp":0.0,"attacker":"Assault Cannon"}},{"Timestamp":51.22964,"Name":"UnitDamage","Data":{"unit":"Hoverbuggy(Clone)","damage":0.25,"hp":0.0,"attacker":"Assault Cannon"}},{"Timestamp":51.3352165,"Name":"UnitSpawn","Data":{"unitSpawned":"Hoverbuggy","unitCount":20}},{"Timestamp":52.4164,"Name":"UnitDamage","Data":{"unit":"Hoverbuggy(Clone)","damage":0.25,"hp":6.0,"attacker":"Assault Cannon"}},{"Timestamp":52.56304,"Name":"UnitDamage","Data":{"unit":"Hoverbuggy(Clone)","damage":12.0,"hp":5.75,"attacker":"Plasma Lance"}},{"Timestamp":52.5630569,"Name":"UnitDeath","Data":{"unit":"Hoverbuggy(Clone)","overkillDamage":6.25,"killTower":"Plasma Lance"}},{"Timestamp":52.64474,"Name":"UnitDamage","Data":{"unit":"Hoverbuggy(Clone)","damage":12.0,"hp":0.0,"attacker":"Plasma Lance"}},{"Timestamp":52.6447754,"Name":"UnitDamage","Data":{"unit":"Hoverbuggy(Clone)","damage":0.25,"hp":0.0,"attacker":"Assault Cannon"}},{"Timestamp":52.66716,"Name":"UnitDamage","Data":{"unit":"Hoverbuggy(Clone)","damage":0.25,"hp":0.0,"attacker":"Assault Cannon"}},{"Timestamp":53.34914,"Name":"UnitSpawn","Data":{"unitSpawned":"Hoverbuggy","unitCount":21}},{"Timestamp":53.9491,"Name":"Economy","Data":{"team":"Defender","currency":4.0,"income":0.0}},{"Timestamp":53.94911,"Name":"Economy","Data":{"team":"Attacker","currency":66.0,"income":63.0}},{"Timestamp":54.3356323,"Name":"UnitDamage","Data":{"unit":"Hoverbuggy(Clone)","damage":0.25,"hp":6.0,"attacker":"Assault Cannon"}},{"Timestamp":54.46164,"Name":"UnitDamage","Data":{"unit":"Hoverbuggy(Clone)","damage":12.0,"hp":5.75,"attacker":"Plasma Lance"}},{"Timestamp":54.46167,"Name":"UnitDeath","Data":{"unit":"Hoverbuggy(Clone)","overkillDamage":6.25,"killTower":"Plasma Lance"}},{"Timestamp":54.5301933,"Name":"UnitDamage","Data":{"unit":"Hoverbuggy(Clone)","damage":0.25,"hp":0.0,"attacker":"Assault Cannon"}},{"Timestamp":55.35256,"Name":"UnitSpawn","Data":{"unitSpawned":"Hoverbuggy","unitCount":22}},{"Timestamp":55.9874077,"Name":"UnitDamage","Data":{"unit":"Hoverbuggy(Clone)","damage":12.0,"hp":6.0,"attacker":"Plasma Lance"}},{"Timestamp":55.9874268,"Name":"UnitDeath","Data":{"unit":"Hoverbuggy(Clone)","overkillDamage":6.0,"killTower":"Plasma Lance"}},{"Timestamp":57.3527756,"Name":"UnitSpawn","Data":{"unitSpawned":"Hovercopter","unitCount":23}},{"Timestamp":57.8406639,"Name":"UnitDamage","Data":{"unit":"Hovercopter(Clone)","damage":12.0,"hp":16.0,"attacker":"Plasma Lance"}},{"Timestamp":57.9640656,"Name":"TowerBuilding","Data":{"tower":"Assault Cannon","X":3,"Y":1}},{"Timestamp":58.95727,"Name":"Economy","Data":{"team":"Defender","currency":1.0,"income":0.0}},{"Timestamp":58.95728,"Name":"Economy","Data":{"team":"Attacker","currency":67.0,"income":63.0}},{"Timestamp":59.0596237,"Name":"UnitDamage","Data":{"unit":"Hovercopter(Clone)","damage":0.25,"hp":4.0,"attacker":"Assault Cannon"}},{"Timestamp":59.2090454,"Name":"UnitDamage","Data":{"unit":"Hovercopter(Clone)","damage":12.0,"hp":3.75,"attacker":"Plasma Lance"}},{"Timestamp":59.20906,"Name":"UnitDeath","Data":{"unit":"Hovercopter(Clone)","overkillDamage":8.25,"killTower":"Plasma Lance"}},{"Timestamp":59.3173523,"Name":"UnitDamage","Data":{"unit":"Hovercopter(Clone)","damage":12.0,"hp":0.0,"attacker":"Plasma Lance"}},{"Timestamp":59.3173828,"Name":"UnitDamage","Data":{"unit":"Hovercopter(Clone)","damage":0.25,"hp":0.0,"attacker":"Assault Cannon"}},{"Timestamp":59.3559837,"Name":"UnitSpawn","Data":{"unitSpawned":"Hovercopter","unitCount":24}},{"Timestamp":60.73002,"Name":"UnitDamage","Data":{"unit":"Hovercopter(Clone)","damage":0.25,"hp":16.0,"attacker":"Assault Cannon"}},{"Timestamp":60.98011,"Name":"UnitDamage","Data":{"unit":"Hovercopter(Clone)","damage":0.25,"hp":15.75,"attacker":"Assault Cannon"}},{"Timestamp":60.9943428,"Name":"UnitDamage","Data":{"unit":"Hovercopter(Clone)","damage":0.25,"hp":15.5,"attacker":"Assault Cannon"}},{"Timestamp":61.06824,"Name":"UnitDamage","Data":{"unit":"Hovercopter(Clone)","damage":0.25,"hp":15.25,"attacker":"Assault Cannon"}},{"Timestamp":61.1930923,"Name":"UnitDamage","Data":{"unit":"Hovercopter(Clone)","damage":12.0,"hp":15.0,"attacker":"Plasma Lance"}},{"Timestamp":61.23617,"Name":"UnitDamage","Data":{"unit":"Hovercopter(Clone)","damage":0.25,"hp":3.0,"attacker":"Assault Cannon"}},{"Timestamp":61.2615547,"Name":"UnitDamage","Data":{"unit":"Hovercopter(Clone)","damage":0.25,"hp":2.75,"attacker":"Assault Cannon"}},{"Timestamp":61.3193474,"Name":"UnitDamage","Data":{"unit":"Hovercopter(Clone)","damage":0.25,"hp":2.5,"attacker":"Assault Cannon"}},{"Timestamp":61.3571129,"Name":"UnitSpawn","Data":{"unitSpawned":"Hoverbuggy","unitCount":25}},{"Timestamp":61.4898453,"Name":"UnitDamage","Data":{"unit":"Hovercopter(Clone)","damage":0.25,"hp":2.25,"attacker":"Assault Cannon"}},{"Timestamp":61.5001755,"Name":"UnitDamage","Data":{"unit":"Hovercopter(Clone)","damage":0.25,"hp":2.0,"attacker":"Assault Cannon"}},{"Timestamp":61.57684,"Name":"UnitDamage","Data":{"unit":"Hovercopter(Clone)","damage":0.25,"hp":1.75,"attacker":"Assault Cannon"}},{"Timestamp":61.74239,"Name":"UnitDamage","Data":{"unit":"Hovercopter(Clone)","damage":0.25,"hp":1.5,"attacker":"Assault Cannon"}},{"Timestamp":61.7668762,"Name":"UnitDamage","Data":{"unit":"Hovercopter(Clone)","damage":0.25,"hp":1.25,"attacker":"Assault Cannon"}},{"Timestamp":61.830677,"Name":"UnitDamage","Data":{"unit":"Hovercopter(Clone)","damage":0.25,"hp":1.0,"attacker":"Assault Cannon"}},{"Timestamp":61.987175,"Name":"UnitDamage","Data":{"unit":"Hovercopter(Clone)","damage":0.25,"hp":0.75,"attacker":"Assault Cannon"}},{"Timestamp":62.0058174,"Name":"UnitDamage","Data":{"unit":"Hovercopter(Clone)","damage":0.25,"hp":0.5,"attacker":"Assault Cannon"}},{"Timestamp":62.0961876,"Name":"UnitDamage","Data":{"unit":"Hovercopter(Clone)","damage":0.25,"hp":0.25,"attacker":"Assault Cannon"}},{"Timestamp":62.0962029,"Name":"UnitDeath","Data":{"unit":"Hovercopter(Clone)","overkillDamage":0.0,"killTower":"Assault Cannon"}},{"Timestamp":62.2540474,"Name":"TowerBuilding","Data":{"tower":"Assault Cannon","X":4,"Y":1}},{"Timestamp":62.33009,"Name":"UnitDamage","Data":{"unit":"Hoverbuggy(Clone)","damage":0.25,"hp":6.0,"attacker":"Assault Cannon"}},{"Timestamp":62.45785,"Name":"UnitDamage","Data":{"unit":"Hoverbuggy(Clone)","damage":0.25,"hp":5.75,"attacker":"Assault Cannon"}},{"Timestamp":62.5315933,"Name":"UnitDamage","Data":{"unit":"Hoverbuggy(Clone)","damage":0.25,"hp":5.5,"attacker":"Assault Cannon"}},{"Timestamp":62.54785,"Name":"UnitDamage","Data":{"unit":"Hoverbuggy(Clone)","damage":12.0,"hp":5.25,"attacker":"Plasma Lance"}},{"Timestamp":62.547863,"Name":"UnitDeath","Data":{"unit":"Hoverbuggy(Clone)","overkillDamage":6.75,"killTower":"Plasma Lance"}},{"Timestamp":62.5906067,"Name":"UnitDamage","Data":{"unit":"Hoverbuggy(Clone)","damage":0.25,"hp":0.0,"attacker":"Assault Cannon"}},{"Timestamp":62.6503563,"Name":"UnitDamage","Data":{"unit":"Hoverbuggy(Clone)","damage":12.0,"hp":0.0,"attacker":"Plasma Lance"}},{"Timestamp":63.35949,"Name":"UnitSpawn","Data":{"unitSpawned":"Hovercopter","unitCount":26}},{"Timestamp":63.96254,"Name":"Economy","Data":{"team":"Defender","currency":1.0,"income":0.0}},{"Timestamp":63.96255,"Name":"Economy","Data":{"team":"Attacker","currency":63.0,"income":63.0}},{"Timestamp":64.528244,"Name":"UnitDamage","Data":{"unit":"Hovercopter(Clone)","damage":12.0,"hp":16.0,"attacker":"Plasma Lance"}},{"Timestamp":64.62676,"Name":"UnitDamage","Data":{"unit":"Hovercopter(Clone)","damage":0.25,"hp":4.0,"attacker":"Assault Cannon"}},{"Timestamp":64.87639,"Name":"UnitDamage","Data":{"unit":"Hovercopter(Clone)","damage":0.25,"hp":3.75,"attacker":"Assault Cannon"}},{"Timestamp":64.91942,"Name":"UnitDamage","Data":{"unit":"Hovercopter(Clone)","damage":0.25,"hp":3.5,"attacker":"Assault Cannon"}},{"Timestamp":65.00233,"Name":"UnitDamage","Data":{"unit":"Hovercopter(Clone)","damage":0.25,"hp":3.25,"attacker":"Assault Cannon"}},{"Timestamp":65.1311951,"Name":"UnitDamage","Data":{"unit":"Hovercopter(Clone)","damage":0.25,"hp":3.0,"attacker":"Assault Cannon"}},{"Timestamp":65.17987,"Name":"UnitDamage","Data":{"unit":"Hovercopter(Clone)","damage":0.25,"hp":2.75,"attacker":"Assault Cannon"}},{"Timestamp":65.25236,"Name":"UnitDamage","Data":{"unit":"Hovercopter(Clone)","damage":0.25,"hp":2.5,"attacker":"Assault Cannon"}},{"Timestamp":65.25239,"Name":"UnitDamage","Data":{"unit":"Hovercopter(Clone)","damage":0.25,"hp":2.25,"attacker":"Assault Cannon"}},{"Timestamp":65.35975,"Name":"UnitSpawn","Data":{"unitSpawned":"Hoverbuggy","unitCount":27}},{"Timestamp":65.3938141,"Name":"UnitDamage","Data":{"unit":"Hovercopter(Clone)","damage":0.25,"hp":2.0,"attacker":"Assault Cannon"}},{"Timestamp":65.43468,"Name":"UnitDamage","Data":{"unit":"Hovercopter(Clone)","damage":0.25,"hp":1.75,"attacker":"Assault Cannon"}},{"Timestamp":65.5143661,"Name":"UnitDamage","Data":{"unit":"Hovercopter(Clone)","damage":0.25,"hp":1.5,"attacker":"Assault Cannon"}},{"Timestamp":65.51443,"Name":"UnitDamage","Data":{"unit":"Hovercopter(Clone)","damage":0.25,"hp":1.25,"attacker":"Assault Cannon"}},{"Timestamp":65.63265,"Name":"UnitDamage","Data":{"unit":"Hovercopter(Clone)","damage":0.25,"hp":1.0,"attacker":"Assault Cannon"}},{"Timestamp":65.68495,"Name":"UnitDamage","Data":{"unit":"Hovercopter(Clone)","damage":0.25,"hp":0.75,"attacker":"Assault Cannon"}},{"Timestamp":65.77152,"Name":"UnitDamage","Data":{"unit":"Hovercopter(Clone)","damage":0.25,"hp":0.5,"attacker":"Assault Cannon"}},{"Timestamp":65.77169,"Name":"UnitDamage","Data":{"unit":"Hovercopter(Clone)","damage":0.25,"hp":0.25,"attacker":"Assault Cannon"}},{"Timestamp":65.77169,"Name":"UnitDeath","Data":{"unit":"Hovercopter(Clone)","overkillDamage":0.0,"killTower":"Assault Cannon"}},{"Timestamp":65.8891449,"Name":"UnitDamage","Data":{"unit":"Hovercopter(Clone)","damage":12.0,"hp":0.0,"attacker":"Plasma Lance"}},{"Timestamp":65.9872,"Name":"UnitDamage","Data":{"unit":"Hovercopter(Clone)","damage":12.0,"hp":0.0,"attacker":"Plasma Lance"}},{"Timestamp":66.27423,"Name":"UnitDamage","Data":{"unit":"Hoverbuggy(Clone)","damage":0.25,"hp":6.0,"attacker":"Assault Cannon"}},{"Timestamp":66.4398,"Name":"UnitDamage","Data":{"unit":"Hoverbuggy(Clone)","damage":0.25,"hp":5.75,"attacker":"Assault Cannon"}},{"Timestamp":66.51084,"Name":"UnitDamage","Data":{"unit":"Hoverbuggy(Clone)","damage":0.25,"hp":5.5,"attacker":"Assault Cannon"}},{"Timestamp":66.52519,"Name":"UnitDamage","Data":{"unit":"Hoverbuggy(Clone)","damage":0.25,"hp":5.25,"attacker":"Assault Cannon"}},{"Timestamp":66.67269,"Name":"UnitDamage","Data":{"unit":"Hoverbuggy(Clone)","damage":0.25,"hp":5.0,"attacker":"Assault Cannon"}},{"Timestamp":66.70662,"Name":"UnitDamage","Data":{"unit":"Hoverbuggy(Clone)","damage":0.25,"hp":4.75,"attacker":"Assault Cannon"}},{"Timestamp":66.76524,"Name":"UnitDamage","Data":{"unit":"Hoverbuggy(Clone)","damage":0.25,"hp":4.5,"attacker":"Assault Cannon"}},{"Timestamp":66.78061,"Name":"UnitDamage","Data":{"unit":"Hoverbuggy(Clone)","damage":0.25,"hp":4.25,"attacker":"Assault Cannon"}},{"Timestamp":66.9296,"Name":"UnitDamage","Data":{"unit":"Hoverbuggy(Clone)","damage":0.25,"hp":4.0,"attacker":"Assault Cannon"}},{"Timestamp":66.94722,"Name":"UnitDamage","Data":{"unit":"Hoverbuggy(Clone)","damage":0.25,"hp":3.75,"attacker":"Assault Cannon"}},{"Timestamp":67.01273,"Name":"UnitDamage","Data":{"unit":"Hoverbuggy(Clone)","damage":0.25,"hp":3.5,"attacker":"Assault Cannon"}},{"Timestamp":67.04257,"Name":"UnitDamage","Data":{"unit":"Hoverbuggy(Clone)","damage":0.25,"hp":3.25,"attacker":"Assault Cannon"}},{"Timestamp":67.17875,"Name":"UnitDamage","Data":{"unit":"Hoverbuggy(Clone)","damage":0.25,"hp":3.0,"attacker":"Assault Cannon"}},{"Timestamp":67.2085,"Name":"UnitDamage","Data":{"unit":"Hoverbuggy(Clone)","damage":0.25,"hp":2.75,"attacker":"Assault Cannon"}},{"Timestamp":67.26428,"Name":"UnitDamage","Data":{"unit":"Hoverbuggy(Clone)","damage":0.25,"hp":2.5,"attacker":"Assault Cannon"}},{"Timestamp":67.26865,"Name":"UnitDamage","Data":{"unit":"Hoverbuggy(Clone)","damage":0.25,"hp":2.25,"attacker":"Assault Cannon"}},{"Timestamp":67.28482,"Name":"UnitDamage","Data":{"unit":"Hoverbuggy(Clone)","damage":0.25,"hp":2.0,"attacker":"Assault Cannon"}},{"Timestamp":67.33361,"Name":"UnitDamage","Data":{"unit":"Hoverbuggy(Clone)","damage":0.25,"hp":1.75,"attacker":"Assault Cannon"}},{"Timestamp":67.37393,"Name":"UnitSpawn","Data":{"unitSpawned":"Hovercopter","unitCount":28}},{"Timestamp":67.43738,"Name":"UnitDamage","Data":{"unit":"Hoverbuggy(Clone)","damage":0.25,"hp":1.5,"attacker":"Assault Cannon"}},{"Timestamp":67.4535446,"Name":"UnitDamage","Data":{"unit":"Hoverbuggy(Clone)","damage":0.25,"hp":1.25,"attacker":"Assault Cannon"}},{"Timestamp":67.51641,"Name":"UnitDamage","Data":{"unit":"Hoverbuggy(Clone)","damage":0.25,"hp":1.0,"attacker":"Assault Cannon"}},{"Timestamp":67.543,"Name":"UnitDamage","Data":{"unit":"Hoverbuggy(Clone)","damage":0.25,"hp":0.75,"attacker":"Assault Cannon"}},{"Timestamp":67.54304,"Name":"UnitDamage","Data":{"unit":"Hoverbuggy(Clone)","damage":0.25,"hp":0.5,"attacker":"Assault Cannon"}},{"Timestamp":67.58509,"Name":"UnitDamage","Data":{"unit":"Hoverbuggy(Clone)","damage":0.25,"hp":0.25,"attacker":"Assault Cannon"}},{"Timestamp":67.5851059,"Name":"UnitDeath","Data":{"unit":"Hoverbuggy(Clone)","overkillDamage":0.0,"killTower":"Assault Cannon"}},{"Timestamp":67.69725,"Name":"UnitDamage","Data":{"unit":"Hoverbuggy(Clone)","damage":0.25,"hp":0.0,"attacker":"Assault Cannon"}},{"Timestamp":67.86798,"Name":"UnitDamage","Data":{"unit":"Hovercopter(Clone)","damage":12.0,"hp":16.0,"attacker":"Plasma Lance"}},{"Timestamp":68.6310654,"Name":"UnitDamage","Data":{"unit":"Hovercopter(Clone)","damage":0.25,"hp":4.0,"attacker":"Assault Cannon"}},{"Timestamp":68.88422,"Name":"UnitDamage","Data":{"unit":"Hovercopter(Clone)","damage":0.25,"hp":3.75,"attacker":"Assault Cannon"}},{"Timestamp":68.91056,"Name":"UnitDamage","Data":{"unit":"Hovercopter(Clone)","damage":0.25,"hp":3.5,"attacker":"Assault Cannon"}},{"Timestamp":68.96073,"Name":"UnitDamage","Data":{"unit":"Hovercopter(Clone)","damage":0.25,"hp":3.25,"attacker":"Assault Cannon"}},{"Timestamp":68.96376,"Name":"Economy","Data":{"team":"Defender","currency":4.0,"income":0.0}},{"Timestamp":68.96377,"Name":"Economy","Data":{"team":"Attacker","currency":66.0,"income":63.0}},{"Timestamp":69.13737,"Name":"UnitDamage","Data":{"unit":"Hovercopter(Clone)","damage":0.25,"hp":3.0,"attacker":"Assault Cannon"}},{"Timestamp":69.16365,"Name":"UnitDamage","Data":{"unit":"Hovercopter(Clone)","damage":0.25,"hp":2.75,"attacker":"Assault Cannon"}},{"Timestamp":69.2122955,"Name":"UnitDamage","Data":{"unit":"Hovercopter(Clone)","damage":0.25,"hp":2.5,"attacker":"Assault Cannon"}},{"Timestamp":69.2224655,"Name":"UnitDamage","Data":{"unit":"Hovercopter(Clone)","damage":12.0,"hp":2.25,"attacker":"Plasma Lance"}},{"Timestamp":69.22248,"Name":"UnitDeath","Data":{"unit":"Hovercopter(Clone)","overkillDamage":9.75,"killTower":"Plasma Lance"}},{"Timestamp":69.24366,"Name":"UnitDamage","Data":{"unit":"Hovercopter(Clone)","damage":0.25,"hp":0.0,"attacker":"Assault Cannon"}},{"Timestamp":69.3274,"Name":"UnitDamage","Data":{"unit":"Hovercopter(Clone)","damage":12.0,"hp":0.0,"attacker":"Plasma Lance"}},{"Timestamp":69.37641,"Name":"UnitSpawn","Data":{"unitSpawned":"Hoverbuggy","unitCount":29}},{"Timestamp":69.51942,"Name":"TowerBuilding","Data":{"tower":"Assault Cannon","X":5,"Y":0}},{"Timestamp":70.44831,"Name":"UnitDamage","Data":{"unit":"Hoverbuggy(Clone)","damage":0.25,"hp":6.0,"attacker":"Assault Cannon"}},{"Timestamp":70.62985,"Name":"UnitDamage","Data":{"unit":"Hoverbuggy(Clone)","damage":0.25,"hp":5.75,"attacker":"Assault Cannon"}},{"Timestamp":70.67231,"Name":"UnitDamage","Data":{"unit":"Hoverbuggy(Clone)","damage":0.25,"hp":5.5,"attacker":"Assault Cannon"}},{"Timestamp":70.69836,"Name":"UnitDamage","Data":{"unit":"Hoverbuggy(Clone)","damage":0.25,"hp":5.25,"attacker":"Assault Cannon"}},{"Timestamp":70.83898,"Name":"UnitDamage","Data":{"unit":"Hoverbuggy(Clone)","damage":0.25,"hp":5.0,"attacker":"Assault Cannon"}},{"Timestamp":70.88052,"Name":"UnitDamage","Data":{"unit":"Hoverbuggy(Clone)","damage":0.25,"hp":4.75,"attacker":"Assault Cannon"}},{"Timestamp":70.9195,"Name":"UnitDamage","Data":{"unit":"Hoverbuggy(Clone)","damage":0.25,"hp":4.5,"attacker":"Assault Cannon"}},{"Timestamp":70.95002,"Name":"UnitDamage","Data":{"unit":"Hoverbuggy(Clone)","damage":0.25,"hp":4.25,"attacker":"Assault Cannon"}},{"Timestamp":71.07846,"Name":"UnitDamage","Data":{"unit":"Hoverbuggy(Clone)","damage":0.25,"hp":4.0,"attacker":"Assault Cannon"}},{"Timestamp":71.10975,"Name":"UnitDamage","Data":{"unit":"Hoverbuggy(Clone)","damage":0.25,"hp":3.75,"attacker":"Assault Cannon"}},{"Timestamp":71.13387,"Name":"UnitDamage","Data":{"unit":"Hoverbuggy(Clone)","damage":0.25,"hp":3.5,"attacker":"Assault Cannon"}},{"Timestamp":71.17887,"Name":"UnitDamage","Data":{"unit":"Hoverbuggy(Clone)","damage":0.25,"hp":3.25,"attacker":"Assault Cannon"}},{"Timestamp":71.1999741,"Name":"UnitDamage","Data":{"unit":"Hoverbuggy(Clone)","damage":12.0,"hp":3.0,"attacker":"Plasma Lance"}},{"Timestamp":71.19999,"Name":"UnitDeath","Data":{"unit":"Hoverbuggy(Clone)","overkillDamage":9.0,"killTower":"Plasma Lance"}},{"Timestamp":71.20001,"Name":"UnitDamage","Data":{"unit":"Hoverbuggy(Clone)","damage":0.25,"hp":0.0,"attacker":"Assault Cannon"}},{"Timestamp":71.37702,"Name":"UnitSpawn","Data":{"unitSpawned":"Hoverbuggy","unitCount":30}},{"Timestamp":72.379425,"Name":"UnitDamage","Data":{"unit":"Hoverbuggy(Clone)","damage":0.25,"hp":6.0,"attacker":"Assault Cannon"}},{"Timestamp":72.56039,"Name":"UnitDamage","Data":{"unit":"Hoverbuggy(Clone)","damage":12.0,"hp":5.75,"attacker":"Plasma Lance"}},{"Timestamp":72.5604,"Name":"UnitDeath","Data":{"unit":"Hoverbuggy(Clone)","overkillDamage":6.25,"killTower":"Plasma Lance"}},{"Timestamp":72.59213,"Name":"UnitDamage","Data":{"unit":"Hoverbuggy(Clone)","damage":0.25,"hp":0.0,"attacker":"Assault Cannon"}},{"Timestamp":72.62464,"Name":"UnitDamage","Data":{"unit":"Hoverbuggy(Clone)","damage":0.25,"hp":0.0,"attacker":"Assault Cannon"}},{"Timestamp":72.6479645,"Name":"UnitDamage","Data":{"unit":"Hoverbuggy(Clone)","damage":0.25,"hp":0.0,"attacker":"Assault Cannon"}},{"Timestamp":72.66467,"Name":"UnitDamage","Data":{"unit":"Hoverbuggy(Clone)","damage":12.0,"hp":0.0,"attacker":"Plasma Lance"}},{"Timestamp":73.3818,"Name":"UnitSpawn","Data":{"unitSpawned":"Hoverbuggy","unitCount":31}},{"Timestamp":73.97359,"Name":"Economy","Data":{"team":"Defender","currency":3.0,"income":0.0}},{"Timestamp":73.9735947,"Name":"Economy","Data":{"team":"Attacker","currency":64.0,"income":63.0}},{"Timestamp":74.46724,"Name":"UnitDamage","Data":{"unit":"Hoverbuggy(Clone)","damage":0.25,"hp":6.0,"attacker":"Assault Cannon"}},{"Timestamp":74.53411,"Name":"UnitDamage","Data":{"unit":"Hoverbuggy(Clone)","damage":12.0,"hp":5.75,"attacker":"Plasma Lance"}},{"Timestamp":74.53413,"Name":"UnitDeath","Data":{"unit":"Hoverbuggy(Clone)","overkillDamage":6.25,"killTower":"Plasma Lance"}},{"Timestamp":74.6332245,"Name":"UnitDamage","Data":{"unit":"Hoverbuggy(Clone)","damage":0.25,"hp":0.0,"attacker":"Assault Cannon"}},{"Timestamp":75.38424,"Name":"UnitSpawn","Data":{"unitSpawned":"Hoverbuggy","unitCount":32}},{"Timestamp":76.00184,"Name":"UnitDamage","Data":{"unit":"Hoverbuggy(Clone)","damage":12.0,"hp":6.0,"attacker":"Plasma Lance"}},{"Timestamp":76.0018539,"Name":"UnitDeath","Data":{"unit":"Hoverbuggy(Clone)","overkillDamage":6.0,"killTower":"Plasma Lance"}},{"Timestamp":77.38666,"Name":"UnitSpawn","Data":{"unitSpawned":"Hoverbuggy","unitCount":33}},{"Timestamp":77.8689957,"Name":"UnitDamage","Data":{"unit":"Hoverbuggy(Clone)","damage":12.0,"hp":6.0,"attacker":"Plasma Lance"}},{"Timestamp":77.86902,"Name":"UnitDeath","Data":{"unit":"Hoverbuggy(Clone)","overkillDamage":6.0,"killTower":"Plasma Lance"}},{"Timestamp":78.97395,"Name":"Economy","Data":{"team":"Defender","currency":6.0,"income":0.0}},{"Timestamp":78.97397,"Name":"Economy","Data":{"team":"Attacker","currency":67.0,"income":63.0}},{"Timestamp":79.38806,"Name":"UnitSpawn","Data":{"unitSpawned":"Hovercopter","unitCount":34}},{"Timestamp":80.00113,"Name":"UnitDamage","Data":{"unit":"Hovercopter(Clone)","damage":12.0,"hp":16.0,"attacker":"Plasma Lance"}},{"Timestamp":80.86573,"Name":"UnitDamage","Data":{"unit":"Hovercopter(Clone)","damage":0.25,"hp":4.0,"attacker":"Assault Cannon"}},{"Timestamp":81.0136,"Name":"UnitDamage","Data":{"unit":"Hovercopter(Clone)","damage":12.0,"hp":3.75,"attacker":"Plasma Lance"}},{"Timestamp":81.0136261,"Name":"UnitDeath","Data":{"unit":"Hovercopter(Clone)","overkillDamage":8.25,"killTower":"Plasma Lance"}},{"Timestamp":81.11599,"Name":"UnitDamage","Data":{"unit":"Hovercopter(Clone)","damage":0.25,"hp":0.0,"attacker":"Assault Cannon"}},{"Timestamp":81.20337,"Name":"UnitDamage","Data":{"unit":"Hovercopter(Clone)","damage":12.0,"hp":0.0,"attacker":"Plasma Lance"}},{"Timestamp":81.39759,"Name":"UnitSpawn","Data":{"unitSpawned":"Hovertank","unitCount":35}},{"Timestamp":81.8899,"Name":"TowerBuilding","Data":{"tower":"Assault Cannon","X":6,"Y":1}},{"Timestamp":83.34343,"Name":"UnitDamage","Data":{"unit":"Hovertank(Clone)","damage":12.0,"hp":35.0,"attacker":"Plasma Lance"}},{"Timestamp":83.40194,"Name":"UnitSpawn","Data":{"unitSpawned":"Hoverbuggy","unitCount":36}},{"Timestamp":83.43652,"Name":"UnitDamage","Data":{"unit":"Hovertank(Clone)","damage":0.25,"hp":23.0,"attacker":"Assault Cannon"}},{"Timestamp":83.7011261,"Name":"UnitDamage","Data":{"unit":"Hovertank(Clone)","damage":0.25,"hp":22.75,"attacker":"Assault Cannon"}},{"Timestamp":83.89565,"Name":"UnitDamage","Data":{"unit":"Hovertank(Clone)","damage":0.25,"hp":22.5,"attacker":"Assault Cannon"}},{"Timestamp":83.93873,"Name":"UnitDamage","Data":{"unit":"Hovertank(Clone)","damage":0.25,"hp":22.25,"attacker":"Assault Cannon"}},{"Timestamp":83.97478,"Name":"Economy","Data":{"team":"Defender","currency":3.0,"income":0.0}},{"Timestamp":83.97479,"Name":"Economy","Data":{"team":"Attacker","currency":63.0,"income":63.0}},{"Timestamp":83.97962,"Name":"UnitDamage","Data":{"unit":"Hovertank(Clone)","damage":0.25,"hp":22.0,"attacker":"Assault Cannon"}},{"Timestamp":84.15441,"Name":"UnitDamage","Data":{"unit":"Hovertank(Clone)","damage":0.25,"hp":21.75,"attacker":"Assault Cannon"}},{"Timestamp":84.20622,"Name":"UnitDamage","Data":{"unit":"Hovertank(Clone)","damage":0.25,"hp":21.5,"attacker":"Assault Cannon"}},{"Timestamp":84.22871,"Name":"UnitDamage","Data":{"unit":"Hovertank(Clone)","damage":0.25,"hp":21.25,"attacker":"Assault Cannon"}},{"Timestamp":84.36505,"Name":"UnitDamage","Data":{"unit":"Hovertank(Clone)","damage":12.0,"hp":21.0,"attacker":"Plasma Lance"}},{"Timestamp":84.3903961,"Name":"UnitDamage","Data":{"unit":"Hovertank(Clone)","damage":0.25,"hp":9.0,"attacker":"Assault Cannon"}},{"Timestamp":84.40197,"Name":"UnitDamage","Data":{"unit":"Hovertank(Clone)","damage":0.25,"hp":8.75,"attacker":"Assault Cannon"}},{"Timestamp":84.44508,"Name":"UnitDamage","Data":{"unit":"Hovertank(Clone)","damage":0.25,"hp":8.5,"attacker":"Assault Cannon"}},{"Timestamp":84.48504,"Name":"UnitDamage","Data":{"unit":"Hovertank(Clone)","damage":0.25,"hp":8.25,"attacker":"Assault Cannon"}},{"Timestamp":84.53723,"Name":"UnitDamage","Data":{"unit":"Hovertank(Clone)","damage":12.0,"hp":8.0,"attacker":"Plasma Lance"}},{"Timestamp":84.53725,"Name":"UnitDeath","Data":{"unit":"Hovertank(Clone)","overkillDamage":4.0,"killTower":"Plasma Lance"}},{"Timestamp":84.6603546,"Name":"UnitDamage","Data":{"unit":"Hoverbuggy(Clone)","damage":0.25,"hp":6.0,"attacker":"Assault Cannon"}},{"Timestamp":84.70357,"Name":"UnitDamage","Data":{"unit":"Hoverbuggy(Clone)","damage":0.25,"hp":5.75,"attacker":"Assault Cannon"}},{"Timestamp":84.72111,"Name":"UnitDamage","Data":{"unit":"Hoverbuggy(Clone)","damage":0.25,"hp":5.5,"attacker":"Assault Cannon"}},{"Timestamp":84.7363,"Name":"UnitDamage","Data":{"unit":"Hoverbuggy(Clone)","damage":0.25,"hp":5.25,"attacker":"Assault Cannon"}},{"Timestamp":84.91801,"Name":"UnitDamage","Data":{"unit":"Hoverbuggy(Clone)","damage":0.25,"hp":5.0,"attacker":"Assault Cannon"}},{"Timestamp":84.9482346,"Name":"UnitDamage","Data":{"unit":"Hoverbuggy(Clone)","damage":0.25,"hp":4.75,"attacker":"Assault Cannon"}},{"Timestamp":84.9833145,"Name":"UnitDamage","Data":{"unit":"Hoverbuggy(Clone)","damage":0.25,"hp":4.5,"attacker":"Assault Cannon"}},{"Timestamp":84.9876862,"Name":"UnitDamage","Data":{"unit":"Hoverbuggy(Clone)","damage":0.25,"hp":4.25,"attacker":"Assault Cannon"}},{"Timestamp":84.98772,"Name":"UnitDamage","Data":{"unit":"Hoverbuggy(Clone)","damage":0.25,"hp":4.0,"attacker":"Assault Cannon"}},{"Timestamp":85.15392,"Name":"UnitDamage","Data":{"unit":"Hoverbuggy(Clone)","damage":0.25,"hp":3.75,"attacker":"Assault Cannon"}},{"Timestamp":85.16426,"Name":"UnitDamage","Data":{"unit":"Hoverbuggy(Clone)","damage":0.25,"hp":3.5,"attacker":"Assault Cannon"}},{"Timestamp":85.2070541,"Name":"UnitDamage","Data":{"unit":"Hoverbuggy(Clone)","damage":0.25,"hp":3.25,"attacker":"Assault Cannon"}},{"Timestamp":85.23222,"Name":"UnitDamage","Data":{"unit":"Hoverbuggy(Clone)","damage":0.25,"hp":3.0,"attacker":"Assault Cannon"}},{"Timestamp":85.24389,"Name":"UnitDamage","Data":{"unit":"Hoverbuggy(Clone)","damage":0.25,"hp":2.75,"attacker":"Assault Cannon"}},{"Timestamp":85.24392,"Name":"UnitDamage","Data":{"unit":"Hoverbuggy(Clone)","damage":0.25,"hp":2.5,"attacker":"Assault Cannon"}},{"Timestamp":85.3572845,"Name":"UnitDamage","Data":{"unit":"Hoverbuggy(Clone)","damage":0.25,"hp":2.25,"attacker":"Assault Cannon"}},{"Timestamp":85.40354,"Name":"UnitSpawn","Data":{"unitSpawned":"Hovertank","unitCount":37}},{"Timestamp":85.40364,"Name":"UnitDamage","Data":{"unit":"Hoverbuggy(Clone)","damage":0.25,"hp":2.0,"attacker":"Assault Cannon"}},{"Timestamp":85.41697,"Name":"UnitDamage","Data":{"unit":"Hoverbuggy(Clone)","damage":0.25,"hp":1.75,"attacker":"Assault Cannon"}},{"Timestamp":85.41701,"Name":"UnitDamage","Data":{"unit":"Hoverbuggy(Clone)","damage":0.25,"hp":1.5,"attacker":"Assault Cannon"}},{"Timestamp":85.4607849,"Name":"UnitDamage","Data":{"unit":"Hoverbuggy(Clone)","damage":0.25,"hp":1.25,"attacker":"Assault Cannon"}},{"Timestamp":85.48727,"Name":"UnitDamage","Data":{"unit":"Hoverbuggy(Clone)","damage":0.25,"hp":1.0,"attacker":"Assault Cannon"}},{"Timestamp":85.49688,"Name":"UnitDamage","Data":{"unit":"Hoverbuggy(Clone)","damage":0.25,"hp":0.75,"attacker":"Assault Cannon"}},{"Timestamp":85.49692,"Name":"UnitDamage","Data":{"unit":"Hoverbuggy(Clone)","damage":0.25,"hp":0.5,"attacker":"Assault Cannon"}},{"Timestamp":85.60747,"Name":"UnitDamage","Data":{"unit":"Hoverbuggy(Clone)","damage":0.25,"hp":0.25,"attacker":"Assault Cannon"}},{"Timestamp":85.60748,"Name":"UnitDeath","Data":{"unit":"Hoverbuggy(Clone)","overkillDamage":0.0,"killTower":"Assault Cannon"}},{"Timestamp":85.65768,"Name":"UnitDamage","Data":{"unit":"Hoverbuggy(Clone)","damage":0.25,"hp":0.0,"attacker":"Assault Cannon"}},{"Timestamp":85.69915,"Name":"UnitDamage","Data":{"unit":"Hoverbuggy(Clone)","damage":0.25,"hp":0.0,"attacker":"Assault Cannon"}},{"Timestamp":85.69919,"Name":"UnitDamage","Data":{"unit":"Hoverbuggy(Clone)","damage":0.25,"hp":0.0,"attacker":"Assault Cannon"}},{"Timestamp":86.6821,"Name":"UnitDamage","Data":{"unit":"Hovertank(Clone)","damage":12.0,"hp":35.0,"attacker":"Plasma Lance"}},{"Timestamp":87.40344,"Name":"UnitSpawn","Data":{"unitSpawned":"Hovercopter","unitCount":38}},{"Timestamp":87.87041,"Name":"UnitDamage","Data":{"unit":"Hovertank(Clone)","damage":12.0,"hp":23.0,"attacker":"Plasma Lance"}},{"Timestamp":87.94048,"Name":"UnitDamage","Data":{"unit":"Hovertank(Clone)","damage":0.25,"hp":11.0,"attacker":"Assault Cannon"}},{"Timestamp":88.04087,"Name":"UnitDamage","Data":{"unit":"Hovertank(Clone)","damage":12.0,"hp":10.75,"attacker":"Plasma Lance"}},{"Timestamp":88.04089,"Name":"UnitDeath","Data":{"unit":"Hovertank(Clone)","overkillDamage":1.25,"killTower":"Plasma Lance"}},{"Timestamp":88.31937,"Name":"TowerBuilding","Data":{"tower":"Rocket Platform","X":1,"Y":1}},{"Timestamp":88.71486,"Name":"UnitDamage","Data":{"unit":"Hovercopter(Clone)","damage":0.25,"hp":16.0,"attacker":"Assault Cannon"}},{"Timestamp":88.96637,"Name":"UnitDamage","Data":{"unit":"Hovercopter(Clone)","damage":0.25,"hp":15.75,"attacker":"Assault Cannon"}},{"Timestamp":88.9897842,"Name":"Economy","Data":{"team":"Defender","currency":0.0,"income":0.0}},{"Timestamp":88.98979,"Name":"Economy","Data":{"team":"Attacker","currency":67.0,"income":63.0}},{"Timestamp":89.01,"Name":"UnitDamage","Data":{"unit":"Hovercopter(Clone)","damage":0.25,"hp":15.5,"attacker":"Assault Cannon"}},{"Timestamp":89.09078,"Name":"UnitDamage","Data":{"unit":"Hovercopter(Clone)","damage":0.25,"hp":15.25,"attacker":"Assault Cannon"}},{"Timestamp":89.2216949,"Name":"UnitDamage","Data":{"unit":"Hovercopter(Clone)","damage":0.25,"hp":15.0,"attacker":"Assault Cannon"}},{"Timestamp":89.27125,"Name":"UnitDamage","Data":{"unit":"Hovercopter(Clone)","damage":0.25,"hp":14.75,"attacker":"Assault Cannon"}},{"Timestamp":89.34354,"Name":"UnitDamage","Data":{"unit":"Hovercopter(Clone)","damage":0.25,"hp":14.5,"attacker":"Assault Cannon"}},{"Timestamp":89.3751,"Name":"UnitDamage","Data":{"unit":"Hovercopter(Clone)","damage":0.25,"hp":14.25,"attacker":"Assault Cannon"}},{"Timestamp":89.40707,"Name":"UnitSpawn","Data":{"unitSpawned":"Hoverbuggy","unitCount":39}},{"Timestamp":89.48703,"Name":"UnitDamage","Data":{"unit":"Hovercopter(Clone)","damage":0.25,"hp":14.0,"attacker":"Assault Cannon"}},{"Timestamp":89.52144,"Name":"UnitDamage","Data":{"unit":"Hovercopter(Clone)","damage":0.25,"hp":13.75,"attacker":"Assault Cannon"}},{"Timestamp":89.60641,"Name":"UnitDamage","Data":{"unit":"Hovercopter(Clone)","damage":0.25,"hp":13.5,"attacker":"Assault Cannon"}},{"Timestamp":89.62484,"Name":"UnitDamage","Data":{"unit":"Hovercopter(Clone)","damage":0.25,"hp":13.25,"attacker":"Assault Cannon"}},{"Timestamp":89.7239151,"Name":"UnitDamage","Data":{"unit":"Hovercopter(Clone)","damage":0.25,"hp":13.0,"attacker":"Assault Cannon"}},{"Timestamp":89.7726746,"Name":"UnitDamage","Data":{"unit":"Hovercopter(Clone)","damage":0.25,"hp":12.75,"attacker":"Assault Cannon"}},{"Timestamp":89.7773,"Name":"UnitDamage","Data":{"unit":"Hovercopter(Clone)","damage":0.25,"hp":12.5,"attacker":"Assault Cannon"}},{"Timestamp":89.86091,"Name":"UnitDamage","Data":{"unit":"Hovercopter(Clone)","damage":0.25,"hp":12.25,"attacker":"Assault Cannon"}},{"Timestamp":89.87283,"Name":"UnitDamage","Data":{"unit":"Hovercopter(Clone)","damage":0.25,"hp":12.0,"attacker":"Assault Cannon"}},{"Timestamp":89.9793549,"Name":"UnitDamage","Data":{"unit":"Hovercopter(Clone)","damage":0.25,"hp":11.75,"attacker":"Assault Cannon"}},{"Timestamp":90.01001,"Name":"UnitDamage","Data":{"unit":"Hovercopter(Clone)","damage":12.0,"hp":11.5,"attacker":"Plasma Lance"}},{"Timestamp":90.010025,"Name":"UnitDeath","Data":{"unit":"Hovercopter(Clone)","overkillDamage":0.5,"killTower":"Plasma Lance"}},{"Timestamp":90.02214,"Name":"UnitDamage","Data":{"unit":"Hovercopter(Clone)","damage":0.25,"hp":0.0,"attacker":"Assault Cannon"}},{"Timestamp":90.0271149,"Name":"UnitDamage","Data":{"unit":"Hovercopter(Clone)","damage":0.25,"hp":0.0,"attacker":"Assault Cannon"}},{"Timestamp":90.04104,"Name":"UnitDamage","Data":{"unit":"Hovercopter(Clone)","damage":0.25,"hp":0.0,"attacker":"Assault Cannon"}},{"Timestamp":90.11037,"Name":"UnitDamage","Data":{"unit":"Hovercopter(Clone)","damage":0.25,"hp":0.0,"attacker":"Assault Cannon"}},{"Timestamp":90.33076,"Name":"UnitDamage","Data":{"unit":"Hoverbuggy(Clone)","damage":1.5,"hp":6.0,"attacker":"Rocket Platform"}},{"Timestamp":90.33144,"Name":"UnitDamage","Data":{"unit":"Hoverbuggy(Clone)","damage":3.0,"hp":4.5,"attacker":"Rocket Platform"}},{"Timestamp":90.49758,"Name":"UnitDamage","Data":{"unit":"Hoverbuggy(Clone)","damage":0.25,"hp":1.5,"attacker":"Assault Cannon"}},{"Timestamp":90.6957,"Name":"UnitDamage","Data":{"unit":"Hoverbuggy(Clone)","damage":0.25,"hp":1.25,"attacker":"Assault Cannon"}},{"Timestamp":90.7418442,"Name":"UnitDamage","Data":{"unit":"Hoverbuggy(Clone)","damage":0.25,"hp":1.0,"attacker":"Assault Cannon"}},{"Timestamp":90.75667,"Name":"UnitDamage","Data":{"unit":"Hoverbuggy(Clone)","damage":0.25,"hp":0.75,"attacker":"Assault Cannon"}},{"Timestamp":90.90907,"Name":"UnitDamage","Data":{"unit":"Hoverbuggy(Clone)","damage":0.25,"hp":0.5,"attacker":"Assault Cannon"}},{"Timestamp":90.94733,"Name":"UnitDamage","Data":{"unit":"Hoverbuggy(Clone)","damage":0.25,"hp":0.25,"attacker":"Assault Cannon"}},{"Timestamp":90.94734,"Name":"UnitDeath","Data":{"unit":"Hoverbuggy(Clone)","overkillDamage":0.0,"killTower":"Assault Cannon"}},{"Timestamp":91.00443,"Name":"UnitDamage","Data":{"unit":"Hoverbuggy(Clone)","damage":0.25,"hp":0.0,"attacker":"Assault Cannon"}},{"Timestamp":91.00446,"Name":"UnitDamage","Data":{"unit":"Hoverbuggy(Clone)","damage":0.25,"hp":0.0,"attacker":"Assault Cannon"}},{"Timestamp":91.4126358,"Name":"UnitSpawn","Data":{"unitSpawned":"Hoverbuggy","unitCount":40}},{"Timestamp":91.71876,"Name":"UnitDamage","Data":{"unit":"Hoverbuggy(Clone)","damage":12.0,"hp":6.0,"attacker":"Plasma Lance"}},{"Timestamp":91.71877,"Name":"UnitDeath","Data":{"unit":"Hoverbuggy(Clone)","overkillDamage":6.0,"killTower":"Plasma Lance"}},{"Timestamp":93.41536,"Name":"UnitSpawn","Data":{"unitSpawned":"Hoverbuggy","unitCount":41}},{"Timestamp":93.81717,"Name":"UnitDamage","Data":{"unit":"Hoverbuggy(Clone)","damage":12.0,"hp":6.0,"attacker":"Plasma Lance"}},{"Timestamp":93.8171844,"Name":"UnitDeath","Data":{"unit":"Hoverbuggy(Clone)","overkillDamage":6.0,"killTower":"Plasma Lance"}},{"Timestamp":93.9929,"Name":"Economy","Data":{"team":"Defender","currency":5.0,"income":0.0}},{"Timestamp":93.9929047,"Name":"Economy","Data":{"team":"Attacker","currency":63.0,"income":63.0}},{"Timestamp":95.422554,"Name":"UnitSpawn","Data":{"unitSpawned":"Hoverbuggy","unitCount":42}},{"Timestamp":95.69713,"Name":"UnitDamage","Data":{"unit":"Hoverbuggy(Clone)","damage":12.0,"hp":6.0,"attacker":"Plasma Lance"}},{"Timestamp":95.69714,"Name":"UnitDeath","Data":{"unit":"Hoverbuggy(Clone)","overkillDamage":6.0,"killTower":"Plasma Lance"}},{"Timestamp":97.4236,"Name":"UnitSpawn","Data":{"unitSpawned":"Hoverbuggy","unitCount":43}},{"Timestamp":98.10421,"Name":"UnitDamage","Data":{"unit":"Hoverbuggy(Clone)","damage":12.0,"hp":6.0,"attacker":"Plasma Lance"}},{"Timestamp":98.10423,"Name":"UnitDeath","Data":{"unit":"Hoverbuggy(Clone)","overkillDamage":6.0,"killTower":"Plasma Lance"}},{"Timestamp":98.9958649,"Name":"Economy","Data":{"team":"Defender","currency":7.0,"income":0.0}},{"Timestamp":98.99587,"Name":"Economy","Data":{"team":"Attacker","currency":66.0,"income":63.0}},{"Timestamp":99.42859,"Name":"UnitSpawn","Data":{"unitSpawned":"Hovercopter","unitCount":44}},{"Timestamp":99.6898,"Name":"UnitDamage","Data":{"unit":"Hovercopter(Clone)","damage":12.0,"hp":16.0,"attacker":"Plasma Lance"}},{"Timestamp":100.6411,"Name":"UnitDamage","Data":{"unit":"Hovercopter(Clone)","damage":0.25,"hp":4.0,"attacker":"Assault Cannon"}},{"Timestamp":100.743233,"Name":"UnitDamage","Data":{"unit":"Hovercopter(Clone)","damage":12.0,"hp":3.75,"attacker":"Plasma Lance"}},{"Timestamp":100.74324,"Name":"UnitDeath","Data":{"unit":"Hovercopter(Clone)","overkillDamage":8.25,"killTower":"Plasma Lance"}},{"Timestamp":101.430656,"Name":"UnitSpawn","Data":{"unitSpawned":"Hovercopter","unitCount":45}},{"Timestamp":101.83239,"Name":"UnitDamage","Data":{"unit":"Hovercopter(Clone)","damage":12.0,"hp":16.0,"attacker":"Plasma Lance"}},{"Timestamp":102.73719,"Name":"UnitDamage","Data":{"unit":"Hovercopter(Clone)","damage":0.25,"hp":4.0,"attacker":"Assault Cannon"}},{"Timestamp":102.989441,"Name":"UnitDamage","Data":{"unit":"Hovercopter(Clone)","damage":0.25,"hp":3.75,"attacker":"Assault Cannon"}},{"Timestamp":103.013779,"Name":"UnitDamage","Data":{"unit":"Hovercopter(Clone)","damage":0.25,"hp":3.5,"attacker":"Assault Cannon"}},{"Timestamp":103.024231,"Name":"UnitDamage","Data":{"unit":"Hovercopter(Clone)","damage":12.0,"hp":3.25,"attacker":"Plasma Lance"}},{"Timestamp":103.024246,"Name":"UnitDeath","Data":{"unit":"Hovercopter(Clone)","overkillDamage":8.75,"killTower":"Plasma Lance"}},{"Timestamp":103.025,"Name":"GameEnd","Data":{"winner":1}}]